Workbook

Sheet README
A1: CHATEAU IN THE WOODS | 4020 Monaco Drive, Indianapolis, IN 46220 | 118 Units
A2: Five-Year Cash Flow Model — Read Me, Deliverable Index & Material Assumptions
A3: Blue = hardcoded input / lever · Black = formula · Green = link to another sheet · Yellow fill = key assumption
A5: HOW THIS MODEL WORKS
A6: Single source of drivers | B6: Every economic assumption lives on the 'Assumptions' tab. All projection cells are formulas; changing a driver recalculates the model end-to-end, including the returns and both sensitivity grids.
A7: Model periodicity | B7: Annual (Year 1 – Year 5) operating model, driven by a 60-month renovation / downtime schedule on the 'Reno Schedule' tab. Month 1 = August 2026 (rent roll is dated 07/01/2026).
A8: Revenue engine | B8: Gross potential rent is built unit-by-unit from the 07/01/2026 rent roll: classic units carry in-place market rent, renovated units carry market rent plus the renovation premium, and units convert as the renovation schedule completes them.
A9: Data hierarchy | B9: Per the case instructions, the Excel rent roll and T-12 govern wherever they conflict with the Offering Memorandum. The OM is used only for facts the Excel files do not contain (unit W/D inventory, rent comps, tax analysis, physical condition, other-income policy detail).
A10: Capital funding convention | B10: All renovation and property capital is funded at closing through Sources & Uses (65% loan / 35% equity). Annual cash flow therefore deducts interest and replacement reserves only, and does not double-count capex. This is conservative — it puts the full equity out on day one with no timing benefit.
A12: TAB INDEX
A13: Assumptions | B13: All inputs and levers. Purchase price, growth, renovation scope, expenses, debt, exit.
A14: Rent Roll | B14: All 118 units from the 07/01/2026 rent roll, with case status rules and per-unit renovation scope applied.
A15: Unit Mix | B15: Floor-plan roll-up: in-place market rents, W/D inventory, renovation cost and premium, renovated rents.
A16: T-12 Recast | B16: T-12 (Feb-25 to Jan-26) actuals mapped to underwriting line items, with the Year-1 underwritten figure and variance.
A17: Other Income | B17: Line-by-line other-income build off T-12 actuals plus the identified ancillary upside, with implementation ramps.
A18: Capex Budget | B18: Non-unit capital: deferred maintenance, building systems and amenity scope, phased by year.
A19: Reno Schedule | B19: 60-month renovation schedule: units completed, capex spend, and renovation downtime vacancy.
A20: Annual Model | B20: The five-year cash flow: revenue build, operating expenses, NOI, capital and cash flow to equity.
A21: Returns | B21: Sources & Uses, debt, exit valuation, unlevered and levered IRR / equity multiple / cash-on-cash.
A22: Sensitivities | B22: Live grids: purchase price × exit cap (IRR and multiple) and renovation premium × exit cap.
A23: DD Questions | B23: Diligence request list, with the placeholder answer assumed in this model for each open item.
A25: MATERIAL ASSUMPTIONS — NOT PROVIDED IN THE CASE MATERIALS
A26: Item | B26: Assumption and basis
A27: Purchase price / basis | B27: $14,200,000 ($120,339/unit, $105.68/SF). The case does not state a price. Derived from the OM cover: a 6.9% Year-1 cap rate on CBRE's $980,838 Acquisition Forecast NOI implies $14.2mm, and 7.3% on the $1,034,543 Upgrade Forecast NOI implies $14.17mm. Treated as a lever — see the price sensitivity.
A28: Renovation scope and premium | B28: Comprehensive interior renovation of all 118 units: $13,000/unit for cabinets, counters, LVP flooring, appliances, lighting, plumbing fixtures, hardware and paint, at a $125/month premium. Plus $5,000/unit (per case instruction) to add hookups and a washer/dryer in the 65 units without one, at an incremental $75/month. Blended $15,754/unit at a $166/month premium = 12.7% return on cost.
A29: Renovated rent support | B29: Renovated rents of $1,250 (1x1) to $1,725 (3x2) sit inside the OM rent comp set. Avalon Lake (1974, same vintage, Graham Rd & Binford) achieves $1,178 / $1,655 / $1,834 for 1/2/3-bedrooms; submarket averages are $1,044 / $1,305 / $1,597. CBRE's own light-touch Upgrade Forecast is $1,094-$1,631 with a $50 premium and $1,375 on the Verdun with a W/D added.
A30: Renovation pace and downtime | B30: 5 units per month beginning month 3, completing all 118 units in month 26. Consistent with natural turnover (T-12 physical occupancy 93.2% implies roughly 55-60 turns a year). 14 days of incremental downtime per renovated unit over and above a normal turn.
A31: Market rent growth | B31: 3.0% per year. Above CBRE's 1.5%+1.5% two-step rollover assumption for 2026 and consistent with long-run Indianapolis Class B/C performance. Applied on a mid-year convention.
A32: Real estate taxes | B32: $140,000 in Year 1 (CBRE 2025-pay-2026 estimate with the SB-1 deduction is $135,374), stepping to $170,000 in Year 2 and $210,000 by Year 5. Indiana reassesses on sale; the OM's own comp study shows assessed value averaging 69% of sale price and rising 6.2% a year after a trade. THIS IS THE SINGLE LARGEST UNDERWRITING JUDGEMENT ON THE EXPENSE SIDE — see the DD Questions tab.
A33: Insurance | B33: $95,000 in Year 1 ($805/unit) growing 5%, versus $94,611 T-12 actual and CBRE's $88,326 forecast. No current loss run or bindable quote was provided.
A34: Bad debt | B34: 1.50% of GPR in Year 1 falling to 1.00% by Year 4. The T-12 shows $28,229 of gross bad debt against $19,050 of collections (net $9,179, 0.5%), but write-offs are accelerating (Jan-26 alone was $5,670) and the rent roll carries 4 units in eviction and 8 on notice.
A35: Exit | B35: 6.75% cap rate on forward (Year 6) NOI, 1.5% cost of sale, at the end of Year 5. Fifteen basis points inside the 6.90% going-in cap, reflecting a fully renovated asset with in-unit laundry throughout versus the classic condition being acquired.
A36: Debt | B36: 65% loan-to-cost on price plus all capital, 5.85% fixed, interest-only, 5-year term, 1% origination. Sized to a 10.4% Year-1 debt yield and a 1.38x Year-1 DSCR. No financing terms were provided.
A37: Excluded upside | B37: Not underwritten: converting the Building 4042 maintenance storage into two additional units, and converting 9 carports to garages. Both are real but return roughly 5-10% on cost, below the interior programme, and neither is needed for the recommendation.
A39: CONFLICTS BETWEEN SOURCES — AND HOW THEY WERE RESOLVED
A40: In-unit washer/dryer count | B40: The OM says '78 out of 118 units have a full size or stackable washer/dryer' but then lists only 53 side-by-side plus 1 stackable = 54, and its own floor-plan and building-mix schedules foot to 54 units with 'WD' in the unit code. The rent roll shows 53 units in a 'w/ WD' unit type (Rhone 15, Roman 4, Cabernet 4, Brunswick 30). Per the data hierarchy the rent roll governs: 53 units have laundry, 65 do not and carry the $5,000 addition. This is a confirmatory diligence item.
A41: Bordeaux washer/dryer unit | B41: The OM identifies one Bordeaux (4017-D) with a stackable washer/dryer at a $1,307 market rent. The rent roll shows all 25 Bordeaux units at a $1,260 market rent in a single 'Bordeaux' unit type. The rent roll governs, so 4017-D is underwritten as needing the $5,000 addition — conservative by $5,000.
A42: Market rents | B42: OM floor-plan mix (dated 09/08/2025) shows $1,044 / $1,109 / $1,174 / $1,343 / $1,212 / $1,257 / $1,581. The 07/01/2026 rent roll shows $1,050 / $1,125 / $1,165 / $1,350 / $1,250 / $1,260 / $1,600. The rent roll governs; it is also nine months newer.
A43: Occupancy | B43: The OM shows 105 occupied / 13 vacant as of 09/08/2025. The 07/01/2026 rent roll shows 114 occupied / 4 vacant (96.6%) after applying the case rules that 'Notice' and 'Evict' count as occupied. The rent roll governs.
A44: Trailing twelve months | B44: The OM's T-12 is August 2024 - July 2025 ($1,774,433 revenue / $799,669 NOI). The Excel T-12 provided is February 2025 - January 2026 ($1,790,101 revenue / $772,374 NOI on the property's own basis). The Excel T-12 governs and is recast on the 'T-12 Recast' tab.

Sheet Assumptions
A1: CHATEAU IN THE WOODS | 4020 Monaco Drive, Indianapolis, IN 46220 | 118 Units
A2: Underwriting Assumptions & Drivers
A3: Blue = hardcoded input / lever · Black = formula · Green = link to another sheet · Yellow fill = key assumption
A5: TRANSACTION
A6: Purchase Price | B6: 14200000 | H6: No price given in the case. Implied by the OM cover: 6.9% Yr-1 cap on CBRE's $980,838 Acquisition Forecast NOI. Primary lever — see Sensitivities.
A7: Price per Unit | B7: =Assumptions!$B$6/Assumptions!$B$17 -> 120338.98
A8: Price per Net Rentable SF | B8: =Assumptions!$B$6/Assumptions!$B$18 -> 105.67756
A9: Acquisition Costs (% of price) | B9: 0.015 | H9: Title, survey, legal, third-party reports, transfer costs.
A10: Analysis Start (Month 1) | B10: 2026-08-01 | H10: Rent roll is dated 07/01/2026; assumes an August 2026 close.
A11: Hold Period (years) | B11: 5
A12: Exit Cap Rate (on Year-6 NOI) | B12: 0.0675 | H12: 15 bps inside the going-in cap: a fully renovated asset with in-unit laundry throughout trades tighter than the classic product being acquired.
A13: Cost of Sale (% of gross value) | B13: 0.015
A14: Implied Going-In Cap (our Year-1 NOI) | B14: ='Annual Model'!C50/Assumptions!$B$6 -> 0.061720258 | H14: On our underwriting, not the broker's forecast. CBRE markets a 6.9% Year-1 cap rate on its own $980,838 Acquisition Forecast NOI, which is what implies the $14.2mm price above.
A16: PROPERTY — FROM RENT ROLL 07/01/2026
A17: Total Units | B17: 118 | H17: Rent roll total row.
A18: Net Rentable Square Feet | B18: 134371 | H18: Rent roll total row; ties to the OM.
A19: Average Unit Size (SF) | B19: =Assumptions!$B$18/Assumptions!$B$17 -> 1138.7373
A20: Year Built | B20: 1974 | H20: OM Property Summary.
A21: Occupied Units at Close | B21: 114 | H21: 102 Current + 8 Notice + 4 Evict. Case rules: 'Notice' and 'Evict' are treated as Occupied.
A22: Vacant Units at Close | B22: =Assumptions!$B$17-Assumptions!$B$21 -> 4 | H22: All four are 'Vacant-Unrented'.
A23: In-Place Physical Occupancy | B23: =Assumptions!$B$21/Assumptions!$B$17 -> 0.96610169
A24: In-Place Market Rent ($/month) | B24: ='Unit Mix'!$D$16 -> 153435
A25: In-Place Actual Rent ($/month) | B25: 144804.03 | H25: Rent roll total row. Occupied units only.
A26: In-Place Loss-to-Lease (occupied units) | B26: =1-Assumptions!$B$25/(Assumptions!$B$24-'Unit Mix'!$D$20) -> 0.022023908
A27: Units WITH In-Unit Washer/Dryer | B27: 53 | H27: Rent roll unit types containing 'w/ WD': Rhone 15, Roman 4, Cabernet 4, Brunswick 30.
A28: Units WITHOUT In-Unit Washer/Dryer | B28: =Assumptions!$B$17-Assumptions!$B$27 -> 65 | H28: Abbey 15, Verdun 25, Bordeaux 25. Each carries the $5,000 addition per the case instructions.
A30: RENOVATION PROGRAMME
A31: Renovation Start (month of hold) | B31: 3 | H31: Months 1-2 for permitting, GC mobilisation, mock-up units and leasing the 4 in-place vacants.
A32: Units Renovated per Month | B32: 5 | H32: 60/year against roughly 55-60 natural turns a year at 93% occupancy — renovations happen on the turn, not by forcing residents out. Completes all 118 units in month 26.
A33: Interior Renovation Cost / Unit | B33: 13000 | H33: Cabinets and counters, LVP flooring, black appliances, lighting and plumbing fixtures, hardware, full paint. Indianapolis classic-to-renovated scope on units last rehabbed in 2006.
A34: W/D Addition Cost / Unit (65 units) | B34: 5000 | H34: PRESCRIBED BY THE CASE: hookups plus the washer and dryer for every unit that does not have one.
A35: Blended Renovation Cost / Unit | B35: =(Assumptions!$B$27*Assumptions!$B$33+Assumptions!$B$28*(Assumptions!$B$33+Assumptions!$B$34))/Assumptions!$B$17 -> 15754.237
A36: Total Renovation Capital | B36: =Assumptions!$B$35*Assumptions!$B$17 -> 1859000
A37: Interior Renovation Premium ($/month) | B37: 125 | H37: All 118 units. Against CBRE's $50 light-touch premium; our scope is materially deeper.
A38: W/D Addition Premium ($/month) | B38: 75 | H38: Incremental, on the 65 units gaining laundry. CBRE forecasts $163 total on the Verdun for a light touch plus a W/D, versus our $200.
A39: Blended Premium / Unit ($/month) | B39: =(Assumptions!$B$27*Assumptions!$B$37+Assumptions!$B$28*(Assumptions!$B$37+Assumptions!$B$38))/Assumptions!$B$17 -> 166.31356
A40: Return on Renovation Cost | B40: =Assumptions!$B$39*12/Assumptions!$B$35 -> 0.12668101
A41: Incremental Downtime per Unit (days) | B41: 14 | H41: Over and above a normal turn. Renovation is executed inside the vacancy window.
A42: Capex Contingency (% of all capital) | B42: 0.08
A44: REVENUE DRIVERS
C45: Year 1 | D45: Year 2 | E45: Year 3 | F45: Year 4 | G45: Year 5
A46: Market Rent Growth | C46: 0.03 | D46: 0.03 | E46: 0.03 | F46: 0.03 | G46: 0.03 | H46: Long-run Indianapolis Class B/C. CBRE's rollover analysis uses 1.5% in 3/26 plus 1.5% in 6/26.
A47: Loss to Lease (% of GPR) | C47: 0.022 | D47: 0.02 | E47: 0.0175 | F47: 0.015 | G47: 0.015 | H47: 2.2% in place today. Burns down as the renovation programme resets leases to market.
A48: Operating Physical Vacancy | C48: 0.05 | D48: 0.05 | E48: 0.05 | F48: 0.05 | G48: 0.05 | H48: T-12 actual physical vacancy is 6.8%; CBRE forecasts 5.0% stabilised. Renovation downtime is added separately from the Reno Schedule.
A49: Concessions (% of GPR) | C49: 0.0075 | D49: 0.0075 | E49: 0.005 | F49: 0.005 | G49: 0.005 | H49: T-12 actual 0.5% and rising in recent months. Elevated while renovated units are first leased.
A50: Bad Debt (% of GPR) | C50: 0.015 | D50: 0.0125 | E50: 0.0125 | F50: 0.01 | G50: 0.01 | H50: T-12 net is 0.5% ($28,229 written off against $19,050 collected) but gross write-offs are accelerating and 4 units are in eviction with 8 on notice.
A51: Other Income Growth | C51: 0.03 | D51: 0.03 | E51: 0.03 | F51: 0.03 | G51: 0.03
A53: OPERATING EXPENSES — YEAR 1 AND ANNUAL GROWTH
B54: Year 1 $ | C54: Growth | H54: Basis
A55: Payroll | B55: 235000 | C55: 0.035 | H55: T-12 $227,969; CBRE forecast $229,021 for 3.5 FTE. We add a second maintenance technician to execute 5 renovations a month.
A56: Property Management Fee (% of EGR) | B56: 0.04 | H56: T-12 effective 3.5%; CBRE forecast 4.0%. Third-party market rate at this size.
A57: Marketing & Advertising | B57: 28000 | C57: 0.03 | H57: T-12 $26,399. Increased for renovated-unit lease-up.
A58: General & Administrative | B58: 50000 | C58: 0.03 | H58: T-12 $62,887 including $17,528 of legal and $14,730 of tax/audit concentrated in Dec-Jan (likely sale-related). CBRE forecast $42,209. Underwritten between the two.
A59: Bulk Internet (net expense) | B59: 39577 | C59: 0.03 | H59: $27.95/unit/month fully stabilised under the 7-year Comcast contract signed May 2025. T-12 shows only $11,068 because the contract is still ramping. Residents are billed $49 — see Other Income.
A60: Electricity (common + vacant) | B60: 31000 | C60: 0.03 | H60: T-12 $30,320.
A61: Gas (central hot water + common) | B61: 16000 | C61: 0.03 | H61: T-12 $15,330.
A62: Water & Sewer | B62: 90000 | C62: 0.04 | H62: T-12 $86,421. 85% is recovered from residents — see Other Income.
A63: Repairs & Maintenance (incl. turns) | B63: 255000 | C63: 0.03 | H63: T-12 $250,935 ($2,127/unit) including $42,921 of turnover cost; CBRE forecast $247,656. No post-renovation savings credited.
A64: Insurance | B64: 95000 | C64: 0.05 | H64: T-12 $94,611 ($802/unit); CBRE forecast $88,326. No loss run or bindable quote provided.
C65: Year 1 | D65: Year 2 | E65: Year 3 | F65: Year 4 | G65: Year 5
A66: Real Estate Taxes | C66: 140000 | D66: 170000 | E66: 190000 | F66: 200000 | G66: 210000 | H66: CBRE 2025-pay-2026 estimate with the SB-1 deduction is $135,374 (T-12 $149,677). Indiana reassesses on sale; the OM's own comp study shows AV averaging 69% of sale price and growing 6.2% a year post-trade. Largest single expense judgement.
A67: Replacement Reserves ($/unit/year) | B67: 300 | H67: Lender-standard for 1974 vintage. Below NOI. Grows with Other Income growth.
A69: DEBT
A70: Maximum Loan to Cost | B70: 0.65 | H70: Value-add / bridge structure with a capital facility.
A71: Minimum Debt Yield (Year-1 NOI / loan) | B71: 0.08 | H71: Lender sizing test. Binding constraint at the base-case price — see Returns.
A72: Minimum DSCR (Year-1) | B72: 1.25 | H72: Lender sizing test on an interest-only structure.
A73: Interest Rate (fixed, interest-only) | B73: 0.0585 | H73: No terms provided. Approximates mid-2026 agency pricing on a 5-year interest-only structure.
A74: Origination Fee (% of loan) | B74: 0.01
A75: Other Financing Costs | B75: 100000 | H75: Lender legal, appraisal, engineering, cap-ex escrow set-up, rate-lock.

Sheet Rent Roll
A1: CHATEAU IN THE WOODS | 4020 Monaco Drive, Indianapolis, IN 46220 | 118 Units
A2: Rent Roll as of 07/01/2026 — with case status rules and per-unit renovation scope
A3: Blue = hardcoded input / lever · Black = formula · Green = link to another sheet · Yellow fill = key assumption
A5: Unit | B5: BD/BA | C5: Unit Type | D5: SF | E5: RR Status | F5: UW Status | G5: Market Rent | H5: In-Place Rent | I5: Loss to Lease | J5: Lease From | K5: Lease To | L5: In-Unit W/D | M5: Interior Reno $ | N5: W/D Add $ | O5: Total Reno $ | P5: Renovated Mkt Rent
A6: 4001-A | B6: 1/1.00 | C6: Rhone w/ WD | D6: 712 | E6: Current | F6: Occupied | G6: 1125 | H6: 1109 | I6: =IF(F6="Vacant",0,H6-G6) -> -16 | J6: 45590 | K6: 46319 | L6: Yes | M6: =Assumptions!$B$33 -> 13000 | N6: =IF(L6="No",Assumptions!$B$34,0) -> 0 | O6: =M6+N6 -> 13000 | P6: =G6+Assumptions!$B$37+IF(L6="No",Assumptions!$B$38,0) -> 1250
A7: 4001-C | B7: 1/1.00 | C7: Rhone w/ WD | D7: 712 | E7: Current | F7: Occupied | G7: 1125 | H7: 1094 | I7: =IF(F7="Vacant",0,H7-G7) -> -31 | J7: 44638 | K7: 46463 | L7: Yes | M7: =Assumptions!$B$33 -> 13000 | N7: =IF(L7="No",Assumptions!$B$34,0) -> 0 | O7: =M7+N7 -> 13000 | P7: =G7+Assumptions!$B$37+IF(L7="No",Assumptions!$B$38,0) -> 1250
A8: 4001-E | B8: 1/1.00 | C8: Rhone w/ WD | D8: 712 | E8: Current | F8: Occupied | G8: 1125 | H8: 1109 | I8: =IF(F8="Vacant",0,H8-G8) -> -16 | J8: 46173 | K8: 46568 | L8: Yes | M8: =Assumptions!$B$33 -> 13000 | N8: =IF(L8="No",Assumptions!$B$34,0) -> 0 | O8: =M8+N8 -> 13000 | P8: =G8+Assumptions!$B$37+IF(L8="No",Assumptions!$B$38,0) -> 1250
A9: 4002-B | B9: 1/1.00 | C9: Abbey | D9: 712 | E9: Current | F9: Occupied | G9: 1050 | H9: 1044 | I9: =IF(F9="Vacant",0,H9-G9) -> -6 | J9: 46142 | K9: 46536 | L9: No | M9: =Assumptions!$B$33 -> 13000 | N9: =IF(L9="No",Assumptions!$B$34,0) -> 5000 | O9: =M9+N9 -> 18000 | P9: =G9+Assumptions!$B$37+IF(L9="No",Assumptions!$B$38,0) -> 1250
A10: 4002-D | B10: 1/1.00 | C10: Abbey | D10: 712 | E10: Current | F10: Occupied | G10: 1050 | H10: 1063 | I10: =IF(F10="Vacant",0,H10-G10) -> 13 | J10: 45474 | K10: 46568 | L10: No | M10: =Assumptions!$B$33 -> 13000 | N10: =IF(L10="No",Assumptions!$B$34,0) -> 5000 | O10: =M10+N10 -> 18000 | P10: =G10+Assumptions!$B$37+IF(L10="No",Assumptions!$B$38,0) -> 1250
A11: 4002-F | B11: 1/1.00 | C11: Abbey | D11: 712 | E11: Current | F11: Occupied | G11: 1050 | H11: 1058 | I11: =IF(F11="Vacant",0,H11-G11) -> 8 | J11: 45108 | K11: 46568 | L11: No | M11: =Assumptions!$B$33 -> 13000 | N11: =IF(L11="No",Assumptions!$B$34,0) -> 5000 | O11: =M11+N11 -> 18000 | P11: =G11+Assumptions!$B$37+IF(L11="No",Assumptions!$B$38,0) -> 1250
A12: 4005-B | B12: 1/1.00 | C12: Abbey | D12: 712 | E12: Current | F12: Occupied | G12: 1050 | H12: 994 | I12: =IF(F12="Vacant",0,H12-G12) -> -56 | J12: 45990 | K12: 46384 | L12: No | M12: =Assumptions!$B$33 -> 13000 | N12: =IF(L12="No",Assumptions!$B$34,0) -> 5000 | O12: =M12+N12 -> 18000 | P12: =G12+Assumptions!$B$37+IF(L12="No",Assumptions!$B$38,0) -> 1250
A13: 4005-D | B13: 1/1.00 | C13: Abbey | D13: 712 | E13: Current | F13: Occupied | G13: 1050 | H13: 1044 | I13: =IF(F13="Vacant",0,H13-G13) -> -6 | J13: 45590 | L13: No | M13: =Assumptions!$B$33 -> 13000 | N13: =IF(L13="No",Assumptions!$B$34,0) -> 5000 | O13: =M13+N13 -> 18000 | P13: =G13+Assumptions!$B$37+IF(L13="No",Assumptions!$B$38,0) -> 1250
A14: 4005-F | B14: 1/1.00 | C14: Abbey | D14: 712 | E14: Current | F14: Occupied | G14: 1050 | H14: 1034 | I14: =IF(F14="Vacant",0,H14-G14) -> -16 | J14: 42644 | K14: 46295 | L14: No | M14: =Assumptions!$B$33 -> 13000 | N14: =IF(L14="No",Assumptions!$B$34,0) -> 5000 | O14: =M14+N14 -> 18000 | P14: =G14+Assumptions!$B$37+IF(L14="No",Assumptions!$B$38,0) -> 1250
A15: 4006-A | B15: 1/1.00 | C15: Rhone w/ WD | D15: 712 | E15: Current | F15: Occupied | G15: 1125 | H15: 1109 | I15: =IF(F15="Vacant",0,H15-G15) -> -16 | J15: 44263 | K15: 46363 | L15: Yes | M15: =Assumptions!$B$33 -> 13000 | N15: =IF(L15="No",Assumptions!$B$34,0) -> 0 | O15: =M15+N15 -> 13000 | P15: =G15+Assumptions!$B$37+IF(L15="No",Assumptions!$B$38,0) -> 1250
A16: 4006-C | B16: 1/1.00 | C16: Rhone w/ WD | D16: 712 | E16: Current | F16: Occupied | G16: 1125 | H16: 1094 | I16: =IF(F16="Vacant",0,H16-G16) -> -31 | J16: 43896 | K16: 46451 | L16: Yes | M16: =Assumptions!$B$33 -> 13000 | N16: =IF(L16="No",Assumptions!$B$34,0) -> 0 | O16: =M16+N16 -> 13000 | P16: =G16+Assumptions!$B$37+IF(L16="No",Assumptions!$B$38,0) -> 1250
A17: 4006-E | B17: 1/1.00 | C17: Rhone w/ WD | D17: 712 | E17: Current | F17: Occupied | G17: 1125 | H17: 1099 | I17: =IF(F17="Vacant",0,H17-G17) -> -26 | J17: 45717 | K17: 46356 | L17: Yes | M17: =Assumptions!$B$33 -> 13000 | N17: =IF(L17="No",Assumptions!$B$34,0) -> 0 | O17: =M17+N17 -> 13000 | P17: =G17+Assumptions!$B$37+IF(L17="No",Assumptions!$B$38,0) -> 1250
A18: 4025-C | B18: 1/1.00 | C18: Rhone w/ WD | D18: 712 | E18: Current | F18: Occupied | G18: 1125 | H18: 999 | I18: =IF(F18="Vacant",0,H18-G18) -> -126 | J18: 45991 | K18: 46385 | L18: Yes | M18: =Assumptions!$B$33 -> 13000 | N18: =IF(L18="No",Assumptions!$B$34,0) -> 0 | O18: =M18+N18 -> 13000 | P18: =G18+Assumptions!$B$37+IF(L18="No",Assumptions!$B$38,0) -> 1250
A19: 4025-E | B19: 1/1.00 | C19: Rhone w/ WD | D19: 712 | E19: Current | F19: Occupied | G19: 1125 | H19: 1079 | I19: =IF(F19="Vacant",0,H19-G19) -> -46 | J19: 45518 | K19: 46247 | L19: Yes | M19: =Assumptions!$B$33 -> 13000 | N19: =IF(L19="No",Assumptions!$B$34,0) -> 0 | O19: =M19+N19 -> 13000 | P19: =G19+Assumptions!$B$37+IF(L19="No",Assumptions!$B$38,0) -> 1250
A20: 4029-B | B20: 1/1.00 | C20: Abbey | D20: 712 | E20: Current | F20: Occupied | G20: 1050 | H20: 1044 | I20: =IF(F20="Vacant",0,H20-G20) -> -6 | J20: 46172 | K20: 46567 | L20: No | M20: =Assumptions!$B$33 -> 13000 | N20: =IF(L20="No",Assumptions!$B$34,0) -> 5000 | O20: =M20+N20 -> 18000 | P20: =G20+Assumptions!$B$37+IF(L20="No",Assumptions!$B$38,0) -> 1250
A21: 4029-D | B21: 1/1.00 | C21: Abbey | D21: 712 | E21: Current | F21: Occupied | G21: 1050 | H21: 1044 | I21: =IF(F21="Vacant",0,H21-G21) -> -6 | J21: 45912 | K21: 46306 | L21: No | M21: =Assumptions!$B$33 -> 13000 | N21: =IF(L21="No",Assumptions!$B$34,0) -> 5000 | O21: =M21+N21 -> 18000 | P21: =G21+Assumptions!$B$37+IF(L21="No",Assumptions!$B$38,0) -> 1250
A22: 4029-F | B22: 1/1.00 | C22: Abbey | D22: 712 | E22: Current | F22: Occupied | G22: 1050 | H22: 1044 | I22: =IF(F22="Vacant",0,H22-G22) -> -6 | J22: 43847 | L22: No | M22: =Assumptions!$B$33 -> 13000 | N22: =IF(L22="No",Assumptions!$B$34,0) -> 5000 | O22: =M22+N22 -> 18000 | P22: =G22+Assumptions!$B$37+IF(L22="No",Assumptions!$B$38,0) -> 1250
A23: 4033-A | B23: 1/1.00 | C23: Rhone w/ WD | D23: 712 | E23: Current | F23: Occupied | G23: 1125 | H23: 1084 | I23: =IF(F23="Vacant",0,H23-G23) -> -41 | J23: 45531 | K23: 46260 | L23: Yes | M23: =Assumptions!$B$33 -> 13000 | N23: =IF(L23="No",Assumptions!$B$34,0) -> 0 | O23: =M23+N23 -> 13000 | P23: =G23+Assumptions!$B$37+IF(L23="No",Assumptions!$B$38,0) -> 1250
A24: 4033-C | B24: 1/1.00 | C24: Rhone w/ WD | D24: 712 | E24: Current | F24: Occupied | G24: 1125 | H24: 1109 | I24: =IF(F24="Vacant",0,H24-G24) -> -16 | J24: 46130 | K24: 46524 | L24: Yes | M24: =Assumptions!$B$33 -> 13000 | N24: =IF(L24="No",Assumptions!$B$34,0) -> 0 | O24: =M24+N24 -> 13000 | P24: =G24+Assumptions!$B$37+IF(L24="No",Assumptions!$B$38,0) -> 1250
A25: 4033-E | B25: 1/1.00 | C25: Rhone w/ WD | D25: 712 | E25: Current | F25: Occupied | G25: 1125 | H25: 1109 | I25: =IF(F25="Vacant",0,H25-G25) -> -16 | J25: 40207 | K25: 46418 | L25: Yes | M25: =Assumptions!$B$33 -> 13000 | N25: =IF(L25="No",Assumptions!$B$34,0) -> 0 | O25: =M25+N25 -> 13000 | P25: =G25+Assumptions!$B$37+IF(L25="No",Assumptions!$B$38,0) -> 1250
A26: 4034-B | B26: 1/1.00 | C26: Abbey | D26: 712 | E26: Current | F26: Occupied | G26: 1050 | H26: 1029 | I26: =IF(F26="Vacant",0,H26-G26) -> -21 | J26: 44680 | K26: 46505 | L26: No | M26: =Assumptions!$B$33 -> 13000 | N26: =IF(L26="No",Assumptions!$B$34,0) -> 5000 | O26: =M26+N26 -> 18000 | P26: =G26+Assumptions!$B$37+IF(L26="No",Assumptions!$B$38,0) -> 1250
A27: 4034-D | B27: 1/1.00 | C27: Abbey | D27: 712 | E27: Current | F27: Occupied | G27: 1050 | H27: 1044 | I27: =IF(F27="Vacant",0,H27-G27) -> -6 | J27: 45961 | K27: 46356 | L27: No | M27: =Assumptions!$B$33 -> 13000 | N27: =IF(L27="No",Assumptions!$B$34,0) -> 5000 | O27: =M27+N27 -> 18000 | P27: =G27+Assumptions!$B$37+IF(L27="No",Assumptions!$B$38,0) -> 1250
A28: 4034-F | B28: 1/1.00 | C28: Abbey | D28: 712 | E28: Current | F28: Occupied | G28: 1050 | H28: 1044 | I28: =IF(F28="Vacant",0,H28-G28) -> -6 | J28: 46105 | K28: 46500 | L28: No | M28: =Assumptions!$B$33 -> 13000 | N28: =IF(L28="No",Assumptions!$B$34,0) -> 5000 | O28: =M28+N28 -> 18000 | P28: =G28+Assumptions!$B$37+IF(L28="No",Assumptions!$B$38,0) -> 1250
A29: 4037-D | B29: 1/1.00 | C29: Abbey | D29: 712 | E29: Current | F29: Occupied | G29: 1050 | H29: 1044 | I29: =IF(F29="Vacant",0,H29-G29) -> -6 | J29: 46101 | K29: 46496 | L29: No | M29: =Assumptions!$B$33 -> 13000 | N29: =IF(L29="No",Assumptions!$B$34,0) -> 5000 | O29: =M29+N29 -> 18000 | P29: =G29+Assumptions!$B$37+IF(L29="No",Assumptions!$B$38,0) -> 1250
A30: 4037-F | B30: 1/1.00 | C30: Abbey | D30: 712 | E30: Current | F30: Occupied | G30: 1050 | H30: 1044 | I30: =IF(F30="Vacant",0,H30-G30) -> -6 | J30: 45566 | K30: 46295 | L30: No | M30: =Assumptions!$B$33 -> 13000 | N30: =IF(L30="No",Assumptions!$B$34,0) -> 5000 | O30: =M30+N30 -> 18000 | P30: =G30+Assumptions!$B$37+IF(L30="No",Assumptions!$B$38,0) -> 1250
A31: 4038-A | B31: 1/1.00 | C31: Rhone w/ WD | D31: 712 | E31: Current | F31: Occupied | G31: 1125 | H31: 1094 | I31: =IF(F31="Vacant",0,H31-G31) -> -31 | J31: 45710 | K31: 46439 | L31: Yes | M31: =Assumptions!$B$33 -> 13000 | N31: =IF(L31="No",Assumptions!$B$34,0) -> 0 | O31: =M31+N31 -> 13000 | P31: =G31+Assumptions!$B$37+IF(L31="No",Assumptions!$B$38,0) -> 1250
A32: 4038-E | B32: 1/1.00 | C32: Rhone w/ WD | D32: 712 | E32: Current | F32: Occupied | G32: 1125 | H32: 1109 | I32: =IF(F32="Vacant",0,H32-G32) -> -16 | J32: 45919 | K32: 46313 | L32: Yes | M32: =Assumptions!$B$33 -> 13000 | N32: =IF(L32="No",Assumptions!$B$34,0) -> 0 | O32: =M32+N32 -> 13000 | P32: =G32+Assumptions!$B$37+IF(L32="No",Assumptions!$B$38,0) -> 1250
A33: 4038-C | B33: 1/1.00 | C33: Rhone w/ WD | D33: 712 | E33: Evict | F33: Occupied | G33: 1125 | H33: 1109 | I33: =IF(F33="Vacant",0,H33-G33) -> -16 | J33: 46066 | K33: 46458 | L33: Yes | M33: =Assumptions!$B$33 -> 13000 | N33: =IF(L33="No",Assumptions!$B$34,0) -> 0 | O33: =M33+N33 -> 13000 | P33: =G33+Assumptions!$B$37+IF(L33="No",Assumptions!$B$38,0) -> 1250
A34: 4025-A | B34: 1/1.00 | C34: Rhone w/ WD | D34: 712 | E34: Notice-Unrented | F34: Occupied | G34: 1125 | H34: 1079 | I34: =IF(F34="Vacant",0,H34-G34) -> -46 | J34: 45506 | K34: 46235 | L34: Yes | M34: =Assumptions!$B$33 -> 13000 | N34: =IF(L34="No",Assumptions!$B$34,0) -> 0 | O34: =M34+N34 -> 13000 | P34: =G34+Assumptions!$B$37+IF(L34="No",Assumptions!$B$38,0) -> 1250
... A40: 4010-A | B40: 2/1.00 | C40: Cabernet w/ WD | D40: 1182 | E40: Current | F40: Occupied | G40: 1350 | H40: 1329 | I40: =IF(F40="Vacant",0,H40-G40) -> -21 | J40: 44708 | K40: 46533 | L40: Yes | M40: =Assumptions!$B$33 -> 13000 | N40: =IF(L40="No",Assumptions!$B$34,0) -> 0 | O40: =M40+N40 -> 13000 | P40: =G40+Assumptions!$B$37+IF(L40="No",Assumptions!$B$38,0) -> 1475
A41: 4013-A | B41: 2/1.00 | C41: Cabernet w/ WD | D41: 1182 | E41: Current | F41: Occupied | G41: 1350 | H41: 1343 | I41: =IF(F41="Vacant",0,H41-G41) -> -7 | J41: 45077 | L41: Yes | M41: =Assumptions!$B$33 -> 13000 | N41: =IF(L41="No",Assumptions!$B$34,0) -> 0 | O41: =M41+N41 -> 13000 | P41: =G41+Assumptions!$B$37+IF(L41="No",Assumptions!$B$38,0) -> 1475
A42: 4021-A | B42: 2/1.00 | C42: Cabernet w/ WD | D42: 1182 | E42: Current | F42: Occupied | G42: 1350 | H42: 1337 | I42: =IF(F42="Vacant",0,H42-G42) -> -13 | J42: 44459 | K42: 46284 | L42: Yes | M42: =Assumptions!$B$33 -> 13000 | N42: =IF(L42="No",Assumptions!$B$34,0) -> 0 | O42: =M42+N42 -> 13000 | P42: =G42+Assumptions!$B$37+IF(L42="No",Assumptions!$B$38,0) -> 1475
A43: 4045-A | B43: 2/1.00 | C43: Cabernet w/ WD | D43: 1182 | E43: Current | F43: Occupied | G43: 1350 | H43: 1343 | I43: =IF(F43="Vacant",0,H43-G43) -> -7 | J43: 46112 | K43: 46506 | L43: Yes | M43: =Assumptions!$B$33 -> 13000 | N43: =IF(L43="No",Assumptions!$B$34,0) -> 0 | O43: =M43+N43 -> 13000 | P43: =G43+Assumptions!$B$37+IF(L43="No",Assumptions!$B$38,0) -> 1475
A44: 4009-A | B44: 2/2.00 | C44: Verdun | D44: 1105 | E44: Current | F44: Occupied | G44: 1250 | H44: 1212 | I44: =IF(F44="Vacant",0,H44-G44) -> -38 | J44: 44862 | K44: 46322 | L44: No | M44: =Assumptions!$B$33 -> 13000 | N44: =IF(L44="No",Assumptions!$B$34,0) -> 5000 | O44: =M44+N44 -> 18000 | P44: =G44+Assumptions!$B$37+IF(L44="No",Assumptions!$B$38,0) -> 1450
A45: 4009-B | B45: 2/2.00 | C45: Bordeaux | D45: 1182 | E45: Current | F45: Occupied | G45: 1260 | H45: 1249 | I45: =IF(F45="Vacant",0,H45-G45) -> -11 | J45: 45233 | K45: 46328 | L45: No | M45: =Assumptions!$B$33 -> 13000 | N45: =IF(L45="No",Assumptions!$B$34,0) -> 5000 | O45: =M45+N45 -> 18000 | P45: =G45+Assumptions!$B$37+IF(L45="No",Assumptions!$B$38,0) -> 1460
A46: 4009-C | B46: 2/2.00 | C46: Verdun | D46: 1105 | E46: Current | F46: Occupied | G46: 1250 | H46: 1206 | I46: =IF(F46="Vacant",0,H46-G46) -> -44 | J46: 45768 | K46: 46497 | L46: No | M46: =Assumptions!$B$33 -> 13000 | N46: =IF(L46="No",Assumptions!$B$34,0) -> 5000 | O46: =M46+N46 -> 18000 | P46: =G46+Assumptions!$B$37+IF(L46="No",Assumptions!$B$38,0) -> 1450
A47: 4009-D | B47: 2/2.00 | C47: Bordeaux | D47: 1182 | E47: Current | F47: Occupied | G47: 1260 | H47: 1257 | I47: =IF(F47="Vacant",0,H47-G47) -> -3 | J47: 43464 | K47: 46385 | L47: No | M47: =Assumptions!$B$33 -> 13000 | N47: =IF(L47="No",Assumptions!$B$34,0) -> 5000 | O47: =M47+N47 -> 18000 | P47: =G47+Assumptions!$B$37+IF(L47="No",Assumptions!$B$38,0) -> 1460
A48: 4009-E | B48: 2/2.00 | C48: Verdun | D48: 1105 | E48: Current | F48: Occupied | G48: 1250 | H48: 1210 | I48: =IF(F48="Vacant",0,H48-G48) -> -40 | J48: 45543 | K48: 46272 | L48: No | M48: =Assumptions!$B$33 -> 13000 | N48: =IF(L48="No",Assumptions!$B$34,0) -> 5000 | O48: =M48+N48 -> 18000 | P48: =G48+Assumptions!$B$37+IF(L48="No",Assumptions!$B$38,0) -> 1450
A49: 4009-F | B49: 2/2.00 | C49: Bordeaux | D49: 1182 | E49: Current | F49: Occupied | G49: 1260 | H49: 1257 | I49: =IF(F49="Vacant",0,H49-G49) -> -3 | J49: 45443 | K49: 46202 | L49: No | M49: =Assumptions!$B$33 -> 13000 | N49: =IF(L49="No",Assumptions!$B$34,0) -> 5000 | O49: =M49+N49 -> 18000 | P49: =G49+Assumptions!$B$37+IF(L49="No",Assumptions!$B$38,0) -> 1460
A50: 4010-C | B50: 2/2.00 | C50: Bordeaux | D50: 1182 | E50: Current | F50: Occupied | G50: 1260 | H50: 1229 | I50: =IF(F50="Vacant",0,H50-G50) -> -31 | J50: 45507 | K50: 46236 | L50: No | M50: =Assumptions!$B$33 -> 13000 | N50: =IF(L50="No",Assumptions!$B$34,0) -> 5000 | O50: =M50+N50 -> 18000 | P50: =G50+Assumptions!$B$37+IF(L50="No",Assumptions!$B$38,0) -> 1460
A51: 4010-D | B51: 2/2.00 | C51: Verdun | D51: 1105 | E51: Current | F51: Occupied | G51: 1250 | H51: 1206 | I51: =IF(F51="Vacant",0,H51-G51) -> -44 | J51: 45460 | K51: 46189 | L51: No | M51: =Assumptions!$B$33 -> 13000 | N51: =IF(L51="No",Assumptions!$B$34,0) -> 5000 | O51: =M51+N51 -> 18000 | P51: =G51+Assumptions!$B$37+IF(L51="No",Assumptions!$B$38,0) -> 1450
A52: 4010-E | B52: 2/2.00 | C52: Bordeaux | D52: 1182 | E52: Current | F52: Occupied | G52: 1260 | H52: 1257 | I52: =IF(F52="Vacant",0,H52-G52) -> -3 | J52: 44918 | K52: 46370 | L52: No | M52: =Assumptions!$B$33 -> 13000 | N52: =IF(L52="No",Assumptions!$B$34,0) -> 5000 | O52: =M52+N52 -> 18000 | P52: =G52+Assumptions!$B$37+IF(L52="No",Assumptions!$B$38,0) -> 1460
A53: 4010-F | B53: 2/2.00 | C53: Verdun | D53: 1105 | E53: Current | F53: Occupied | G53: 1250 | H53: 1206 | I53: =IF(F53="Vacant",0,H53-G53) -> -44 | J53: 45108 | K53: 46203 | L53: No | M53: =Assumptions!$B$33 -> 13000 | N53: =IF(L53="No",Assumptions!$B$34,0) -> 5000 | O53: =M53+N53 -> 18000 | P53: =G53+Assumptions!$B$37+IF(L53="No",Assumptions!$B$38,0) -> 1450
... A63: 4017-B | B63: 2/2.00 | C63: Bordeaux | D63: 1182 | E63: Current | F63: Occupied | G63: 1260 | H63: 1214 | I63: =IF(F63="Vacant",0,H63-G63) -> -46 | J63: 45167 | K63: 46535 | L63: No | M63: =Assumptions!$B$33 -> 13000 | N63: =IF(L63="No",Assumptions!$B$34,0) -> 5000 | O63: =M63+N63 -> 18000 | P63: =G63+Assumptions!$B$37+IF(L63="No",Assumptions!$B$38,0) -> 1460
A64: 4017-E | B64: 2/2.00 | C64: Verdun | D64: 1105 | E64: Current | F64: Occupied | G64: 1250 | H64: 1212 | I64: =IF(F64="Vacant",0,H64-G64) -> -38 | J64: 45366 | L64: No | M64: =Assumptions!$B$33 -> 13000 | N64: =IF(L64="No",Assumptions!$B$34,0) -> 5000 | O64: =M64+N64 -> 18000 | P64: =G64+Assumptions!$B$37+IF(L64="No",Assumptions!$B$38,0) -> 1450
A65: 4017-F | B65: 2/2.00 | C65: Bordeaux | D65: 1182 | E65: Current | F65: Occupied | G65: 1260 | H65: 1257 | I65: =IF(F65="Vacant",0,H65-G65) -> -3 | J65: 46099 | K65: 46463 | L65: No | M65: =Assumptions!$B$33 -> 13000 | N65: =IF(L65="No",Assumptions!$B$34,0) -> 5000 | O65: =M65+N65 -> 18000 | P65: =G65+Assumptions!$B$37+IF(L65="No",Assumptions!$B$38,0) -> 1460
A66: 4021-C | B66: 2/2.00 | C66: Bordeaux | D66: 1182 | E66: Current | F66: Occupied | G66: 1260 | H66: 1257 | I66: =IF(F66="Vacant",0,H66-G66) -> -3 | J66: 45203 | K66: 46298 | L66: No | M66: =Assumptions!$B$33 -> 13000 | N66: =IF(L66="No",Assumptions!$B$34,0) -> 5000 | O66: =M66+N66 -> 18000 | P66: =G66+Assumptions!$B$37+IF(L66="No",Assumptions!$B$38,0) -> 1460
A67: 4021-D | B67: 2/2.00 | C67: Verdun | D67: 1105 | E67: Current | F67: Occupied | G67: 1250 | H67: 1212 | I67: =IF(F67="Vacant",0,H67-G67) -> -38 | J67: 46203 | K67: 46597 | L67: No | M67: =Assumptions!$B$33 -> 13000 | N67: =IF(L67="No",Assumptions!$B$34,0) -> 5000 | O67: =M67+N67 -> 18000 | P67: =G67+Assumptions!$B$37+IF(L67="No",Assumptions!$B$38,0) -> 1450
A68: 4021-E | B68: 2/2.00 | C68: Bordeaux | D68: 1182 | E68: Current | F68: Occupied | G68: 1260 | H68: 1257 | I68: =IF(F68="Vacant",0,H68-G68) -> -3 | J68: 45815 | K68: 46544 | L68: No | M68: =Assumptions!$B$33 -> 13000 | N68: =IF(L68="No",Assumptions!$B$34,0) -> 5000 | O68: =M68+N68 -> 18000 | P68: =G68+Assumptions!$B$37+IF(L68="No",Assumptions!$B$38,0) -> 1460
A69: 4021-F | B69: 2/2.00 | C69: Verdun | D69: 1105 | E69: Current | F69: Occupied | G69: 1250 | H69: 1212 | I69: =IF(F69="Vacant",0,H69-G69) -> -38 | J69: 45801 | K69: 46530 | L69: No | M69: =Assumptions!$B$33 -> 13000 | N69: =IF(L69="No",Assumptions!$B$34,0) -> 5000 | O69: =M69+N69 -> 18000 | P69: =G69+Assumptions!$B$37+IF(L69="No",Assumptions!$B$38,0) -> 1450
A70: 4041-A | B70: 2/2.00 | C70: Verdun | D70: 1105 | E70: Current | F70: Occupied | G70: 1250 | H70: 1212 | I70: =IF(F70="Vacant",0,H70-G70) -> -38 | J70: 44561 | K70: 46386 | L70: No | M70: =Assumptions!$B$33 -> 13000 | N70: =IF(L70="No",Assumptions!$B$34,0) -> 5000 | O70: =M70+N70 -> 18000 | P70: =G70+Assumptions!$B$37+IF(L70="No",Assumptions!$B$38,0) -> 1450
A71: 4041-B | B71: 2/2.00 | C71: Bordeaux | D71: 1182 | E71: Current | F71: Occupied | G71: 1260 | H71: 1257 | I71: =IF(F71="Vacant",0,H71-G71) -> -3 | J71: 45891 | K71: 46620 | L71: No | M71: =Assumptions!$B$33 -> 13000 | N71: =IF(L71="No",Assumptions!$B$34,0) -> 5000 | O71: =M71+N71 -> 18000 | P71: =G71+Assumptions!$B$37+IF(L71="No",Assumptions!$B$38,0) -> 1460
A72: 4041-C | B72: 2/2.00 | C72: Verdun | D72: 1105 | E72: Current | F72: Occupied | G72: 1250 | H72: 1204 | I72: =IF(F72="Vacant",0,H72-G72) -> -46 | J72: 44883 | K72: 46343 | L72: No | M72: =Assumptions!$B$33 -> 13000 | N72: =IF(L72="No",Assumptions!$B$34,0) -> 5000 | O72: =M72+N72 -> 18000 | P72: =G72+Assumptions!$B$37+IF(L72="No",Assumptions!$B$38,0) -> 1450
A73: 4041-D | B73: 2/2.00 | C73: Bordeaux | D73: 1182 | E73: Current | F73: Occupied | G73: 1260 | H73: 1242 | I73: =IF(F73="Vacant",0,H73-G73) -> -18 | J73: 45495 | K73: 46224 | L73: No | M73: =Assumptions!$B$33 -> 13000 | N73: =IF(L73="No",Assumptions!$B$34,0) -> 5000 | O73: =M73+N73 -> 18000 | P73: =G73+Assumptions!$B$37+IF(L73="No",Assumptions!$B$38,0) -> 1460
A74: 4041-F | B74: 2/2.00 | C74: Bordeaux | D74: 1182 | E74: Current | F74: Occupied | G74: 1260 | H74: 1257 | I74: =IF(F74="Vacant",0,H74-G74) -> -3 | J74: 45278 | K74: 46373 | L74: No | M74: =Assumptions!$B$33 -> 13000 | N74: =IF(L74="No",Assumptions!$B$34,0) -> 5000 | O74: =M74+N74 -> 18000 | P74: =G74+Assumptions!$B$37+IF(L74="No",Assumptions!$B$38,0) -> 1460
A75: 4042-C | B75: 2/2.00 | C75: Bordeaux | D75: 1182 | E75: Current | F75: Occupied | G75: 1260 | H75: 1257 | I75: =IF(F75="Vacant",0,H75-G75) -> -3 | J75: 45212 | K75: 46307 | L75: No | M75: =Assumptions!$B$33 -> 13000 | N75: =IF(L75="No",Assumptions!$B$34,0) -> 5000 | O75: =M75+N75 -> 18000 | P75: =G75+Assumptions!$B$37+IF(L75="No",Assumptions!$B$38,0) -> 1460
A76: 4042-D | B76: 2/2.00 | C76: Verdun | D76: 1105 | E76: Current | F76: Occupied | G76: 1250 | H76: 1194 | I76: =IF(F76="Vacant",0,H76-G76) -> -56 | J76: 44999 | K76: 46459 | L76: No | M76: =Assumptions!$B$33 -> 13000 | N76: =IF(L76="No",Assumptions!$B$34,0) -> 5000 | O76: =M76+N76 -> 18000 | P76: =G76+Assumptions!$B$37+IF(L76="No",Assumptions!$B$38,0) -> 1450
... A90: 4041-E | B90: 2/2.00 | C90: Verdun | D90: 1105 | E90: Notice-Unrented | F90: Occupied | G90: 1250 | H90: 1209 | I90: =IF(F90="Vacant",0,H90-G90) -> -41 | J90: 45606 | K90: 46335 | L90: No | M90: =Assumptions!$B$33 -> 13000 | N90: =IF(L90="No",Assumptions!$B$34,0) -> 5000 | O90: =M90+N90 -> 18000 | P90: =G90+Assumptions!$B$37+IF(L90="No",Assumptions!$B$38,0) -> 1450
A91: 4045-C | B91: 2/2.00 | C91: Bordeaux | D91: 1182 | E91: Vacant-Unrented | F91: Vacant | G91: 1260 | I91: =IF(F91="Vacant",0,H91-G91) -> 0 | L91: No | M91: =Assumptions!$B$33 -> 13000 | N91: =IF(L91="No",Assumptions!$B$34,0) -> 5000 | O91: =M91+N91 -> 18000 | P91: =G91+Assumptions!$B$37+IF(L91="No",Assumptions!$B$38,0) -> 1460
A92: 4046-A | B92: 2/2.00 | C92: Verdun | D92: 1105 | E92: Vacant-Unrented | F92: Vacant | G92: 1250 | I92: =IF(F92="Vacant",0,H92-G92) -> 0 | L92: No | M92: =Assumptions!$B$33 -> 13000 | N92: =IF(L92="No",Assumptions!$B$34,0) -> 5000 | O92: =M92+N92 -> 18000 | P92: =G92+Assumptions!$B$37+IF(L92="No",Assumptions!$B$38,0) -> 1450
A93: 4046-B | B93: 2/2.00 | C93: Bordeaux | D93: 1182 | E93: Vacant-Unrented | F93: Vacant | G93: 1260 | I93: =IF(F93="Vacant",0,H93-G93) -> 0 | L93: No | M93: =Assumptions!$B$33 -> 13000 | N93: =IF(L93="No",Assumptions!$B$34,0) -> 5000 | O93: =M93+N93 -> 18000 | P93: =G93+Assumptions!$B$37+IF(L93="No",Assumptions!$B$38,0) -> 1460
A94: 4001-B | B94: 3/2.00 | C94: Brunswick w/ WD | D94: 1590 | E94: Current | F94: Occupied | G94: 1600 | H94: 1581 | I94: =IF(F94="Vacant",0,H94-G94) -> -19 | J94: 46109 | K94: 46504 | L94: Yes | M94: =Assumptions!$B$33 -> 13000 | N94: =IF(L94="No",Assumptions!$B$34,0) -> 0 | O94: =M94+N94 -> 13000 | P94: =G94+Assumptions!$B$37+IF(L94="No",Assumptions!$B$38,0) -> 1725
A95: 4001-D | B95: 3/2.00 | C95: Brunswick w/ WD | D95: 1590 | E95: Current | F95: Occupied | G95: 1600 | H95: 1581 | I95: =IF(F95="Vacant",0,H95-G95) -> -19 | J95: 46111 | K95: 46506 | L95: Yes | M95: =Assumptions!$B$33 -> 13000 | N95: =IF(L95="No",Assumptions!$B$34,0) -> 0 | O95: =M95+N95 -> 13000 | P95: =G95+Assumptions!$B$37+IF(L95="No",Assumptions!$B$38,0) -> 1725
A96: 4001-F | B96: 3/2.00 | C96: Brunswick w/ WD | D96: 1590 | E96: Current | F96: Occupied | G96: 1600 | H96: 1557 | I96: =IF(F96="Vacant",0,H96-G96) -> -43 | J96: 45721 | K96: 46450 | L96: Yes | M96: =Assumptions!$B$33 -> 13000 | N96: =IF(L96="No",Assumptions!$B$34,0) -> 0 | O96: =M96+N96 -> 13000 | P96: =G96+Assumptions!$B$37+IF(L96="No",Assumptions!$B$38,0) -> 1725
A97: 4002-A | B97: 3/2.00 | C97: Brunswick w/ WD | D97: 1590 | E97: Current | F97: Occupied | G97: 1600 | H97: 1581 | I97: =IF(F97="Vacant",0,H97-G97) -> -19 | J97: 46143 | K97: 46507 | L97: Yes | M97: =Assumptions!$B$33 -> 13000 | N97: =IF(L97="No",Assumptions!$B$34,0) -> 0 | O97: =M97+N97 -> 13000 | P97: =G97+Assumptions!$B$37+IF(L97="No",Assumptions!$B$38,0) -> 1725
A98: 4005-C | B98: 3/2.00 | C98: Brunswick w/ WD | D98: 1590 | E98: Current | F98: Occupied | G98: 1600 | H98: 1581 | I98: =IF(F98="Vacant",0,H98-G98) -> -19 | J98: 46076 | K98: 46468 | L98: Yes | M98: =Assumptions!$B$33 -> 13000 | N98: =IF(L98="No",Assumptions!$B$34,0) -> 0 | O98: =M98+N98 -> 13000 | P98: =G98+Assumptions!$B$37+IF(L98="No",Assumptions!$B$38,0) -> 1725
A99: 4005-E | B99: 3/2.00 | C99: Brunswick w/ WD | D99: 1590 | E99: Current | F99: Occupied | G99: 1600 | H99: 1571 | I99: =IF(F99="Vacant",0,H99-G99) -> -29 | J99: 45493 | K99: 46222 | L99: Yes | M99: =Assumptions!$B$33 -> 13000 | N99: =IF(L99="No",Assumptions!$B$34,0) -> 0 | O99: =M99+N99 -> 13000 | P99: =G99+Assumptions!$B$37+IF(L99="No",Assumptions!$B$38,0) -> 1725
A100: 4006-B | B100: 3/2.00 | C100: Brunswick w/ WD | D100: 1590 | E100: Current | F100: Occupied | G100: 1600 | H100: 1571 | I100: =IF(F100="Vacant",0,H100-G100) -> -29 | J100: 43724 | K100: 46278 | L100: Yes | M100: =Assumptions!$B$33 -> 13000 | N100: =IF(L100="No",Assumptions!$B$34,0) -> 0 | O100: =M100+N100 -> 13000 | P100: =G100+Assumptions!$B$37+IF(L100="No",Assumptions!$B$38,0) -> 1725
A101: 4006-D | B101: 3/2.00 | C101: Brunswick w/ WD | D101: 1590 | E101: Current | F101: Occupied | G101: 1600 | H101: 1581 | I101: =IF(F101="Vacant",0,H101-G101) -> -19 | J101: 46101 | K101: 46496 | L101: Yes | M101: =Assumptions!$B$33 -> 13000 | N101: =IF(L101="No",Assumptions!$B$34,0) -> 0 | O101: =M101+N101 -> 13000 | P101: =G101+Assumptions!$B$37+IF(L101="No",Assumptions!$B$38,0) -> 1725
A102: 4006-F | B102: 3/2.00 | C102: Brunswick w/ WD | D102: 1590 | E102: Current | F102: Occupied | G102: 1600 | H102: 1561 | I102: =IF(F102="Vacant",0,H102-G102) -> -39 | J102: 45536 | K102: 46295 | L102: Yes | M102: =Assumptions!$B$33 -> 13000 | N102: =IF(L102="No",Assumptions!$B$34,0) -> 0 | O102: =M102+N102 -> 13000 | P102: =G102+Assumptions!$B$37+IF(L102="No",Assumptions!$B$38,0) -> 1725
A103: 4025-B | B103: 3/2.00 | C103: Brunswick w/ WD | D103: 1590 | E103: Current | F103: Occupied | G103: 1600 | H103: 1581 | I103: =IF(F103="Vacant",0,H103-G103) -> -19 | J103: 37196 | K103: 46326 | L103: Yes | M103: =Assumptions!$B$33 -> 13000 | N103: =IF(L103="No",Assumptions!$B$34,0) -> 0 | O103: =M103+N103 -> 13000 | P103: =G103+Assumptions!$B$37+IF(L103="No",Assumptions!$B$38,0) -> 1725
A104: 4025-D | B104: 3/2.00 | C104: Brunswick w/ WD | D104: 1590 | E104: Current | F104: Occupied | G104: 1600 | H104: 1581 | I104: =IF(F104="Vacant",0,H104-G104) -> -19 | J104: 45919 | K104: 46283 | L104: Yes | M104: =Assumptions!$B$33 -> 13000 | N104: =IF(L104="No",Assumptions!$B$34,0) -> 0 | O104: =M104+N104 -> 13000 | P104: =G104+Assumptions!$B$37+IF(L104="No",Assumptions!$B$38,0) -> 1725
A105: 4025-F | B105: 3/2.00 | C105: Brunswick w/ WD | D105: 1590 | E105: Current | F105: Occupied | G105: 1600 | H105: 1581 | I105: =IF(F105="Vacant",0,H105-G105) -> -19 | J105: 46079 | K105: 46471 | L105: Yes | M105: =Assumptions!$B$33 -> 13000 | N105: =IF(L105="No",Assumptions!$B$34,0) -> 0 | O105: =M105+N105 -> 13000 | P105: =G105+Assumptions!$B$37+IF(L105="No",Assumptions!$B$38,0) -> 1725
... A111: 4034-C | B111: 3/2.00 | C111: Brunswick w/ WD | D111: 1590 | E111: Current | F111: Occupied | G111: 1600 | H111: 1565 | I111: =IF(F111="Vacant",0,H111-G111) -> -35 | J111: 45085 | K111: 46545 | L111: Yes | M111: =Assumptions!$B$33 -> 13000 | N111: =IF(L111="No",Assumptions!$B$34,0) -> 0 | O111: =M111+N111 -> 13000 | P111: =G111+Assumptions!$B$37+IF(L111="No",Assumptions!$B$38,0) -> 1725
A112: 4034-E | B112: 3/2.00 | C112: Brunswick w/ WD | D112: 1590 | E112: Current | F112: Occupied | G112: 1600 | H112: 1581 | I112: =IF(F112="Vacant",0,H112-G112) -> -19 | J112: 39255 | L112: Yes | M112: =Assumptions!$B$33 -> 13000 | N112: =IF(L112="No",Assumptions!$B$34,0) -> 0 | O112: =M112+N112 -> 13000 | P112: =G112+Assumptions!$B$37+IF(L112="No",Assumptions!$B$38,0) -> 1725
A113: 4037-A | B113: 3/2.00 | C113: Brunswick w/ WD | D113: 1590 | E113: Current | F113: Occupied | G113: 1600 | H113: 1569 | I113: =IF(F113="Vacant",0,H113-G113) -> -31 | J113: 43982 | K113: 46418 | L113: Yes | M113: =Assumptions!$B$33 -> 13000 | N113: =IF(L113="No",Assumptions!$B$34,0) -> 0 | O113: =M113+N113 -> 13000 | P113: =G113+Assumptions!$B$37+IF(L113="No",Assumptions!$B$38,0) -> 1725
A114: 4037-C | B114: 3/2.00 | C114: Brunswick w/ WD | D114: 1590 | E114: Current | F114: Occupied | G114: 1600 | H114: 1581 | I114: =IF(F114="Vacant",0,H114-G114) -> -19 | J114: 45997 | K114: 46361 | L114: Yes | M114: =Assumptions!$B$33 -> 13000 | N114: =IF(L114="No",Assumptions!$B$34,0) -> 0 | O114: =M114+N114 -> 13000 | P114: =G114+Assumptions!$B$37+IF(L114="No",Assumptions!$B$38,0) -> 1725
A115: 4037-E | B115: 3/2.00 | C115: Brunswick w/ WD | D115: 1590 | E115: Current | F115: Occupied | G115: 1600 | H115: 1581 | I115: =IF(F115="Vacant",0,H115-G115) -> -19 | J115: 46127 | K115: 46521 | L115: Yes | M115: =Assumptions!$B$33 -> 13000 | N115: =IF(L115="No",Assumptions!$B$34,0) -> 0 | O115: =M115+N115 -> 13000 | P115: =G115+Assumptions!$B$37+IF(L115="No",Assumptions!$B$38,0) -> 1725
A116: 4038-B | B116: 3/2.00 | C116: Brunswick w/ WD | D116: 1590 | E116: Current | F116: Occupied | G116: 1600 | H116: 1549 | I116: =IF(F116="Vacant",0,H116-G116) -> -51 | J116: 44681 | K116: 46506 | L116: Yes | M116: =Assumptions!$B$33 -> 13000 | N116: =IF(L116="No",Assumptions!$B$34,0) -> 0 | O116: =M116+N116 -> 13000 | P116: =G116+Assumptions!$B$37+IF(L116="No",Assumptions!$B$38,0) -> 1725
A117: 4038-D | B117: 3/2.00 | C117: Brunswick w/ WD | D117: 1590 | E117: Current | F117: Occupied | G117: 1600 | H117: 1557 | I117: =IF(F117="Vacant",0,H117-G117) -> -43 | J117: 45730 | K117: 46459 | L117: Yes | M117: =Assumptions!$B$33 -> 13000 | N117: =IF(L117="No",Assumptions!$B$34,0) -> 0 | O117: =M117+N117 -> 13000 | P117: =G117+Assumptions!$B$37+IF(L117="No",Assumptions!$B$38,0) -> 1725
A118: 4038-F | B118: 3/2.00 | C118: Brunswick w/ WD | D118: 1590 | E118: Current | F118: Occupied | G118: 1600 | H118: 1524 | I118: =IF(F118="Vacant",0,H118-G118) -> -76 | J118: 45170 | K118: 46265 | L118: Yes | M118: =Assumptions!$B$33 -> 13000 | N118: =IF(L118="No",Assumptions!$B$34,0) -> 0 | O118: =M118+N118 -> 13000 | P118: =G118+Assumptions!$B$37+IF(L118="No",Assumptions!$B$38,0) -> 1725
A119: 4002-E | B119: 3/2.00 | C119: Brunswick w/ WD | D119: 1590 | E119: Evict | F119: Occupied | G119: 1600 | H119: 1499 | I119: =IF(F119="Vacant",0,H119-G119) -> -101 | J119: 45990 | K119: 46384 | L119: Yes | M119: =Assumptions!$B$33 -> 13000 | N119: =IF(L119="No",Assumptions!$B$34,0) -> 0 | O119: =M119+N119 -> 13000 | P119: =G119+Assumptions!$B$37+IF(L119="No",Assumptions!$B$38,0) -> 1725
A120: 4029-A | B120: 3/2.00 | C120: Brunswick w/ WD | D120: 1590 | E120: Evict | F120: Occupied | G120: 1600 | H120: 1559 | I120: =IF(F120="Vacant",0,H120-G120) -> -41 | J120: 45261 | K120: 46356 | L120: Yes | M120: =Assumptions!$B$33 -> 13000 | N120: =IF(L120="No",Assumptions!$B$34,0) -> 0 | O120: =M120+N120 -> 13000 | P120: =G120+Assumptions!$B$37+IF(L120="No",Assumptions!$B$38,0) -> 1725
A121: 4002-C | B121: 3/2.00 | C121: Brunswick w/ WD | D121: 1590 | E121: Notice-Unrented | F121: Occupied | G121: 1600 | H121: 1561 | I121: =IF(F121="Vacant",0,H121-G121) -> -39 | J121: 45120 | K121: 46215 | L121: Yes | M121: =Assumptions!$B$33 -> 13000 | N121: =IF(L121="No",Assumptions!$B$34,0) -> 0 | O121: =M121+N121 -> 13000 | P121: =G121+Assumptions!$B$37+IF(L121="No",Assumptions!$B$38,0) -> 1725
A122: 4005-A | B122: 3/2.00 | C122: Brunswick w/ WD | D122: 1590 | E122: Notice-Unrented | F122: Occupied | G122: 1600 | H122: 1565 | I122: =IF(F122="Vacant",0,H122-G122) -> -35 | J122: 45450 | K122: 46179 | L122: Yes | M122: =Assumptions!$B$33 -> 13000 | N122: =IF(L122="No",Assumptions!$B$34,0) -> 0 | O122: =M122+N122 -> 13000 | P122: =G122+Assumptions!$B$37+IF(L122="No",Assumptions!$B$38,0) -> 1725
A123: 4033-F | B123: 3/2.00 | C123: Brunswick w/ WD | D123: 1590 | E123: Vacant-Unrented | F123: Vacant | G123: 1600 | I123: =IF(F123="Vacant",0,H123-G123) -> 0 | L123: Yes | M123: =Assumptions!$B$33 -> 13000 | N123: =IF(L123="No",Assumptions!$B$34,0) -> 0 | O123: =M123+N123 -> 13000 | P123: =G123+Assumptions!$B$37+IF(L123="No",Assumptions!$B$38,0) -> 1725
A124: Total / Average — 118 Units | D124: =SUM(D6:D123) -> 134371 | F124: =COUNTIF(F6:F123,"Occupied")&" occ" -> 114 occ | G124: =SUM(G6:G123) -> 153435 | H124: =SUM(H6:H123) -> 144804.03 | I124: =SUM(I6:I123) -> -3260.97 | L124: =COUNTIF(L6:L123,"Yes")&" w/ W/D" -> 53 w/ W/D | M124: =SUM(M6:M123) -> 1534000 | N124: =SUM(N6:N123) -> 325000 | O124: =SUM(O6:O123) -> 1859000 | P124: =SUM(P6:P123) -> 173060
A126: Case status rules applied: 'Notice-Unrented' and 'Evict' are treated as Occupied; any variation of 'Vacant' is treated as Vacant. Source: rent roll export dated 07/01/2026.
A127: In-unit washer/dryer is taken from the rent roll unit-type description ('w/ WD'), which the OM's own floor-plan and building-mix schedules corroborate at 53 units. Per the data hierarchy the rent roll governs over the OM's conflicting '78 of 118' statement.

Sheet Unit Mix
A1: CHATEAU IN THE WOODS | 4020 Monaco Drive, Indianapolis, IN 46220 | 118 Units
A2: Floor Plan Mix, Renovation Scope and Renovated Rents (rent roll 07/01/2026)
A3: Blue = hardcoded input / lever · Black = formula · Green = link to another sheet · Yellow fill = key assumption
A5: Floor Plan | B5: Type | C5: Units | D5: % of Total | E5: SF / Unit | F5: Total SF | G5: In-Unit W/D | H5: Occ. Units | I5: Market Rent | J5: Market Rent PSF | K5: In-Place Rent (occ) | L5: Avg In-Place Rent | M5: Loss to Lease | N5: Reno Cost / Unit | O5: Reno Prem. / Month | P5: Renovated Mkt Rent | Q5: Renov. Rent PSF
A6: Abbey | B6: 1/1 | C6: 15 | D6: =C6/$C$13 -> 0.12711864 | E6: 712 | F6: =C6*E6 -> 10680 | G6: No | H6: 15 | I6: 1050 | J6: =I6/E6 -> 1.4747191 | K6: 15618 | L6: =IF(H6=0,0,K6/H6) -> 1041.2 | M6: =IF(H6=0,0,L6/I6-1) -> -0.0083809524 | N6: =Assumptions!$B$33+IF(G6="No",Assumptions!$B$34,0) -> 18000 | O6: =Assumptions!$B$37+IF(G6="No",Assumptions!$B$38,0) -> 200 | P6: =I6+O6 -> 1250 | Q6: =P6/E6 -> 1.755618
A7: Rhone w/ WD | B7: 1/1 | C7: 15 | D7: =C7/$C$13 -> 0.12711864 | E7: 712 | F7: =C7*E7 -> 10680 | G7: Yes | H7: 15 | I7: 1125 | J7: =I7/E7 -> 1.5800562 | K7: 16385 | L7: =IF(H7=0,0,K7/H7) -> 1092.3333 | M7: =IF(H7=0,0,L7/I7-1) -> -0.029037037 | N7: =Assumptions!$B$33+IF(G7="No",Assumptions!$B$34,0) -> 13000 | O7: =Assumptions!$B$37+IF(G7="No",Assumptions!$B$38,0) -> 125 | P7: =I7+O7 -> 1250 | Q7: =P7/E7 -> 1.755618
A8: Roman w/ WD | B8: 1/1.5 | C8: 4 | D8: =C8/$C$13 -> 0.033898305 | E8: 852 | F8: =C8*E8 -> 3408 | G8: Yes | H8: 4 | I8: 1165 | J8: =I8/E8 -> 1.3673709 | K8: 4656 | L8: =IF(H8=0,0,K8/H8) -> 1164 | M8: =IF(H8=0,0,L8/I8-1) -> -0.0008583691 | N8: =Assumptions!$B$33+IF(G8="No",Assumptions!$B$34,0) -> 13000 | O8: =Assumptions!$B$37+IF(G8="No",Assumptions!$B$38,0) -> 125 | P8: =I8+O8 -> 1290 | Q8: =P8/E8 -> 1.5140845
A9: Cabernet w/ WD | B9: 2/1 | C9: 4 | D9: =C9/$C$13 -> 0.033898305 | E9: 1182 | F9: =C9*E9 -> 4728 | G9: Yes | H9: 4 | I9: 1350 | J9: =I9/E9 -> 1.142132 | K9: 5352 | L9: =IF(H9=0,0,K9/H9) -> 1338 | M9: =IF(H9=0,0,L9/I9-1) -> -0.0088888889 | N9: =Assumptions!$B$33+IF(G9="No",Assumptions!$B$34,0) -> 13000 | O9: =Assumptions!$B$37+IF(G9="No",Assumptions!$B$38,0) -> 125 | P9: =I9+O9 -> 1475 | Q9: =P9/E9 -> 1.2478849
A10: Verdun | B10: 2/2 | C10: 25 | D10: =C10/$C$13 -> 0.21186441 | E10: 1105 | F10: =C10*E10 -> 27625 | G10: No | H10: 24 | I10: 1250 | J10: =I10/E10 -> 1.1312217 | K10: 28580.03 | L10: =IF(H10=0,0,K10/H10) -> 1190.8346 | M10: =IF(H10=0,0,L10/I10-1) -> -0.047332333 | N10: =Assumptions!$B$33+IF(G10="No",Assumptions!$B$34,0) -> 18000 | O10: =Assumptions!$B$37+IF(G10="No",Assumptions!$B$38,0) -> 200 | P10: =I10+O10 -> 1450 | Q10: =P10/E10 -> 1.3122172
A11: Bordeaux | B11: 2/2 | C11: 25 | D11: =C11/$C$13 -> 0.21186441 | E11: 1182 | F11: =C11*E11 -> 29550 | G11: No | H11: 23 | I11: 1260 | J11: =I11/E11 -> 1.0659898 | K11: 28802 | L11: =IF(H11=0,0,K11/H11) -> 1252.2609 | M11: =IF(H11=0,0,L11/I11-1) -> -0.006142167 | N11: =Assumptions!$B$33+IF(G11="No",Assumptions!$B$34,0) -> 18000 | O11: =Assumptions!$B$37+IF(G11="No",Assumptions!$B$38,0) -> 200 | P11: =I11+O11 -> 1460 | Q11: =P11/E11 -> 1.2351946
A12: Brunswick w/ WD | B12: 3/2 | C12: 30 | D12: =C12/$C$13 -> 0.25423729 | E12: 1590 | F12: =C12*E12 -> 47700 | G12: Yes | H12: 29 | I12: 1600 | J12: =I12/E12 -> 1.0062893 | K12: 45411 | L12: =IF(H12=0,0,K12/H12) -> 1565.8966 | M12: =IF(H12=0,0,L12/I12-1) -> -0.021314655 | N12: =Assumptions!$B$33+IF(G12="No",Assumptions!$B$34,0) -> 13000 | O12: =Assumptions!$B$37+IF(G12="No",Assumptions!$B$38,0) -> 125 | P12: =I12+O12 -> 1725 | Q12: =P12/E12 -> 1.0849057
A13: Total / Weighted Average | C13: =SUM(C6:C12) -> 118 | D13: =SUM(D6:D12) -> 1 | E13: =F13/C13 -> 1138.7373 | F13: =SUM(F6:F12) -> 134371 | G13: =SUMIF(G6:G12,"Yes",C6:C12)&" of "&C13 -> 53 of 118 | H13: =SUM(H6:H12) -> 114 | I13: =SUMPRODUCT(C6:C12,I6:I12)/C13 -> 1300.2966 | J13: =SUMPRODUCT(C6:C12,I6:I12)/F13 -> 1.1418759 | K13: =SUM(K6:K12) -> 144804.03 | L13: =K13/H13 -> 1270.2108 | M13: =L13/(SUMPRODUCT(H6:H12,I6:I12)/H13)-1 -> -0.022023908 | N13: =SUMPRODUCT(C6:C12,N6:N12)/C13 -> 15754.237 | O13: =SUMPRODUCT(C6:C12,O6:O12)/C13 -> 166.31356 | P13: =SUMPRODUCT(C6:C12,P6:P12)/C13 -> 1466.6102 | Q13: =SUMPRODUCT(C6:C12,P6:P12)/F13 -> 1.2879267
A15: AGGREGATE RENT POTENTIAL
A16: Total Market Rent — Classic Condition ($/month) | D16: =SUMPRODUCT(C6:C12,I6:I12) -> 153435
A17: Total Market Rent — Renovated ($/month) | D17: =SUMPRODUCT(C6:C12,P6:P12) -> 173060
A18: Average Market Rent / Unit — Classic | D18: =D16/C13 -> 1300.2966
A19: Average Market Rent / Unit — Renovated | D19: =D17/C13 -> 1466.6102
A20: Market Rent of the 4 Vacant Units ($/month) | D20: =SUMPRODUCT((C6:C12-H6:H12),I6:I12) -> 5370
A21: Total Renovation Capital ($) | D21: =SUMPRODUCT(C6:C12,N6:N12) -> 1859000
A22: Units Requiring W/D Addition | D22: =SUMIF(G6:G12,"No",C6:C12) -> 65
A24: Unit counts, square footage, market rents and in-place rents are taken directly from the 07/01/2026 rent roll and foot to its total row ($153,435 market / $144,804 in-place / 134,371 SF). Renovation cost and premium are driven from the Assumptions tab.

Sheet T-12 Recast
A1: CHATEAU IN THE WOODS | 4020 Monaco Drive, Indianapolis, IN 46220 | 118 Units
A2: T-12 Actuals (Feb 2025 – Jan 2026) Recast to Underwriting Line Items
A3: Blue = hardcoded input / lever · Black = formula · Green = link to another sheet · Yellow fill = key assumption
A5: REVENUE
B6: T-12 Actual | C6: Per Unit | D6: UW Year 1 | E6: Variance | F6: Underwriting note
A7: Gross Rent Potential | B7: 1813657 | C7: =B7/Assumptions!$B$17 -> 15369.975 | D7: ='Annual Model'!C21 -> 1906611.9 | E7: =IF(B7=0,"n/a",D7/B7-1) -> 0.051252758 | F7: T-12 gross rent potential at then-current market rents. UW Year 1 reflects the 07/01/2026 rent roll, renovated-unit premiums as they come online, and market rent growth.
A8: Economic Vacancy / Loss to Lease | B8: -31322.94 | C8: =B8/Assumptions!$B$17 -> -265.44864 | D8: ='Annual Model'!C23 -> -41945.462 | E8: =IF(B8=0,"n/a",D8/B8-1) -> 0.33912916 | F8: T-12 loss to lease is 1.7% of GPR. Rent roll shows 2.2% in place today.
A9: Physical Vacancy | B9: -171096 | C9: =B9/Assumptions!$B$17 -> -1449.9661 | D9: ='Annual Model'!C24+'Annual Model'!C25 -> -126748.4 | E9: =IF(B9=0,"n/a",D9/B9-1) -> -0.25919717 | F9: T-12 physical vacancy is 9.4% of GPR (and deteriorating: Jan-26 alone was $20,757). UW is 5.0% operating plus renovation downtime.
A10: Concessions | B10: -9688 | C10: =B10/Assumptions!$B$17 -> -82.101695 | D10: ='Annual Model'!C26 -> -14299.589 | E10: =IF(B10=0,"n/a",D10/B10-1) -> 0.47601047 | F10: T-12 $9,688. Concessions restarted in Aug-25 after a year at zero.
A11: Bad Debt, net of collections | B11: -9179.26 | C11: =B11/Assumptions!$B$17 -> -77.790339 | D11: ='Annual Model'!C27 -> -28599.179 | E11: =IF(B11=0,"n/a",D11/B11-1) -> 2.1156301 | F11: T-12 gross write-offs $28,229 less $19,050 collected = $9,179 net (0.5%). Underwritten at 1.5% falling to 1.0% given 4 evictions and 8 notices on the rent roll.
A12: Net Rental Income | B12: 1592370.8 | C12: =B12/Assumptions!$B$17 -> 13494.668 | D12: ='Annual Model'!C28 -> 1695019.3 | E12: =IF(B12=0,"n/a",D12/B12-1) -> 0.064462682
A14: OTHER INCOME
A15: Carport / Garage Rent (74 carports @ $25) | B15: 16197 | C15: =B15/Assumptions!$B$17 -> 137.26271
A16: Storage Rent (5 of 23 rented @ $15-20) | B16: 141 | C16: =B16/Assumptions!$B$17 -> 1.1949153
A17: Credit Builder Fees | B17: 2346.11 | C17: =B17/Assumptions!$B$17 -> 19.882288
A18: Onsite Transfer Fees | B18: 200 | C18: =B18/Assumptions!$B$17 -> 1.6949153
A19: Administrative Fees | B19: 5250 | C19: =B19/Assumptions!$B$17 -> 44.491525
A20: Utility Fees (water/sewer + valet trash bundled) | B20: 97811.57 | C20: =B20/Assumptions!$B$17 -> 828.91161
A21: Technology Fee ($49 bulk internet, ramping) | B21: 13553 | C21: =B21/Assumptions!$B$17 -> 114.85593
A22: Lease Termination Fees | B22: 4000 | C22: =B22/Assumptions!$B$17 -> 33.898305
A23: Eviction Fees | B23: 3095.96 | C23: =B23/Assumptions!$B$17 -> 26.236949
A24: Washer/Dryer Rental (programme discontinued) | B24: 209 | C24: =B24/Assumptions!$B$17 -> 1.7711864
A25: Application Fees | B25: 7050 | C25: =B25/Assumptions!$B$17 -> 59.745763
A26: Utility Reimbursement | B26: 545.93 | C26: =B26/Assumptions!$B$17 -> 4.6265254
... A32: Damage Charges (cleaning, flooring, paint, other) | B32: 20467.4 | C32: =B32/Assumptions!$B$17 -> 173.45254
A33: Total Operating Other Income | B33: =SUM(B15:B32) -> 193597.53 | C33: =B33/Assumptions!$B$17 -> 1640.657 | D33: ='Other Income'!C25 -> 238318.9 | E33: =IF(B33=0,"n/a",D33/B33-1) -> 0.23100176 | F33: Interest income of $4,133 is excluded as non-property income. Bad debt is shown above as a revenue deduction rather than netted in other income.
A34: Memo: Interest Income (excluded) | B34: 4132.89 | C34: =B34/Assumptions!$B$17 -> 35.024492 | F34: Excluded from underwritten revenue — a function of the seller's cash balances, not the real estate.
A36: OPERATING EXPENSES
B37: T-12 Actual | C37: Per Unit | D37: UW Year 1 | E37: Variance | F37: Underwriting note
A38: Payroll (incl. contract labour) | B38: 227969.28 | C38: =B38/Assumptions!$B$17 -> 1931.9431 | D38: =Assumptions!$B$55 -> 235000 | E38: =D38/B38-1 -> 0.030840647 | F38: T-12 $227,969 ($1,932/unit) including $9,778 of contract labour. CBRE forecast $229,021 for a manager, part-time leasing, maintenance supervisor and one technician. We fund a second technician.
A39: Property Management Fee | B39: 62064.01 | C39: =B39/Assumptions!$B$17 -> 525.96619 | D39: ='Annual Model'!C36 -> 77333.528 | E39: =D39/B39-1 -> 0.24602854 | F39: T-12 is an effective 3.5% of revenue. Underwritten at a market 4.0% of effective gross revenue.
A40: Marketing & Advertising | B40: 26399.14 | C40: =B40/Assumptions!$B$17 -> 223.72153 | D40: =Assumptions!$B$57 -> 28000 | E40: =D40/B40-1 -> 0.060640612 | F40: T-12 $26,399, of which $22,047 is ILS. Increased modestly for renovated-unit lease-up.
A41: General & Administrative | B41: 62885.88 | C41: =B41/Assumptions!$B$17 -> 532.93119 | D41: =Assumptions!$B$58 -> 50000 | E41: =D41/B41-1 -> -0.20490896 | F41: T-12 $62,887 includes $17,528 legal and $14,730 tax/audit concentrated in Dec-25/Jan-26, almost certainly transaction-related. CBRE forecast $42,209. Underwritten at $50,000 between the two.
A42: Bulk Internet | B42: 11068.2 | C42: =B42/Assumptions!$B$17 -> 93.798305 | D42: =Assumptions!$B$59 -> 39577 | E42: =D42/B42-1 -> 2.5757395 | F42: T-12 $11,068 captures only 7 months of a ramping contract. Stabilised is $27.95/unit/month = $39,577. Understating this line is the easiest way to overstate NOI on this deal.
A43: Electricity (common + vacant) | B43: 30319.93 | C43: =B43/Assumptions!$B$17 -> 256.94856 | D43: =Assumptions!$B$60 -> 31000 | E43: =D43/B43-1 -> 0.022429801 | F43: T-12 $30,320 across corporate and vacant-unit meters.
A44: Gas (central hot water + common) | B44: 15330.1 | C44: =B44/Assumptions!$B$17 -> 129.9161 | D44: =Assumptions!$B$61 -> 16000 | E44: =D44/B44-1 -> 0.043698345 | F44: T-12 $15,330. Central gas water heaters plus 8 individual electric.
A45: Water & Sewer | B45: 86468.36 | C45: =B45/Assumptions!$B$17 -> 732.78271 | D45: =Assumptions!$B$62 -> 90000 | E45: =D45/B45-1 -> 0.040843148 | F45: T-12 $86,468. Master-metered and billed back to residents; recovery is modelled at 85% in Other Income.
A46: Repairs & Maintenance (incl. turns) | B46: 250934.72 | C46: =B46/Assumptions!$B$17 -> 2126.5654 | D46: =Assumptions!$B$63 -> 255000 | E46: =D46/B46-1 -> 0.016200548 | F46: T-12 $250,935 ($2,127/unit) including $42,921 of turnover cost. No post-renovation savings credited, though a fully renovated portfolio should run lighter.
A47: Insurance | B47: 94611.24 | C47: =B47/Assumptions!$B$17 -> 801.79017 | D47: =Assumptions!$B$64 -> 95000 | E47: =D47/B47-1 -> 0.0041090255 | F47: T-12 $94,611 ($802/unit). CBRE forecast $88,326. Held at T-12 plus a small cushion pending a loss run.
A48: Real Estate Taxes | B48: 149676.52 | C48: =B48/Assumptions!$B$17 -> 1268.4451 | D48: ='Annual Model'!C45 -> 140000 | E48: =D48/B48-1 -> -0.064649552 | F48: T-12 $149,677 including a $17,958 October catch-up. CBRE's 2025-pay-2026 estimate with the SB-1 deduction is $135,374. Year 1 $140,000 stepping to $210,000 by Year 5 for reassessment on sale.
A49: Total Operating Expenses | B49: =SUM(B38:B48) -> 1017727.4 | C49: =B49/Assumptions!$B$17 -> 8624.8083 | D49: ='Annual Model'!C46 -> 1056910.5 | E49: =D49/B49-1 -> 0.038500632
A50: Net Operating Income | B50: =B12+B33-B49 -> 768240.95 | C50: =B50/Assumptions!$B$17 -> 6510.5165 | D50: ='Annual Model'!C50 -> 876427.66 | E50: =D50/B50-1 -> 0.14082394
A52: Memo — items the property books below NOI or excludes:
A53: Replacement Reserve / capital spend (T-12 actual) | B53: 108412.44 | C53: =B53/Assumptions!$B$17 -> 918.74949 | F53: The property expensed $108,412 of capital below the line in the T-12, including $34,535 of concrete/asphalt and $29,053 of water heaters. Evidence of real ongoing capital need.
A54: Depreciation & Amortisation | B54: 167811.52 | C54: =B54/Assumptions!$B$17 -> 1422.1315 | F54: Non-cash; excluded.
A56: Source: Chateau in the Woods Trailing Profit And Loss Detail, January 2026, accrual basis (ResMan), covering February 2025 through January 2026. All T-12 figures are the report's own Adjusted Total column.
A57: Tie-out: the property's own statement shows total income of $1,790,101 less total expense of $1,017,727 = $772,374 of NOI. This recast shows $768,242, the difference being the $4,133 of interest income excluded above as non-property income. Bad debt is presented here as a revenue deduction rather than netted inside other income, which changes the presentation but not the NOI.

Sheet Other Income
A1: CHATEAU IN THE WOODS | 4020 Monaco Drive, Indianapolis, IN 46220 | 118 Units
A2: Other Income Build — T-12 Actuals plus Identified Ancillary Upside
A3: Blue = hardcoded input / lever · Black = formula · Green = link to another sheet · Yellow fill = key assumption
B5: T-12 Actual | C5: Year 1 | D5: Year 2 | E5: Year 3 | F5: Year 4 | G5: Year 5 | H5: Basis
A6: Ramp — Technology Fee ($49) implementation | C6: 0.85 | D6: 1 | E6: 1 | F6: 1 | G6: 1 | H6: Contract signed May 2025 and implemented on new leases and renewals over 13 months. Jan-26 booked $3,303 of a $5,489 full month, i.e. 60% penetrated at the T-12 close.
A7: Ramp — Valet Trash ($25) implementation | C7: 0.75 | D7: 0.95 | E7: 1 | F7: 1 | G7: 1 | H7: Charged on new leases and renewals. The property begins paying the valet contractor in Jan-2026.
A8: Ramp — Pet Rent (new policy) | C8: 0.5 | D8: 1 | E8: 1 | F8: 1 | G8: 1 | H8: The property charges no pet fee or pet rent today. New policy phased in on renewals over year one.
A9: Economic occupancy factor for per-unit charges | C9: 0.95 | D9: 0.95 | E9: 0.95 | F9: 0.95 | G9: 0.95 | H9: Consistent with CBRE's other-income forecast method.
A11: OTHER INCOME LINE ITEMS
A12: Water & Sewer Recovery (85% of expense) | B12: 97811.57 | C12: =0.85*Assumptions!$B$62 -> 76500 | D12: =C12*(1+Assumptions!$C$62) -> 79560 | E12: =D12*(1+Assumptions!$C$62) -> 82742.4 | F12: =E12*(1+Assumptions!$C$62) -> 86052.096 | G12: =F12*(1+Assumptions!$C$62) -> 89494.18 | H12: T-12 Utility Fees of $97,812 bundle water/sewer and valet trash. CBRE's forecast splits them and assumes 85% water/sewer recovery. Flexes with the water & sewer expense line.
A13: Valet Trash ($25/unit/month) | B13: 0 | C13: =25*12*Assumptions!$B$17*C$9*C$7 -> 25222.5 | D13: =C13/C$7*D$7*(1+Assumptions!D$51) -> 32906.955 | E13: =D13/D$7*E$7*(1+Assumptions!E$51) -> 35678.067 | F13: =E13/E$7*F$7*(1+Assumptions!F$51) -> 36748.409 | G13: =F13/F$7*G$7*(1+Assumptions!G$51) -> 37850.861 | H13: Broken out of Utility Fees per CBRE. A valet contract has been signed and the property starts paying for the service in Jan-2026, so the charge must be collected.
A14: Technology Fee ($49/unit/month) | B14: 13553 | C14: =49*12*Assumptions!$B$17*C$9*C$6 -> 56027.58 | D14: =C14/C$6*D$6*(1+Assumptions!D$51) -> 67892.244 | E14: =D14/D$6*E$6*(1+Assumptions!E$51) -> 69929.011 | F14: =E14/E$6*F$6*(1+Assumptions!F$51) -> 72026.882 | G14: =F14/F$6*G$6*(1+Assumptions!G$51) -> 74187.688 | H14: Offsets the $27.95/unit/month bulk internet expense. Contractual and already being billed.
A15: Carport Rent (74 carports @ $25/month) | B15: 16197 | C15: =B15 -> 16197 | D15: =C15*(1+Assumptions!D$51) -> 16682.91 | E15: =D15*(1+Assumptions!E$51) -> 17183.397 | F15: =E15*(1+Assumptions!F$51) -> 17698.899 | G15: =F15*(1+Assumptions!G$51) -> 18229.866 | H15: T-12 actual. 74 carports at $25; occupancy of the carports, not the units.
A16: Pet Rent ($30/month on 25% of units) | B16: 500 | C16: =30*12*Assumptions!$B$17*0.25*C$8 -> 5310 | D16: =C16/C$8*D$8*(1+Assumptions!D$51) -> 10938.6 | E16: =D16/D$8*E$8*(1+Assumptions!E$51) -> 11266.758 | F16: =E16/E$8*F$8*(1+Assumptions!F$51) -> 11604.761 | G16: =F16/F$8*G$8*(1+Assumptions!G$51) -> 11952.904 | H16: The property currently charges nothing for pets. A conservative $30/month on 25% of units; CBRE forecasts the same $10,620.
A17: Storage Rent (23 units available) | B17: 141 | C17: =3600 -> 3600 | D17: =C17*(1+Assumptions!D$51) -> 3708 | E17: =D17*(1+Assumptions!E$51) -> 3819.24 | F17: =E17*(1+Assumptions!F$51) -> 3933.8172 | G17: =F17*(1+Assumptions!G$51) -> 4051.8317 | H17: Only 5 of 23 storage units are rented today at $15-20. Underwritten at 12 rented at $25.
A18: Application & Administrative Fees | B18: 14846.11 | C18: =B18 -> 14846.11 | D18: =C18*(1+Assumptions!D$51) -> 15291.493 | E18: =D18*(1+Assumptions!E$51) -> 15750.238 | F18: =E18*(1+Assumptions!F$51) -> 16222.745 | G18: =F18*(1+Assumptions!G$51) -> 16709.428 | H18: T-12 actual: application, administrative, credit builder and transfer fees.
A19: Late & NSF Fees | B19: 10175 | C19: =B19 -> 10175 | D19: =C19*(1+Assumptions!D$51) -> 10480.25 | E19: =D19*(1+Assumptions!E$51) -> 10794.657 | F19: =E19*(1+Assumptions!F$51) -> 11118.497 | G19: =F19*(1+Assumptions!G$51) -> 11452.052 | H19: T-12 actual.
A20: Short-Term Lease Premiums | B20: 6440.71 | C20: =B20 -> 6440.71 | D20: =C20*(1+Assumptions!D$51) -> 6633.9313 | E20: =D20*(1+Assumptions!E$51) -> 6832.9492 | F20: =E20*(1+Assumptions!F$51) -> 7037.9377 | G20: =F20*(1+Assumptions!G$51) -> 7249.0758 | H20: T-12 actual. $75/month on 6-8 month renewals, $50/month on 9-11 month renewals.
A21: Lease Termination & Eviction Fees | B21: 7095.96 | C21: =4000 -> 4000 | D21: =C21*(1+Assumptions!D$51) -> 4120 | E21: =D21*(1+Assumptions!E$51) -> 4243.6 | F21: =E21*(1+Assumptions!F$51) -> 4370.908 | G21: =F21*(1+Assumptions!G$51) -> 4502.0352 | H21: T-12 $7,096. Haircut — volatile and partly a function of the current resident base.
A22: Damage Charges Recovered (net of SODA) | B22: 20467.4 | C22: =15000 -> 15000 | D22: =C22*(1+Assumptions!D$51) -> 15450 | E22: =D22*(1+Assumptions!E$51) -> 15913.5 | F22: =E22*(1+Assumptions!F$51) -> 16390.905 | G22: =F22*(1+Assumptions!G$51) -> 16882.632 | H22: T-12 $20,467. Haircut; should fall as the resident profile improves post-renovation.
A23: Miscellaneous & Utility Reimbursement | B23: 6160.78 | C23: =5000 -> 5000 | D23: =C23*(1+Assumptions!D$51) -> 5150 | E23: =D23*(1+Assumptions!E$51) -> 5304.5 | F23: =E23*(1+Assumptions!F$51) -> 5463.635 | G23: =F23*(1+Assumptions!G$51) -> 5627.5441 | H23: T-12 actual, lightly haircut.
A24: Washer/Dryer Rental | B24: 209 | C24: =0 -> 0 | D24: =C24*(1+Assumptions!D$51) -> 0 | E24: =D24*(1+Assumptions!E$51) -> 0 | F24: =E24*(1+Assumptions!F$51) -> 0 | G24: =F24*(1+Assumptions!G$51) -> 0 | H24: Programme discontinued, and in-unit laundry is now monetised through the rent premium. Set to zero to avoid double-counting.
A25: Total Other Income | B25: =SUM(B12:B24) -> 193597.53 | C25: =SUM(C12:C24) -> 238318.9 | D25: =SUM(D12:D24) -> 268814.38 | E25: =SUM(E12:E24) -> 279458.32 | F25: =SUM(F12:F24) -> 288669.49 | G25: =SUM(G12:G24) -> 298190.1
A26: Per Unit | B26: =B25/Assumptions!$B$17 -> 1640.657 | C26: =C25/Assumptions!$B$17 -> 2019.6517 | D26: =D25/Assumptions!$B$17 -> 2278.088 | E26: =E25/Assumptions!$B$17 -> 2368.2908 | F26: =F25/Assumptions!$B$17 -> 2446.3516 | G26: =G25/Assumptions!$B$17 -> 2527.0347
A27: % of Effective Gross Revenue | C27: =C25/'Annual Model'!C32 -> 0.12326809 | D27: =D25/'Annual Model'!D32 -> 0.12643178 | E27: =E25/'Annual Model'!E32 -> 0.1205756 | F27: =F25/'Annual Model'!F32 -> 0.11990429 | G27: =G25/'Annual Model'!G32 -> 0.1202096
A29: T-12 total operating other income of $193,598 ($1,641/unit) excludes $4,133 of interest income and treats bad debt as a revenue deduction. CBRE's Acquisition Forecast is $263,803 ($2,236/unit); the ancillary upside underwritten here — fully implementing the technology fee and valet trash charge, and introducing pet rent — is the same upside the OM identifies, phased in over the ramps shown above rather than assumed on day one.

Sheet Capex Budget
A1: CHATEAU IN THE WOODS | 4020 Monaco Drive, Indianapolis, IN 46220 | 118 Units
A2: Non-Unit Capital Budget — Deferred Maintenance, Building Systems & Amenities
A3: Blue = hardcoded input / lever · Black = formula · Green = link to another sheet · Yellow fill = key assumption
A5: Item | B5: Total Cost | C5: Per Unit | D5: Yr 1 % | E5: Yr 2 % | F5: Yr 3 % | G5: Yr 4 % | H5: Yr 5 % | I5: Scope and source
A6: Roof replacement — 3.5 of 5 roofs | B6: 360000 | C6: =B6/Assumptions!$B$17 -> 3050.8475 | D6: 0 | E6: 0.4 | F6: 0.4 | G6: 0.2 | H6: 0 | I6: OM: '3.5 of 5 roofs are older than 2006. They are rubber roofs. Assume they will need to be replaced within 10 years.' Building 4 cost $90,000 in 2020 and half of Building 5 cost $54,507 in 2024. A buyer in five years will price any roof we do not replace, so it is underwritten inside the hold.
A7: Asphalt patch, sealcoat & stripe | B7: 150000 | C7: =B7/Assumptions!$B$17 -> 1271.1864 | D7: 1 | E7: 0 | F7: 0 | G7: 0 | H7: 0 | I7: OM immediate need: parking lot and carport areas. The property spent $34,535 on concrete/asphalt in the T-12 alone and $38,749 in 2022 — patch-and-repair, not a programme.
A8: Sump pumps (4) & patio drain cleanout | B8: 40000 | C8: =B8/Assumptions!$B$17 -> 338.98305 | D8: 1 | E8: 0 | F8: 0 | G8: 0 | H8: 0 | I8: OM immediate need: 37 below-grade units, 4 sump pumps needed. Water intrusion risk in below-grade units is a live liability, not a cosmetic item.
A9: Window & sliding patio door glass | B9: 150000 | C9: =B9/Assumptions!$B$17 -> 1271.1864 | D9: 0.34 | E9: 0.33 | F9: 0.33 | G9: 0 | H9: 0 | I9: OM: original aluminium sliders and sliding patio doors, fogged glass replaced on turns. Executed with the interior renovation on each turn.
A10: Building entry system upgrades (20 entries) | B10: 60000 | C10: =B10/Assumptions!$B$17 -> 508.47458 | D10: 0.5 | E10: 0.5 | F10: 0 | G10: 0 | H10: 0 | I10: OM value-add item: upgrade building entry systems across the 20 building entries.
A11: Clubhouse, business centre & fitness refresh | B11: 75000 | C11: =B11/Assumptions!$B$17 -> 635.59322 | D11: 1 | E11: 0 | F11: 0 | G11: 0 | H11: 0 | I11: OM suggested amenity: update clubhouse furniture and decor. Required to support renovated rents.
A12: Dog park, grilling stations & pool deck seating | B12: 50000 | C12: =B12/Assumptions!$B$17 -> 423.72881 | D12: 1 | E12: 0 | F12: 0 | G12: 0 | H12: 0 | I12: OM suggested amenities. Low cost, high visibility on tours; supports the rent premium.
A13: Exterior paint, landscaping & signage refresh | B13: 100000 | C13: =B13/Assumptions!$B$17 -> 847.45763 | D13: 0.5 | E13: 0.5 | F13: 0 | G13: 0 | H13: 0 | I13: Curb appeal. Siding is fibre cement and was replaced in 2020 ($225,000), so this is paint and grounds, not envelope.
A14: Total Non-Unit Capital | B14: =SUM(B6:B13) -> 985000 | C14: =B14/Assumptions!$B$17 -> 8347.4576 | D14: =SUMPRODUCT($B$6:$B$13,D6:D13) -> 446000 | E14: =SUMPRODUCT($B$6:$B$13,E6:E13) -> 273500 | F14: =SUMPRODUCT($B$6:$B$13,F6:F13) -> 193500 | G14: =SUMPRODUCT($B$6:$B$13,G6:G13) -> 72000 | H14: =SUMPRODUCT($B$6:$B$13,H6:H13) -> 0
A15: Check: phasing sums to 100% | B15: =SUM(D14:H14)/B14 -> 1
A17: Excluded from this budget by choice, and therefore from the returns: converting the Building 4042 maintenance storage into two additional apartments, and converting the back 9 carports to garages plus a new maintenance shop. Both are identified in the OM and both are genuine, but at roughly $310,000 and $180,000 respectively they return only about 5-10% on cost against a 12.7% interior programme. They are upside we would pursue with a second look at scope and pricing, not underwritten value.

Sheet Reno Schedule
A1: CHATEAU IN THE WOODS | 4020 Monaco Drive, Indianapolis, IN 46220 | 118 Units
A2: 60-Month Renovation Schedule — Unit Delivery, Capital Spend and Downtime
A3: Blue = hardcoded input / lever · Black = formula · Green = link to another sheet · Yellow fill = key assumption
A5: Month | B5: Date | C5: Model Year | D5: Units Completed | E5: Cumulative Renovated | F5: Renovated Units Earning Premium | G5: Classic Units | H5: Reno'd w/ Existing W/D | I5: Reno'd Needing W/D Add | J5: Interior Capex | K5: W/D Install Capex | L5: Total Reno Capex | M5: Downtime Vac. (% of GPR)
A6: 1 | B6: =EDATE(Assumptions!$B$10,A6-1) -> 46235 | C6: =ROUNDUP(A6/12,0) -> 1 | D6: =IF(A6<Assumptions!$B$31,0,MAX(0,MIN(Assumptions!$B$32,Assumptions!$B$17-0))) -> 0 | E6: =0+D6 -> 0 | F6: =0 -> 0 | G6: =Assumptions!$B$17-F6 -> 118 | H6: =D6*Assumptions!$B$27/Assumptions!$B$17 -> 0 | I6: =D6*Assumptions!$B$28/Assumptions!$B$17 -> 0 | J6: =D6*Assumptions!$B$33 -> 0 | K6: =I6*Assumptions!$B$34 -> 0 | L6: =J6+K6 -> 0 | M6: =D6*Assumptions!$B$41/30/Assumptions!$B$17 -> 0
A7: 2 | B7: =EDATE(Assumptions!$B$10,A7-1) -> 46266 | C7: =ROUNDUP(A7/12,0) -> 1 | D7: =IF(A7<Assumptions!$B$31,0,MAX(0,MIN(Assumptions!$B$32,Assumptions!$B$17-E6))) -> 0 | E7: =E6+D7 -> 0 | F7: =E6 -> 0 | G7: =Assumptions!$B$17-F7 -> 118 | H7: =D7*Assumptions!$B$27/Assumptions!$B$17 -> 0 | I7: =D7*Assumptions!$B$28/Assumptions!$B$17 -> 0 | J7: =D7*Assumptions!$B$33 -> 0 | K7: =I7*Assumptions!$B$34 -> 0 | L7: =J7+K7 -> 0 | M7: =D7*Assumptions!$B$41/30/Assumptions!$B$17 -> 0
A8: 3 | B8: =EDATE(Assumptions!$B$10,A8-1) -> 46296 | C8: =ROUNDUP(A8/12,0) -> 1 | D8: =IF(A8<Assumptions!$B$31,0,MAX(0,MIN(Assumptions!$B$32,Assumptions!$B$17-E7))) -> 5 | E8: =E7+D8 -> 5 | F8: =E7 -> 0 | G8: =Assumptions!$B$17-F8 -> 118 | H8: =D8*Assumptions!$B$27/Assumptions!$B$17 -> 2.2457627 | I8: =D8*Assumptions!$B$28/Assumptions!$B$17 -> 2.7542373 | J8: =D8*Assumptions!$B$33 -> 65000 | K8: =I8*Assumptions!$B$34 -> 13771.186 | L8: =J8+K8 -> 78771.186 | M8: =D8*Assumptions!$B$41/30/Assumptions!$B$17 -> 0.019774011
A9: 4 | B9: =EDATE(Assumptions!$B$10,A9-1) -> 46327 | C9: =ROUNDUP(A9/12,0) -> 1 | D9: =IF(A9<Assumptions!$B$31,0,MAX(0,MIN(Assumptions!$B$32,Assumptions!$B$17-E8))) -> 5 | E9: =E8+D9 -> 10 | F9: =E8 -> 5 | G9: =Assumptions!$B$17-F9 -> 113 | H9: =D9*Assumptions!$B$27/Assumptions!$B$17 -> 2.2457627 | I9: =D9*Assumptions!$B$28/Assumptions!$B$17 -> 2.7542373 | J9: =D9*Assumptions!$B$33 -> 65000 | K9: =I9*Assumptions!$B$34 -> 13771.186 | L9: =J9+K9 -> 78771.186 | M9: =D9*Assumptions!$B$41/30/Assumptions!$B$17 -> 0.019774011
A10: 5 | B10: =EDATE(Assumptions!$B$10,A10-1) -> 46357 | C10: =ROUNDUP(A10/12,0) -> 1 | D10: =IF(A10<Assumptions!$B$31,0,MAX(0,MIN(Assumptions!$B$32,Assumptions!$B$17-E9))) -> 5 | E10: =E9+D10 -> 15 | F10: =E9 -> 10 | G10: =Assumptions!$B$17-F10 -> 108 | H10: =D10*Assumptions!$B$27/Assumptions!$B$17 -> 2.2457627 | I10: =D10*Assumptions!$B$28/Assumptions!$B$17 -> 2.7542373 | J10: =D10*Assumptions!$B$33 -> 65000 | K10: =I10*Assumptions!$B$34 -> 13771.186 | L10: =J10+K10 -> 78771.186 | M10: =D10*Assumptions!$B$41/30/Assumptions!$B$17 -> 0.019774011
A11: 6 | B11: =EDATE(Assumptions!$B$10,A11-1) -> 46388 | C11: =ROUNDUP(A11/12,0) -> 1 | D11: =IF(A11<Assumptions!$B$31,0,MAX(0,MIN(Assumptions!$B$32,Assumptions!$B$17-E10))) -> 5 | E11: =E10+D11 -> 20 | F11: =E10 -> 15 | G11: =Assumptions!$B$17-F11 -> 103 | H11: =D11*Assumptions!$B$27/Assumptions!$B$17 -> 2.2457627 | I11: =D11*Assumptions!$B$28/Assumptions!$B$17 -> 2.7542373 | J11: =D11*Assumptions!$B$33 -> 65000 | K11: =I11*Assumptions!$B$34 -> 13771.186 | L11: =J11+K11 -> 78771.186 | M11: =D11*Assumptions!$B$41/30/Assumptions!$B$17 -> 0.019774011
A12: 7 | B12: =EDATE(Assumptions!$B$10,A12-1) -> 46419 | C12: =ROUNDUP(A12/12,0) -> 1 | D12: =IF(A12<Assumptions!$B$31,0,MAX(0,MIN(Assumptions!$B$32,Assumptions!$B$17-E11))) -> 5 | E12: =E11+D12 -> 25 | F12: =E11 -> 20 | G12: =Assumptions!$B$17-F12 -> 98 | H12: =D12*Assumptions!$B$27/Assumptions!$B$17 -> 2.2457627 | I12: =D12*Assumptions!$B$28/Assumptions!$B$17 -> 2.7542373 | J12: =D12*Assumptions!$B$33 -> 65000 | K12: =I12*Assumptions!$B$34 -> 13771.186 | L12: =J12+K12 -> 78771.186 | M12: =D12*Assumptions!$B$41/30/Assumptions!$B$17 -> 0.019774011
A13: 8 | B13: =EDATE(Assumptions!$B$10,A13-1) -> 46447 | C13: =ROUNDUP(A13/12,0) -> 1 | D13: =IF(A13<Assumptions!$B$31,0,MAX(0,MIN(Assumptions!$B$32,Assumptions!$B$17-E12))) -> 5 | E13: =E12+D13 -> 30 | F13: =E12 -> 25 | G13: =Assumptions!$B$17-F13 -> 93 | H13: =D13*Assumptions!$B$27/Assumptions!$B$17 -> 2.2457627 | I13: =D13*Assumptions!$B$28/Assumptions!$B$17 -> 2.7542373 | J13: =D13*Assumptions!$B$33 -> 65000 | K13: =I13*Assumptions!$B$34 -> 13771.186 | L13: =J13+K13 -> 78771.186 | M13: =D13*Assumptions!$B$41/30/Assumptions!$B$17 -> 0.019774011
A14: 9 | B14: =EDATE(Assumptions!$B$10,A14-1) -> 46478 | C14: =ROUNDUP(A14/12,0) -> 1 | D14: =IF(A14<Assumptions!$B$31,0,MAX(0,MIN(Assumptions!$B$32,Assumptions!$B$17-E13))) -> 5 | E14: =E13+D14 -> 35 | F14: =E13 -> 30 | G14: =Assumptions!$B$17-F14 -> 88 | H14: =D14*Assumptions!$B$27/Assumptions!$B$17 -> 2.2457627 | I14: =D14*Assumptions!$B$28/Assumptions!$B$17 -> 2.7542373 | J14: =D14*Assumptions!$B$33 -> 65000 | K14: =I14*Assumptions!$B$34 -> 13771.186 | L14: =J14+K14 -> 78771.186 | M14: =D14*Assumptions!$B$41/30/Assumptions!$B$17 -> 0.019774011
A15: 10 | B15: =EDATE(Assumptions!$B$10,A15-1) -> 46508 | C15: =ROUNDUP(A15/12,0) -> 1 | D15: =IF(A15<Assumptions!$B$31,0,MAX(0,MIN(Assumptions!$B$32,Assumptions!$B$17-E14))) -> 5 | E15: =E14+D15 -> 40 | F15: =E14 -> 35 | G15: =Assumptions!$B$17-F15 -> 83 | H15: =D15*Assumptions!$B$27/Assumptions!$B$17 -> 2.2457627 | I15: =D15*Assumptions!$B$28/Assumptions!$B$17 -> 2.7542373 | J15: =D15*Assumptions!$B$33 -> 65000 | K15: =I15*Assumptions!$B$34 -> 13771.186 | L15: =J15+K15 -> 78771.186 | M15: =D15*Assumptions!$B$41/30/Assumptions!$B$17 -> 0.019774011
A16: 11 | B16: =EDATE(Assumptions!$B$10,A16-1) -> 46539 | C16: =ROUNDUP(A16/12,0) -> 1 | D16: =IF(A16<Assumptions!$B$31,0,MAX(0,MIN(Assumptions!$B$32,Assumptions!$B$17-E15))) -> 5 | E16: =E15+D16 -> 45 | F16: =E15 -> 40 | G16: =Assumptions!$B$17-F16 -> 78 | H16: =D16*Assumptions!$B$27/Assumptions!$B$17 -> 2.2457627 | I16: =D16*Assumptions!$B$28/Assumptions!$B$17 -> 2.7542373 | J16: =D16*Assumptions!$B$33 -> 65000 | K16: =I16*Assumptions!$B$34 -> 13771.186 | L16: =J16+K16 -> 78771.186 | M16: =D16*Assumptions!$B$41/30/Assumptions!$B$17 -> 0.019774011
A17: 12 | B17: =EDATE(Assumptions!$B$10,A17-1) -> 46569 | C17: =ROUNDUP(A17/12,0) -> 1 | D17: =IF(A17<Assumptions!$B$31,0,MAX(0,MIN(Assumptions!$B$32,Assumptions!$B$17-E16))) -> 5 | E17: =E16+D17 -> 50 | F17: =E16 -> 45 | G17: =Assumptions!$B$17-F17 -> 73 | H17: =D17*Assumptions!$B$27/Assumptions!$B$17 -> 2.2457627 | I17: =D17*Assumptions!$B$28/Assumptions!$B$17 -> 2.7542373 | J17: =D17*Assumptions!$B$33 -> 65000 | K17: =I17*Assumptions!$B$34 -> 13771.186 | L17: =J17+K17 -> 78771.186 | M17: =D17*Assumptions!$B$41/30/Assumptions!$B$17 -> 0.019774011
A18: 13 | B18: =EDATE(Assumptions!$B$10,A18-1) -> 46600 | C18: =ROUNDUP(A18/12,0) -> 2 | D18: =IF(A18<Assumptions!$B$31,0,MAX(0,MIN(Assumptions!$B$32,Assumptions!$B$17-E17))) -> 5 | E18: =E17+D18 -> 55 | F18: =E17 -> 50 | G18: =Assumptions!$B$17-F18 -> 68 | H18: =D18*Assumptions!$B$27/Assumptions!$B$17 -> 2.2457627 | I18: =D18*Assumptions!$B$28/Assumptions!$B$17 -> 2.7542373 | J18: =D18*Assumptions!$B$33 -> 65000 | K18: =I18*Assumptions!$B$34 -> 13771.186 | L18: =J18+K18 -> 78771.186 | M18: =D18*Assumptions!$B$41/30/Assumptions!$B$17 -> 0.019774011
... A65: 60 | B65: =EDATE(Assumptions!$B$10,A65-1) -> 48030 | C65: =ROUNDUP(A65/12,0) -> 5 | D65: =IF(A65<Assumptions!$B$31,0,MAX(0,MIN(Assumptions!$B$32,Assumptions!$B$17-E64))) -> 0 | E65: =E64+D65 -> 118 | F65: =E64 -> 118 | G65: =Assumptions!$B$17-F65 -> 0 | H65: =D65*Assumptions!$B$27/Assumptions!$B$17 -> 0 | I65: =D65*Assumptions!$B$28/Assumptions!$B$17 -> 0 | J65: =D65*Assumptions!$B$33 -> 0 | K65: =I65*Assumptions!$B$34 -> 0 | L65: =J65+K65 -> 0 | M65: =D65*Assumptions!$B$41/30/Assumptions!$B$17 -> 0
A66: Total | D66: =SUM(D6:D65) -> 118 | H66: =SUM(H6:H65) -> 53 | I66: =SUM(I6:I65) -> 65 | J66: =SUM(J6:J65) -> 1534000 | K66: =SUM(K6:K65) -> 325000 | L66: =SUM(L6:L65) -> 1859000
A68: ANNUAL SUMMARY — FEEDS THE CASH FLOW MODEL | C68: Year 1 | D68: Year 2 | E68: Year 3 | F68: Year 4 | G68: Year 5
A69: Units Completed in Year | C69: =SUMIFS($D$6:$D$65,$C$6:$C$65,1) -> 50 | D69: =SUMIFS($D$6:$D$65,$C$6:$C$65,2) -> 60 | E69: =SUMIFS($D$6:$D$65,$C$6:$C$65,3) -> 8 | F69: =SUMIFS($D$6:$D$65,$C$6:$C$65,4) -> 0 | G69: =SUMIFS($D$6:$D$65,$C$6:$C$65,5) -> 0
A70: Cumulative Renovated at Year End | C70: =SUMIFS($D$6:$D$65,$C$6:$C$65,"<="&1) -> 50 | D70: =SUMIFS($D$6:$D$65,$C$6:$C$65,"<="&2) -> 110 | E70: =SUMIFS($D$6:$D$65,$C$6:$C$65,"<="&3) -> 118 | F70: =SUMIFS($D$6:$D$65,$C$6:$C$65,"<="&4) -> 118 | G70: =SUMIFS($D$6:$D$65,$C$6:$C$65,"<="&5) -> 118
A71: Average Renovated Units Earning Premium | C71: =AVERAGEIFS($F$6:$F$65,$C$6:$C$65,1) -> 18.75 | D71: =AVERAGEIFS($F$6:$F$65,$C$6:$C$65,2) -> 77.5 | E71: =AVERAGEIFS($F$6:$F$65,$C$6:$C$65,3) -> 117.08333 | F71: =AVERAGEIFS($F$6:$F$65,$C$6:$C$65,4) -> 118 | G71: =AVERAGEIFS($F$6:$F$65,$C$6:$C$65,5) -> 118
A72: Average Classic Units | C72: =AVERAGEIFS($G$6:$G$65,$C$6:$C$65,1) -> 99.25 | D72: =AVERAGEIFS($G$6:$G$65,$C$6:$C$65,2) -> 40.5 | E72: =AVERAGEIFS($G$6:$G$65,$C$6:$C$65,3) -> 0.91666667 | F72: =AVERAGEIFS($G$6:$G$65,$C$6:$C$65,4) -> 0 | G72: =AVERAGEIFS($G$6:$G$65,$C$6:$C$65,5) -> 0
A73: Renovation Capital Spend | C73: =SUMIFS($L$6:$L$65,$C$6:$C$65,1) -> 787711.86 | D73: =SUMIFS($L$6:$L$65,$C$6:$C$65,2) -> 945254.24 | E73: =SUMIFS($L$6:$L$65,$C$6:$C$65,3) -> 126033.9 | F73: =SUMIFS($L$6:$L$65,$C$6:$C$65,4) -> 0 | G73: =SUMIFS($L$6:$L$65,$C$6:$C$65,5) -> 0
A74: Renovation Downtime Vacancy (% of GPR) | C74: =AVERAGEIFS($M$6:$M$65,$C$6:$C$65,1) -> 0.016478343 | D74: =AVERAGEIFS($M$6:$M$65,$C$6:$C$65,2) -> 0.019774011 | E74: =AVERAGEIFS($M$6:$M$65,$C$6:$C$65,3) -> 0.0026365348 | F74: =AVERAGEIFS($M$6:$M$65,$C$6:$C$65,4) -> 0 | G74: =AVERAGEIFS($M$6:$M$65,$C$6:$C$65,5) -> 0
A76: A unit renovated during month m begins earning the renovated rent in month m+1, so column F (renovated units earning the premium) is the prior month's cumulative count. Renovations are executed on natural turnover at 5 units a month, completing all 118 units in month 26.

Sheet Annual Model
A1: CHATEAU IN THE WOODS | 4020 Monaco Drive, Indianapolis, IN 46220 | 118 Units
A2: Five-Year Operating Cash Flow — August 2026 through July 2031
A3: Blue = hardcoded input / lever · Black = formula · Green = link to another sheet · Yellow fill = key assumption
B5: Basis | C5: Year 1 | D5: Year 2 | E5: Year 3 | F5: Year 4 | G5: Year 5 | H5: Year 6 (exit)
A6: Period Ending | C6: =EDATE(Assumptions!$B$10,12-1) -> 46569 | D6: =EDATE(Assumptions!$B$10,24-1) -> 46935 | E6: =EDATE(Assumptions!$B$10,36-1) -> 47300 | F6: =EDATE(Assumptions!$B$10,48-1) -> 47665 | G6: =EDATE(Assumptions!$B$10,60-1) -> 48030 | H6: =EDATE(Assumptions!$B$10,72-1) -> 48396
A7: MARKET RENT INDEXATION
A8: Market Rent Growth | B8: Assumptions | C8: =Assumptions!C$46 -> 0.03 | D8: =Assumptions!D$46 -> 0.03 | E8: =Assumptions!E$46 -> 0.03 | F8: =Assumptions!F$46 -> 0.03 | G8: =Assumptions!G$46 -> 0.03 | H8: =Assumptions!G$46 -> 0.03
A9: Rent Index — End of Year | B9: Prior year index × (1 + growth) | C9: =1*(1+C8) -> 1.03 | D9: =C9*(1+D8) -> 1.0609 | E9: =D9*(1+E8) -> 1.092727 | F9: =E9*(1+F8) -> 1.1255088 | G9: =F9*(1+G8) -> 1.1592741 | H9: =G9*(1+H8) -> 1.1940523
A10: Rent Factor — Mid-Year Convention | B10: SQRT(prior year-end index × this year-end index) | C10: =SQRT(1*C9) -> 1.0148892 | D10: =SQRT(C9*D9) -> 1.0453358 | E10: =SQRT(D9*E9) -> 1.0766959 | F10: =SQRT(E9*F9) -> 1.1089968 | G10: =SQRT(F9*G9) -> 1.1422667 | H10: =SQRT(G9*H9) -> 1.1765347
A12: UNIT POSITION
A13: Average Classic Units | B13: Reno Schedule | C13: ='Reno Schedule'!C$72 -> 99.25 | D13: ='Reno Schedule'!D$72 -> 40.5 | E13: ='Reno Schedule'!E$72 -> 0.91666667 | F13: ='Reno Schedule'!F$72 -> 0 | G13: ='Reno Schedule'!G$72 -> 0 | H13: =0 -> 0
A14: Average Renovated Units | B14: Reno Schedule | C14: ='Reno Schedule'!C$71 -> 18.75 | D14: ='Reno Schedule'!D$71 -> 77.5 | E14: ='Reno Schedule'!E$71 -> 117.08333 | F14: ='Reno Schedule'!F$71 -> 118 | G14: ='Reno Schedule'!G$71 -> 118 | H14: =Assumptions!$B$17 -> 118
A15: Units Renovated in Year | B15: Reno Schedule | C15: ='Reno Schedule'!C$69 -> 50 | D15: ='Reno Schedule'!D$69 -> 60 | E15: ='Reno Schedule'!E$69 -> 8 | F15: ='Reno Schedule'!F$69 -> 0 | G15: ='Reno Schedule'!G$69 -> 0 | H15: =0 -> 0
A16: Cumulative Renovated (% of portfolio) | B16: Reno Schedule | C16: ='Reno Schedule'!C$70/Assumptions!$B$17 -> 0.42372881 | D16: ='Reno Schedule'!D$70/Assumptions!$B$17 -> 0.93220339 | E16: ='Reno Schedule'!E$70/Assumptions!$B$17 -> 1 | F16: ='Reno Schedule'!F$70/Assumptions!$B$17 -> 1 | G16: ='Reno Schedule'!G$70/Assumptions!$B$17 -> 1 | H16: =1 -> 1
A18: REVENUE
A19: Gross Potential Rent — Classic Units | B19: Avg classic units × avg classic market rent × 12 × rent factor | C19: =C13*'Unit Mix'!$D$18*12*C10 -> 1571711.4 | D19: =D13*'Unit Mix'!$D$18*12*D10 -> 660593.87 | E19: =E13*'Unit Mix'!$D$18*12*E10 -> 15400.264 | F19: =F13*'Unit Mix'!$D$18*12*F10 -> 0 | G19: =G13*'Unit Mix'!$D$18*12*G10 -> 0 | H19: =0 -> 0
A20: Gross Potential Rent — Renovated Units | B20: Avg renovated units × avg renovated market rent × 12 × rent factor | C20: =C14*'Unit Mix'!$D$19*12*C10 -> 334900.52 | D20: =D14*'Unit Mix'!$D$19*12*D10 -> 1425783.1 | E20: =E14*'Unit Mix'!$D$19*12*E10 -> 2218625.9 | F20: =F14*'Unit Mix'!$D$19*12*F10 -> 2303075.8 | G20: =G14*'Unit Mix'!$D$19*12*G10 -> 2372168.1 | H20: =H14*'Unit Mix'!$D$19*12*H10 -> 2443333.1
A21: Gross Potential Rent | C21: =C19+C20 -> 1906611.9 | D21: =D19+D20 -> 2086377 | E21: =E19+E20 -> 2234026.2 | F21: =F19+F20 -> 2303075.8 | G21: =G19+G20 -> 2372168.1 | H21: =H19+H20 -> 2443333.1
A22: Average Monthly Rent per Unit | B22: GPR / units / 12 | C22: =C21/Assumptions!$B$17/12 -> 1346.4773 | D22: =D21/Assumptions!$B$17/12 -> 1473.4301 | E22: =E21/Assumptions!$B$17/12 -> 1577.7021 | F22: =F21/Assumptions!$B$17/12 -> 1626.466 | G22: =G21/Assumptions!$B$17/12 -> 1675.2599 | H22: =H21/Assumptions!$B$17/12 -> 1725.5177
A23: Less: Loss to Lease | B23: % of GPR (Assumptions) | C23: =-C21*Assumptions!C$47 -> -41945.462 | D23: =-D21*Assumptions!D$47 -> -41727.54 | E23: =-E21*Assumptions!E$47 -> -39095.458 | F23: =-F21*Assumptions!F$47 -> -34546.137 | G23: =-G21*Assumptions!G$47 -> -35582.521 | H23: =-H21*Assumptions!G$47 -> -36649.997
A24: Less: Operating Physical Vacancy | B24: % of GPR (Assumptions) | C24: =-C21*Assumptions!C$48 -> -95330.596 | D24: =-D21*Assumptions!D$48 -> -104318.85 | E24: =-E21*Assumptions!E$48 -> -111701.31 | F24: =-F21*Assumptions!F$48 -> -115153.79 | G24: =-G21*Assumptions!G$48 -> -118608.4 | H24: =-H21*Assumptions!G$48 -> -122166.66
A25: Less: Renovation Downtime Vacancy | B25: Reno Schedule × GPR | C25: =-C21*'Reno Schedule'!C$74 -> -31417.805 | D25: =-D21*'Reno Schedule'!D$74 -> -41256.043 | E25: =-E21*'Reno Schedule'!E$74 -> -5890.0878 | F25: =-F21*'Reno Schedule'!F$74 -> 0 | G25: =-G21*'Reno Schedule'!G$74 -> 0 | H25: =0 -> 0
A26: Less: Concessions | B26: % of GPR (Assumptions) | C26: =-C21*Assumptions!C$49 -> -14299.589 | D26: =-D21*Assumptions!D$49 -> -15647.828 | E26: =-E21*Assumptions!E$49 -> -11170.131 | F26: =-F21*Assumptions!F$49 -> -11515.379 | G26: =-G21*Assumptions!G$49 -> -11860.84 | H26: =-H21*Assumptions!G$49 -> -12216.666
A27: Less: Bad Debt | B27: % of GPR (Assumptions) | C27: =-C21*Assumptions!C$50 -> -28599.179 | D27: =-D21*Assumptions!D$50 -> -26079.713 | E27: =-E21*Assumptions!E$50 -> -27925.327 | F27: =-F21*Assumptions!F$50 -> -23030.758 | G27: =-G21*Assumptions!G$50 -> -23721.681 | H27: =-H21*Assumptions!G$50 -> -24433.331
A28: Net Rental Income | C28: =SUM(C21:C27)-C22 -> 1695019.3 | D28: =SUM(D21:D27)-D22 -> 1857347 | E28: =SUM(E21:E27)-E22 -> 2038243.9 | F28: =SUM(F21:F27)-F22 -> 2118829.7 | G28: =SUM(G21:G27)-G22 -> 2182394.6 | H28: =SUM(H21:H27)-H22 -> 2247866.5
A29: Economic Occupancy | B29: NRI / GPR | C29: =C28/C21 -> 0.88902166 | D29: =D28/D21 -> 0.89022599 | E29: =E28/E21 -> 0.91236347 | F29: =F28/F21 -> 0.92 | G29: =G28/G21 -> 0.92 | H29: =H28/H21 -> 0.92
A30: Physical Occupancy | B30: 1 - operating - downtime vacancy | C30: =1+(C24+C25)/C21 -> 0.93352166 | D30: =1+(D24+D25)/D21 -> 0.93022599 | E30: =1+(E24+E25)/E21 -> 0.94736347 | F30: =1+(F24+F25)/F21 -> 0.95 | G30: =1+(G24+G25)/G21 -> 0.95 | H30: =1+(H24+H25)/H21 -> 0.95
A31: Other Income | B31: Other Income tab | C31: ='Other Income'!C$25 -> 238318.9 | D31: ='Other Income'!D$25 -> 268814.38 | E31: ='Other Income'!E$25 -> 279458.32 | F31: ='Other Income'!F$25 -> 288669.49 | G31: ='Other Income'!G$25 -> 298190.1 | H31: ='Other Income'!G$25*(1+Assumptions!G$51) -> 307135.8
A32: Effective Gross Revenue | C32: =C28+C31 -> 1933338.2 | D32: =D28+D31 -> 2126161.4 | E32: =E28+E31 -> 2317702.2 | F32: =F28+F31 -> 2407499.2 | G32: =G28+G31 -> 2480584.7 | H32: =H28+H31 -> 2555002.3
A34: OPERATING EXPENSES
A35: Payroll | B35: Year 1 input, grown | C35: =Assumptions!$B$55 -> 235000 | D35: =C35*(1+Assumptions!$C$55) -> 243225 | E35: =D35*(1+Assumptions!$C$55) -> 251737.88 | F35: =E35*(1+Assumptions!$C$55) -> 260548.7 | G35: =F35*(1+Assumptions!$C$55) -> 269667.91 | H35: =G35*(1+Assumptions!$C$55) -> 279106.28
A36: Property Management Fee | B36: % of effective gross revenue | C36: =C32*Assumptions!$B$56 -> 77333.528 | D36: =D32*Assumptions!$B$56 -> 85046.457 | E36: =E32*Assumptions!$B$56 -> 92708.087 | F36: =F32*Assumptions!$B$56 -> 96299.969 | G36: =G32*Assumptions!$B$56 -> 99223.389 | H36: =H32*Assumptions!$B$56 -> 102200.09
A37: Marketing & Advertising | B37: Year 1 input, grown | C37: =Assumptions!$B$57 -> 28000 | D37: =C37*(1+Assumptions!$C$57) -> 28840 | E37: =D37*(1+Assumptions!$C$57) -> 29705.2 | F37: =E37*(1+Assumptions!$C$57) -> 30596.356 | G37: =F37*(1+Assumptions!$C$57) -> 31514.247 | H37: =G37*(1+Assumptions!$C$57) -> 32459.674
A38: General & Administrative | B38: Year 1 input, grown | C38: =Assumptions!$B$58 -> 50000 | D38: =C38*(1+Assumptions!$C$58) -> 51500 | E38: =D38*(1+Assumptions!$C$58) -> 53045 | F38: =E38*(1+Assumptions!$C$58) -> 54636.35 | G38: =F38*(1+Assumptions!$C$58) -> 56275.44 | H38: =G38*(1+Assumptions!$C$58) -> 57963.704
A39: Bulk Internet | B39: $27.95/unit/month stabilised, grown | C39: =Assumptions!$B$59 -> 39577 | D39: =C39*(1+Assumptions!$C$59) -> 40764.31 | E39: =D39*(1+Assumptions!$C$59) -> 41987.239 | F39: =E39*(1+Assumptions!$C$59) -> 43246.856 | G39: =F39*(1+Assumptions!$C$59) -> 44544.262 | H39: =G39*(1+Assumptions!$C$59) -> 45880.59
A40: Electricity | B40: Year 1 input, grown | C40: =Assumptions!$B$60 -> 31000 | D40: =C40*(1+Assumptions!$C$60) -> 31930 | E40: =D40*(1+Assumptions!$C$60) -> 32887.9 | F40: =E40*(1+Assumptions!$C$60) -> 33874.537 | G40: =F40*(1+Assumptions!$C$60) -> 34890.773 | H40: =G40*(1+Assumptions!$C$60) -> 35937.496
A41: Gas | B41: Year 1 input, grown | C41: =Assumptions!$B$61 -> 16000 | D41: =C41*(1+Assumptions!$C$61) -> 16480 | E41: =D41*(1+Assumptions!$C$61) -> 16974.4 | F41: =E41*(1+Assumptions!$C$61) -> 17483.632 | G41: =F41*(1+Assumptions!$C$61) -> 18008.141 | H41: =G41*(1+Assumptions!$C$61) -> 18548.385
A42: Water & Sewer | B42: Year 1 input, grown; 85% recovered in Other Income | C42: =Assumptions!$B$62 -> 90000 | D42: =C42*(1+Assumptions!$C$62) -> 93600 | E42: =D42*(1+Assumptions!$C$62) -> 97344 | F42: =E42*(1+Assumptions!$C$62) -> 101237.76 | G42: =F42*(1+Assumptions!$C$62) -> 105287.27 | H42: =G42*(1+Assumptions!$C$62) -> 109498.76
A43: Repairs & Maintenance | B43: Year 1 input, grown | C43: =Assumptions!$B$63 -> 255000 | D43: =C43*(1+Assumptions!$C$63) -> 262650 | E43: =D43*(1+Assumptions!$C$63) -> 270529.5 | F43: =E43*(1+Assumptions!$C$63) -> 278645.39 | G43: =F43*(1+Assumptions!$C$63) -> 287004.75 | H43: =G43*(1+Assumptions!$C$63) -> 295614.89
A44: Insurance | B44: Year 1 input, grown | C44: =Assumptions!$B$64 -> 95000 | D44: =C44*(1+Assumptions!$C$64) -> 99750 | E44: =D44*(1+Assumptions!$C$64) -> 104737.5 | F44: =E44*(1+Assumptions!$C$64) -> 109974.38 | G44: =F44*(1+Assumptions!$C$64) -> 115473.09 | H44: =G44*(1+Assumptions!$C$64) -> 121246.75
A45: Real Estate Taxes | B45: Explicit annual schedule (reassessment on sale) | C45: =Assumptions!C$66 -> 140000 | D45: =Assumptions!D$66 -> 170000 | E45: =Assumptions!E$66 -> 190000 | F45: =Assumptions!F$66 -> 200000 | G45: =Assumptions!G$66 -> 210000 | H45: =Assumptions!G$66*1.05 -> 220500
A46: Total Operating Expenses | C46: =SUM(C35:C45) -> 1056910.5 | D46: =SUM(D35:D45) -> 1123785.8 | E46: =SUM(E35:E45) -> 1181656.7 | F46: =SUM(F35:F45) -> 1226543.9 | G46: =SUM(G35:G45) -> 1271889.3 | H46: =SUM(H35:H45) -> 1318956.6
A47: Per Unit | C47: =C46/Assumptions!$B$17 -> 8956.8689 | D47: =D46/Assumptions!$B$17 -> 9523.6082 | E47: =E46/Assumptions!$B$17 -> 10014.04 | F47: =F46/Assumptions!$B$17 -> 10394.44 | G47: =G46/Assumptions!$B$17 -> 10778.723 | H47: =H46/Assumptions!$B$17 -> 11177.598
A48: Operating Expense Ratio | B48: Total opex / EGR | C48: =C46/C32 -> 0.54667649 | D48: =D46/D32 -> 0.52855148 | E48: =E46/E32 -> 0.50983975 | F48: =F46/F32 -> 0.50946804 | G48: =G46/G32 -> 0.51273768 | H48: =H46/H32 -> 0.51622523
A50: NET OPERATING INCOME | C50: =C32-C46 -> 876427.66 | D50: =D32-D46 -> 1002375.7 | E50: =E32-E46 -> 1136045.5 | F50: =F32-F46 -> 1180955.3 | G50: =G32-G46 -> 1208695.5 | H50: =H32-H46 -> 1236045.6
A51: NOI per Unit | C51: =C50/Assumptions!$B$17 -> 7427.3531 | D51: =D50/Assumptions!$B$17 -> 8494.709 | E51: =E50/Assumptions!$B$17 -> 9627.504 | F51: =F50/Assumptions!$B$17 -> 10008.096 | G51: =G50/Assumptions!$B$17 -> 10243.182 | H51: =H50/Assumptions!$B$17 -> 10474.963
A52: NOI Margin | C52: =C50/C32 -> 0.45332351 | D52: =D50/D32 -> 0.47144852 | E52: =E50/E32 -> 0.49016025 | F52: =F50/F32 -> 0.49053196 | G52: =G50/G32 -> 0.48726232
A53: NOI Growth | C53: ="n/a" -> n/a | D53: =D50/C50-1 -> 0.14370609 | E53: =E50/D50-1 -> 0.13335301 | F53: =F50/E50-1 -> 0.039531727 | G53: =G50/F50-1 -> 0.023489586
A54: Yield on Purchase Price | B54: NOI / purchase price | C54: =C50/Assumptions!$B$6 -> 0.061720258 | D54: =D50/Assumptions!$B$6 -> 0.070589835 | E54: =E50/Assumptions!$B$6 -> 0.080003202 | F54: =F50/Assumptions!$B$6 -> 0.083165867 | G54: =G50/Assumptions!$B$6 -> 0.085119398
A55: Yield on Total Cost | B55: NOI / (price + all capital) | C55: =C50/Returns!$C$22 -> 0.050744096 | D55: =D50/Returns!$C$22 -> 0.058036331 | E55: =E50/Returns!$C$22 -> 0.065775651 | F55: =F50/Returns!$C$22 -> 0.068375876 | G55: =G50/Returns!$C$22 -> 0.069981997
A57: BELOW NOI
A58: Less: Replacement Reserves | B58: $/unit/year, grown | C58: =-Assumptions!$B$67*Assumptions!$B$17 -> -35400 | D58: =C58*(1+Assumptions!D$51) -> -36462 | E58: =D58*(1+Assumptions!E$51) -> -37555.86 | F58: =E58*(1+Assumptions!F$51) -> -38682.536 | G58: =F58*(1+Assumptions!G$51) -> -39843.012
A59: Net Cash Flow before Debt Service | C59: =C50+C58 -> 841027.66 | D59: =D50+D58 -> 965913.66 | E59: =E50+E58 -> 1098489.6 | F59: =F50+F58 -> 1142272.8 | G59: =G50+G58 -> 1168852.4
A60: Less: Interest Expense | B60: Loan balance × rate (interest-only) | C60: =-Returns!$C$27*Assumptions!$B$73 -> -640887.73 | D60: =-Returns!$C$27*Assumptions!$B$73 -> -640887.73 | E60: =-Returns!$C$27*Assumptions!$B$73 -> -640887.73 | F60: =-Returns!$C$27*Assumptions!$B$73 -> -640887.73 | G60: =-Returns!$C$27*Assumptions!$B$73 -> -640887.73
A61: Cash Flow to Equity (operations) | C61: =C59+C60 -> 200139.93 | D61: =D59+D60 -> 325025.93 | E61: =E59+E60 -> 457601.88 | F61: =F59+F60 -> 501385.04 | G61: =G59+G60 -> 527964.72
A62: Debt Service Coverage Ratio | B62: NOI / interest | C62: =C50/-C60 -> 1.3675214 | D62: =D50/-D60 -> 1.5640425 | E62: =E50/-E60 -> 1.7726123 | F62: =F50/-F60 -> 1.8426867 | G62: =G50/-G60 -> 1.8859707
A63: Debt Yield | B63: NOI / loan balance | C63: =C50/Returns!$C$27 -> 0.08 | D63: =D50/Returns!$C$27 -> 0.091496487 | E63: =E50/Returns!$C$27 -> 0.10369782 | F63: =F50/Returns!$C$27 -> 0.10779717 | G63: =G50/Returns!$C$27 -> 0.11032928
A64: Cash-on-Cash Return | B64: CF to equity / sponsor equity | C64: =C61/Returns!$C$17 -> 0.029699959 | D64: =D61/Returns!$C$17 -> 0.048232537 | E64: =E61/Returns!$C$17 -> 0.067906273 | F64: =F61/Returns!$C$17 -> 0.074403518 | G64: =G61/Returns!$C$17 -> 0.078347834
A66: MEMO — CAPITAL SPEND (funded at closing per Sources & Uses)
A67: Renovation Capital | B67: Reno Schedule | C67: ='Reno Schedule'!C$73 -> 787711.86 | D67: ='Reno Schedule'!D$73 -> 945254.24 | E67: ='Reno Schedule'!E$73 -> 126033.9 | F67: ='Reno Schedule'!F$73 -> 0 | G67: ='Reno Schedule'!G$73 -> 0
A68: Non-Unit / Deferred Maintenance Capital | B68: Capex Budget | C68: ='Capex Budget'!D14 -> 446000 | D68: ='Capex Budget'!E14 -> 273500 | E68: ='Capex Budget'!F14 -> 193500 | F68: ='Capex Budget'!G14 -> 72000 | G68: ='Capex Budget'!H14 -> 0
A69: Contingency | B69: % of capital spend | C69: =(C67+C68)*Assumptions!$B$42 -> 98696.949 | D69: =(D67+D68)*Assumptions!$B$42 -> 97500.339 | E69: =(E67+E68)*Assumptions!$B$42 -> 25562.712 | F69: =(F67+F68)*Assumptions!$B$42 -> 5760 | G69: =(G67+G68)*Assumptions!$B$42 -> 0
A70: Total Capital Deployed | C70: =SUM(C67:C69) -> 1332408.8 | D70: =SUM(D67:D69) -> 1316254.6 | E70: =SUM(E67:E69) -> 345096.61 | F70: =SUM(F67:F69) -> 77760 | G70: =SUM(G67:G69) -> 0
A72: Capital is deployed over the schedule shown above but funded in full at closing in Sources & Uses, so it is not deducted again from annual cash flow. That convention is conservative: it puts 100% of the equity out on day one and gives the model no benefit from the real timing of draws.

Sheet Returns
A1: CHATEAU IN THE WOODS | 4020 Monaco Drive, Indianapolis, IN 46220 | 118 Units
A2: Sources & Uses, Debt, Exit Valuation and Returns
A3: Blue = hardcoded input / lever · Black = formula · Green = link to another sheet · Yellow fill = key assumption
A5: SOURCES & USES
A6: USES | C6: Amount | D6: Per Unit | E6: % of Total | J6: Note
A7: Purchase Price | C7: =Assumptions!$B$6 -> 14200000 | D7: =C7/Assumptions!$B$17 -> 120338.98 | E7: =C7/$C$13 -> 0.8025286 | J7: Implied by the OM's 6.9% Year-1 cap rate on CBRE's forecast NOI.
A8: Acquisition Costs | C8: =Assumptions!$B$6*Assumptions!$B$9 -> 213000 | D8: =C8/Assumptions!$B$17 -> 1805.0847 | E8: =C8/$C$13 -> 0.012037929 | J8: 1.5% of price.
A9: Renovation Capital (118 units) | C9: ='Unit Mix'!$D$21 -> 1859000 | D9: =C9/Assumptions!$B$17 -> 15754.237 | E9: =C9/$C$13 -> 0.10506343 | J9: $13,000/unit interior plus $5,000/unit for the 65 units gaining laundry.
A10: Non-Unit / Deferred Maintenance Capital | C10: ='Capex Budget'!B14 -> 985000 | D10: =C10/Assumptions!$B$17 -> 8347.4576 | E10: =C10/$C$13 -> 0.055668357 | J10: Roofs, asphalt, sump pumps, glass, entries, amenities.
A11: Capital Contingency | C11: =('Unit Mix'!$D$21+'Capex Budget'!B14)*Assumptions!$B$42 -> 227520 | D11: =C11/Assumptions!$B$17 -> 1928.1356 | E11: =C11/$C$13 -> 0.012858543 | J11: 8% of all capital.
A12: Financing Costs | C12: =C27*Assumptions!$B$74+Assumptions!$B$75 -> 209553.46 | D12: =C12/Assumptions!$B$17 -> 1775.8768 | E12: =C12/$C$13 -> 0.011843144 | J12: 1% origination plus lender legal, appraisal, engineering and escrow set-up.
A13: Total Uses | C13: =SUM(C7:C12) -> 17694073 | D13: =C13/Assumptions!$B$17 -> 149949.78 | E13: =SUM(E7:E12) -> 1
A15: SOURCES | C15: Amount | D15: Per Unit | E15: % of Total
A16: Senior / Value-Add Loan | C16: =C27 -> 10955346 | D16: =C16/Assumptions!$B$17 -> 92841.914 | E16: =C16/$C$18 -> 0.6191534
A17: Sponsor Equity | C17: =C13-C16 -> 6738727.6 | D17: =C17/Assumptions!$B$17 -> 57107.861 | E17: =C17/$C$18 -> 0.3808466
A18: Total Sources | C18: =SUM(C16:C17) -> 17694073 | D18: =C18/Assumptions!$B$17 -> 149949.78 | E18: =SUM(E16:E17) -> 1
A19: Check: sources = uses | C19: =C18-C13 -> 0
A21: TOTAL CAPITALISATION & DEBT TERMS
A22: Total Capitalised Cost (price + all capital) | C22: =Assumptions!$B$6+'Unit Mix'!$D$21+'Capex Budget'!B14+C11 -> 17271520 | J22: Basis for loan-to-cost sizing and the yield-on-cost metric.
A23: Total Cost per Unit | C23: =C22/Assumptions!$B$17 -> 146368.81
A24: Loan Sizing Test 1 — Maximum Loan to Cost | C24: =C22*Assumptions!$B$70 -> 11226488 | J24: Maximum loan-to-cost applied to total capitalised cost.
A25: Loan Sizing Test 2 — Minimum Debt Yield | C25: ='Annual Model'!C50/Assumptions!$B$71 -> 10955346 | J25: Year-1 NOI divided by the minimum debt yield.
A26: Loan Sizing Test 3 — Minimum DSCR | C26: ='Annual Model'!C50/(Assumptions!$B$72*Assumptions!$B$73) -> 11985336 | J26: Year-1 NOI divided by (minimum DSCR × interest rate), interest-only.
A27: Loan Amount (lesser of the three tests) | C27: =MIN(C24,C25,C26) -> 10955346 | J27: Sizing to the lesser of the three tests, as a lender would.
A28: Effective Loan to Cost | C28: =C27/C22 -> 0.6343012
A29: Loan per Unit | C29: =C27/Assumptions!$B$17 -> 92841.914
A30: Interest Rate (fixed, interest-only) | C30: =Assumptions!$B$73 -> 0.0585
A31: Annual Interest Expense | C31: =C27*Assumptions!$B$73 -> 640887.73
A32: Year-1 Debt Yield | C32: ='Annual Model'!C50/C27 -> 0.08 | J32: Lender test: NOI / loan.
A33: Year-1 DSCR | C33: ='Annual Model'!C50/C31 -> 1.3675214 | J33: Lender test: NOI / interest.
A35: EXIT VALUATION — END OF YEAR 5
A36: Year-6 Forward NOI | C36: ='Annual Model'!H50 -> 1236045.6 | J36: Next-twelve-months NOI a buyer would capitalise.
A37: Exit Cap Rate | C37: =Assumptions!$B$12 -> 0.0675 | J37: 15 bps inside the going-in cap, reflecting a fully renovated asset with in-unit laundry throughout.
A38: Gross Sale Value | C38: =C36/Assumptions!$B$12 -> 18311787
A39: Value per Unit | C39: =C38/Assumptions!$B$17 -> 155184.64
A40: Less: Cost of Sale | C40: =-C38*Assumptions!$B$13 -> -274676.81
A41: Net Sale Proceeds | C41: =C38+C40 -> 18037111
A42: Less: Loan Repayment | C42: =-C27 -> -10955346
A43: Net Proceeds to Equity | C43: =C41+C42 -> 7081764.7
A44: Value Created over Total Cost | C44: =C41-C22-Assumptions!$B$6*Assumptions!$B$9 -> 552590.55 | J44: Net sale proceeds less total capitalised cost and acquisition costs.
A46: CASH FLOWS AND RETURNS
C47: At Close | D47: Year 1 | E47: Year 2 | F47: Year 3 | G47: Year 4 | H47: Year 5 | I47: Total
A48: UNLEVERED
A49: Net Cash Flow before Debt Service | C49: =-(C22+Assumptions!$B$6*Assumptions!$B$9) -> -17484520 | D49: ='Annual Model'!C59 -> 841027.66 | E49: ='Annual Model'!D59 -> 965913.66 | F49: ='Annual Model'!E59 -> 1098489.6 | G49: ='Annual Model'!F59 -> 1142272.8 | H49: ='Annual Model'!G59 -> 1168852.4
A50: Net Sale Proceeds | H50: =C41 -> 18037111
A51: Total Unlevered Cash Flow | C51: =C49 -> -17484520 | D51: =SUM(D49:D50) -> 841027.66 | E51: =SUM(E49:E50) -> 965913.66 | F51: =SUM(F49:F50) -> 1098489.6 | G51: =SUM(G49:G50) -> 1142272.8 | H51: =SUM(H49:H50) -> 19205963 | I51: =SUM(C51:H51) -> 5769146.7
A53: LEVERED
A54: Sponsor Equity | C54: =-C17 -> -6738727.6
A55: Cash Flow to Equity (operations) | D55: ='Annual Model'!C61 -> 200139.93 | E55: ='Annual Model'!D61 -> 325025.93 | F55: ='Annual Model'!E61 -> 457601.88 | G55: ='Annual Model'!F61 -> 501385.04 | H55: ='Annual Model'!G61 -> 527964.72
A56: Net Proceeds to Equity at Sale | H56: =C43 -> 7081764.7
A57: Total Levered Cash Flow | C57: =C54 -> -6738727.6 | D57: =SUM(D55:D56) -> 200139.93 | E57: =SUM(E55:E56) -> 325025.93 | F57: =SUM(F55:F56) -> 457601.88 | G57: =SUM(G55:G56) -> 501385.04 | H57: =SUM(H55:H56) -> 7609729.5 | I57: =SUM(C57:H57) -> 2355154.6
A58: Cash-on-Cash Return | D58: =D55/C17 -> 0.029699959 | E58: =E55/C17 -> 0.048232537 | F58: =F55/C17 -> 0.067906273 | G58: =G55/C17 -> 0.074403518 | H58: =H55/C17 -> 0.078347834
A60: RETURN SUMMARY
C61: Unlevered | D61: Levered | J61: Note
A62: Internal Rate of Return | C62: =IRR(C51:H51) -> 0.064624245 | D62: =IRR(C57:H57) -> 0.067006663
A63: Equity Multiple | C63: =SUM(D51:H51)/-C51 -> 1.3299574 | D63: =SUM(D57:H57)/-C57 -> 1.3494954
A64: Profit | C64: =I51 -> 5769146.7 | D64: =I57 -> 2355154.6
A65: Average Cash-on-Cash (Years 1-5) | D65: =AVERAGE(D55:H55)/C17 -> 0.059718024
A66: Going-In Cap Rate (our underwriting) | C66: ='Annual Model'!C50/Assumptions!$B$6 -> 0.061720258
A67: Stabilised Yield on Total Cost (Year 5) | C67: ='Annual Model'!G50/C22 -> 0.069981997 | J67: Development spread over the 6.75% exit cap is the value created by the business plan.
A68: Renovation Return on Cost | C68: =Assumptions!$B$39*12/Assumptions!$B$35 -> 0.12668101
A69: HURDLE TEST & RECOMMENDATION
C70: Target | D70: This Deal | E70: Result | J70: Note
A71: Levered IRR | C71: 0.14 | D71: =D62 -> 0.067006663 | E71: =IF(D71>=C71,"PASS","FAIL") -> FAIL
A72: Equity Multiple | C72: 1.8 | D72: =D63 -> 1.3494954 | E72: =IF(D72>=C72,"PASS","FAIL") -> FAIL
A73: Year-5 Yield on Total Cost vs Exit Cap (spread) | C73: 0.0075 | D73: ='Annual Model'!G50/C22-Assumptions!$B$12 -> 0.0024819968 | E73: =IF(D73>=C73,"PASS","FAIL") -> FAIL
A74: Recommended Maximum Bid | C74: 12250000 | D74: =C74/Assumptions!$B$17 -> 103813.56 | J74: The highest basis at which this business plan clears a 14% levered IRR and a 1.8x multiple on our underwriting. See the Sensitivities tab, which computes the full price ladder live.
A75: Implied Going-In Cap at the Recommended Bid | C75: ='Annual Model'!C50/C74 -> 0.071545115
A76: Discount to the Implied Ask | C76: =C74/Assumptions!$B$6-1 -> -0.13732394
A77: AT THE RECOMMENDED BID — SIDE BY SIDE
C78: At the Ask | D78: At Our Bid | J78: Operating NOI is identical in both cases — only the basis, the loan and the equity change.
A79: Purchase Price | C79: =Assumptions!$B$6 -> 14200000 | D79: =$C$74 -> 12250000
A80: Price per Unit | C80: =Assumptions!$B$6/Assumptions!$B$17 -> 120338.98 | D80: =$C$74/Assumptions!$B$17 -> 103813.56
A81: Total Capitalised Cost | C81: =C22 -> 17271520 | D81: =$C$74+'Unit Mix'!$D$21+'Capex Budget'!B14+C11 -> 15321520
A82: All-in Basis per Unit | C82: =C22/Assumptions!$B$17 -> 146368.81 | D82: =D81/Assumptions!$B$17 -> 129843.39
A83: Going-In Cap Rate (our Year-1 NOI) | C83: ='Annual Model'!C50/Assumptions!$B$6 -> 0.061720258 | D83: ='Annual Model'!C50/$C$74 -> 0.071545115
A84: Year-5 Yield on Total Cost | C84: ='Annual Model'!G50/C22 -> 0.069981997 | D84: ='Annual Model'!G50/D81 -> 0.078888743
A85: Spread to the Exit Cap | C85: =C84-Assumptions!$B$12 -> 0.0024819968 | D85: =D84-Assumptions!$B$12 -> 0.011388743
A86: Loan Amount | C86: =C27 -> 10955346 | D86: =MIN(D81*Assumptions!$B$70,C25,C26) -> 9958988
A87: Sponsor Equity | C87: =C17 -> 6738727.6 | D87: =D79+D79*Assumptions!$B$9+'Unit Mix'!$D$21+'Capex Budget'!B14+C11+D86*Assumptions!$B$74+Assumptions!$B$75-D86 -> 5745871.9
A88: Annual Interest Expense | C88: =C31 -> 640887.73 | D88: =D86*Assumptions!$B$73 -> 582600.8
A89: Net Proceeds to Equity at Sale | C89: =C43 -> 7081764.7 | D89: =C41-D86 -> 8078122.6
A91: Unlevered Cash Flow at Our Bid | C91: =-(D81+D79*Assumptions!$B$9) -> -15505270 | D91: ='Annual Model'!C59 -> 841027.66 | E91: ='Annual Model'!D59 -> 965913.66 | F91: ='Annual Model'!E59 -> 1098489.6 | G91: ='Annual Model'!F59 -> 1142272.8 | H91: ='Annual Model'!G59+C41 -> 19205963
A92: Levered Cash Flow at Our Bid | C92: =-D87 -> -5745871.9 | D92: ='Annual Model'!C59-$D$88 -> 258426.87 | E92: ='Annual Model'!D59-$D$88 -> 383312.86 | F92: ='Annual Model'!E59-$D$88 -> 515888.81 | G92: ='Annual Model'!F59-$D$88 -> 559671.97 | H92: ='Annual Model'!G59-$D$88+D89 -> 8664374.2
A93: Unlevered IRR / Equity Multiple | C93: =IRR(C51:H51) -> 0.064624245 | D93: =IRR(C91:H91) -> 0.093417073 | E93: =SUM(D91:H91)/-C91 -> 1.4997267
A94: Levered IRR / Equity Multiple | C94: =IRR(C57:H57) -> 0.067006663 | D94: =IRR(C92:H92) -> 0.13802828 | E94: =SUM(D92:H92)/-C92 -> 1.8068058
A95: Average Cash-on-Cash (Years 1-5) | C95: =AVERAGE(D55:H55)/C17 -> 0.059718024 | D95: =(AVERAGE('Annual Model'!C59:G59)-D88)/D87 -> 0.080181118
A96: VALUE CREATION BRIDGE — WHERE THE MONEY IS MADE (AND LOST)
A97: Component | C97: Amount | D97: Per Unit | J97: Comment
A98: Purchase Price | C98: =-Assumptions!$B$6 -> -14200000 | D98: =C98/Assumptions!$B$17 -> -120338.98 | J98: What we pay.
A99: Acquisition Costs | C99: =-Assumptions!$B$6*Assumptions!$B$9 -> -213000 | D99: =C99/Assumptions!$B$17 -> -1805.0847
A100: Renovation Capital (118 units) | C100: =-'Unit Mix'!$D$21 -> -1859000 | D100: =C100/Assumptions!$B$17 -> -15754.237 | J100: Earns a 12.7% return on cost.
A101: Non-Unit / Deferred Maintenance Capital | C101: =-'Capex Budget'!B14 -> -985000 | D101: =C101/Assumptions!$B$17 -> -8347.4576 | J101: Earns no direct rent. Required to hold the asset and to support the renovated rents, but it is a pure drag on returns.
A102: Capital Contingency | C102: =-C11 -> -227520 | D102: =C102/Assumptions!$B$17 -> -1928.1356
A103: Cumulative NOI, Years 1-5 | C103: =SUM('Annual Model'!C50:G50) -> 5404499.6 | D103: =C103/Assumptions!$B$17 -> 45800.844 | J103: Five years of operations.
A104: Replacement Reserves over the hold | C104: =SUM('Annual Model'!C58:G58) -> -187943.41 | D104: =C104/Assumptions!$B$17 -> -1592.7407
A105: Net Sale Proceeds | C105: =C41 -> 18037111 | D105: =C105/Assumptions!$B$17 -> 152856.87 | J105: Year-6 NOI capitalised at the exit cap, less 1.5% cost of sale.
A106: Unlevered Profit | C106: =SUM(C98:C105) -> 5769146.7 | D106: =C106/Assumptions!$B$17 -> 48891.074
A108: NOI lift created by the renovation programme | C108: =Assumptions!$B$39*Assumptions!$B$17*12*(1-Assumptions!G$47-Assumptions!G$48-Assumptions!G$49-Assumptions!G$50)*(1-Assumptions!$B$56) -> 207993.6 | J108: Blended premium, net of vacancy, loss to lease, concessions, bad debt and the management fee.
A109: Value of that lift at the exit cap | C109: =C108/Assumptions!$B$12 -> 3081386.7
...

Sheet Sensitivities
A1: CHATEAU IN THE WOODS | 4020 Monaco Drive, Indianapolis, IN 46220 | 118 Units
A2: Live Sensitivity Grids — recalculate with every change to the Assumptions tab
A3: Blue = hardcoded input / lever · Black = formula · Green = link to another sheet · Yellow fill = key assumption
A5: HELPER BLOCK 1 — PURCHASE PRICE × EXIT CAP (live cash flows)
A6: Purchase Price | B6: Exit Cap | C6: Loan | D6: Equity | E6: Year 0 | F6: Year 1 | G6: Year 2 | H6: Year 3 | I6: Year 4 | J6: Year 5 | K6: Levered IRR | L6: Equity Mult.
A7: 11500000 | B7: 0.06 | C7: =MIN((A7+('Unit Mix'!$D$21+'Capex Budget'!$B$14)*(1+Assumptions!$B$42))*Assumptions!$B$70,'Annual Model'!C50/Assumptions!$B$71,'Annual Model'!C50/(Assumptions!$B$72*Assumptions!$B$73)) -> 9471488 | D7: =A7+('Unit Mix'!$D$21+'Capex Budget'!$B$14)*(1+Assumptions!$B$42)+A7*Assumptions!$B$9+C7*Assumptions!$B$74+Assumptions!$B$75-C7 -> 5467246.9 | E7: =-D7 -> -5467246.9 | F7: ='Annual Model'!C59-C7*Assumptions!$B$73 -> 286945.62 | G7: ='Annual Model'!D59-C7*Assumptions!$B$73 -> 411831.61 | H7: ='Annual Model'!E59-C7*Assumptions!$B$73 -> 544407.56 | I7: ='Annual Model'!F59-C7*Assumptions!$B$73 -> 588190.72 | J7: ='Annual Model'!G59-C7*Assumptions!$B$73+('Annual Model'!H50/B7)*(1-Assumptions!$B$13)-C7 -> 11435032 | K7: =IRR(E7:J7) -> 0.2120336 | L7: =SUM(F7:J7)/-E7 -> 2.4265243
A8: 11500000 | B8: 0.065 | C8: =MIN((A8+('Unit Mix'!$D$21+'Capex Budget'!$B$14)*(1+Assumptions!$B$42))*Assumptions!$B$70,'Annual Model'!C50/Assumptions!$B$71,'Annual Model'!C50/(Assumptions!$B$72*Assumptions!$B$73)) -> 9471488 | D8: =A8+('Unit Mix'!$D$21+'Capex Budget'!$B$14)*(1+Assumptions!$B$42)+A8*Assumptions!$B$9+C8*Assumptions!$B$74+Assumptions!$B$75-C8 -> 5467246.9 | E8: =-D8 -> -5467246.9 | F8: ='Annual Model'!C59-C8*Assumptions!$B$73 -> 286945.62 | G8: ='Annual Model'!D59-C8*Assumptions!$B$73 -> 411831.61 | H8: ='Annual Model'!E59-C8*Assumptions!$B$73 -> 544407.56 | I8: ='Annual Model'!F59-C8*Assumptions!$B$73 -> 588190.72 | J8: ='Annual Model'!G59-C8*Assumptions!$B$73+('Annual Model'!H50/B8)*(1-Assumptions!$B$13)-C8 -> 9874128 | K8: =IRR(E8:J8) -> 0.18108094 | L8: =SUM(F8:J8)/-E8 -> 2.1410234
A9: 11500000 | B9: 0.0675 | C9: =MIN((A9+('Unit Mix'!$D$21+'Capex Budget'!$B$14)*(1+Assumptions!$B$42))*Assumptions!$B$70,'Annual Model'!C50/Assumptions!$B$71,'Annual Model'!C50/(Assumptions!$B$72*Assumptions!$B$73)) -> 9471488 | D9: =A9+('Unit Mix'!$D$21+'Capex Budget'!$B$14)*(1+Assumptions!$B$42)+A9*Assumptions!$B$9+C9*Assumptions!$B$74+Assumptions!$B$75-C9 -> 5467246.9 | E9: =-D9 -> -5467246.9 | F9: ='Annual Model'!C59-C9*Assumptions!$B$73 -> 286945.62 | G9: ='Annual Model'!D59-C9*Assumptions!$B$73 -> 411831.61 | H9: ='Annual Model'!E59-C9*Assumptions!$B$73 -> 544407.56 | I9: ='Annual Model'!F59-C9*Assumptions!$B$73 -> 588190.72 | J9: ='Annual Model'!G59-C9*Assumptions!$B$73+('Annual Model'!H50/B9)*(1-Assumptions!$B$13)-C9 -> 9180393 | K9: =IRR(E9:J9) -> 0.16614311 | L9: =SUM(F9:J9)/-E9 -> 2.0141341
A10: 11500000 | B10: 0.07 | C10: =MIN((A10+('Unit Mix'!$D$21+'Capex Budget'!$B$14)*(1+Assumptions!$B$42))*Assumptions!$B$70,'Annual Model'!C50/Assumptions!$B$71,'Annual Model'!C50/(Assumptions!$B$72*Assumptions!$B$73)) -> 9471488 | D10: =A10+('Unit Mix'!$D$21+'Capex Budget'!$B$14)*(1+Assumptions!$B$42)+A10*Assumptions!$B$9+C10*Assumptions!$B$74+Assumptions!$B$75-C10 -> 5467246.9 | E10: =-D10 -> -5467246.9 | F10: ='Annual Model'!C59-C10*Assumptions!$B$73 -> 286945.62 | G10: ='Annual Model'!D59-C10*Assumptions!$B$73 -> 411831.61 | H10: ='Annual Model'!E59-C10*Assumptions!$B$73 -> 544407.56 | I10: ='Annual Model'!F59-C10*Assumptions!$B$73 -> 588190.72 | J10: ='Annual Model'!G59-C10*Assumptions!$B$73+('Annual Model'!H50/B10)*(1-Assumptions!$B$13)-C10 -> 8536210.4 | K10: =IRR(E10:J10) -> 0.15150401 | L10: =SUM(F10:J10)/-E10 -> 1.8963084
A11: 11500000 | B11: 0.075 | C11: =MIN((A11+('Unit Mix'!$D$21+'Capex Budget'!$B$14)*(1+Assumptions!$B$42))*Assumptions!$B$70,'Annual Model'!C50/Assumptions!$B$71,'Annual Model'!C50/(Assumptions!$B$72*Assumptions!$B$73)) -> 9471488 | D11: =A11+('Unit Mix'!$D$21+'Capex Budget'!$B$14)*(1+Assumptions!$B$42)+A11*Assumptions!$B$9+C11*Assumptions!$B$74+Assumptions!$B$75-C11 -> 5467246.9 | E11: =-D11 -> -5467246.9 | F11: ='Annual Model'!C59-C11*Assumptions!$B$73 -> 286945.62 | G11: ='Annual Model'!D59-C11*Assumptions!$B$73 -> 411831.61 | H11: ='Annual Model'!E59-C11*Assumptions!$B$73 -> 544407.56 | I11: ='Annual Model'!F59-C11*Assumptions!$B$73 -> 588190.72 | J11: ='Annual Model'!G59-C11*Assumptions!$B$73+('Annual Model'!H50/B11)*(1-Assumptions!$B$13)-C11 -> 7376681.9 | K11: =IRR(E11:J11) -> 0.12296162 | L11: =SUM(F11:J11)/-E11 -> 1.684222
A12: 12000000 | B12: 0.06 | C12: =MIN((A12+('Unit Mix'!$D$21+'Capex Budget'!$B$14)*(1+Assumptions!$B$42))*Assumptions!$B$70,'Annual Model'!C50/Assumptions!$B$71,'Annual Model'!C50/(Assumptions!$B$72*Assumptions!$B$73)) -> 9796488 | D12: =A12+('Unit Mix'!$D$21+'Capex Budget'!$B$14)*(1+Assumptions!$B$42)+A12*Assumptions!$B$9+C12*Assumptions!$B$74+Assumptions!$B$75-C12 -> 5652996.9 | E12: =-D12 -> -5652996.9 | F12: ='Annual Model'!C59-C12*Assumptions!$B$73 -> 267933.12 | G12: ='Annual Model'!D59-C12*Assumptions!$B$73 -> 392819.11 | H12: ='Annual Model'!E59-C12*Assumptions!$B$73 -> 525395.06 | I12: ='Annual Model'!F59-C12*Assumptions!$B$73 -> 569178.22 | J12: ='Annual Model'!G59-C12*Assumptions!$B$73+('Annual Model'!H50/B12)*(1-Assumptions!$B$13)-C12 -> 11091019 | K12: =IRR(E12:J12) -> 0.19427914 | L12: =SUM(F12:J12)/-E12 -> 2.272484
A13: 12000000 | B13: 0.065 | C13: =MIN((A13+('Unit Mix'!$D$21+'Capex Budget'!$B$14)*(1+Assumptions!$B$42))*Assumptions!$B$70,'Annual Model'!C50/Assumptions!$B$71,'Annual Model'!C50/(Assumptions!$B$72*Assumptions!$B$73)) -> 9796488 | D13: =A13+('Unit Mix'!$D$21+'Capex Budget'!$B$14)*(1+Assumptions!$B$42)+A13*Assumptions!$B$9+C13*Assumptions!$B$74+Assumptions!$B$75-C13 -> 5652996.9 | E13: =-D13 -> -5652996.9 | F13: ='Annual Model'!C59-C13*Assumptions!$B$73 -> 267933.12 | G13: ='Annual Model'!D59-C13*Assumptions!$B$73 -> 392819.11 | H13: ='Annual Model'!E59-C13*Assumptions!$B$73 -> 525395.06 | I13: ='Annual Model'!F59-C13*Assumptions!$B$73 -> 569178.22 | J13: ='Annual Model'!G59-C13*Assumptions!$B$73+('Annual Model'!H50/B13)*(1-Assumptions!$B$13)-C13 -> 9530115.5 | K13: =IRR(E13:J13) -> 0.16264032 | L13: =SUM(F13:J13)/-E13 -> 1.9963643
A14: 12000000 | B14: 0.0675 | C14: =MIN((A14+('Unit Mix'!$D$21+'Capex Budget'!$B$14)*(1+Assumptions!$B$42))*Assumptions!$B$70,'Annual Model'!C50/Assumptions!$B$71,'Annual Model'!C50/(Assumptions!$B$72*Assumptions!$B$73)) -> 9796488 | D14: =A14+('Unit Mix'!$D$21+'Capex Budget'!$B$14)*(1+Assumptions!$B$42)+A14*Assumptions!$B$9+C14*Assumptions!$B$74+Assumptions!$B$75-C14 -> 5652996.9 | E14: =-D14 -> -5652996.9 | F14: ='Annual Model'!C59-C14*Assumptions!$B$73 -> 267933.12 | G14: ='Annual Model'!D59-C14*Assumptions!$B$73 -> 392819.11 | H14: ='Annual Model'!E59-C14*Assumptions!$B$73 -> 525395.06 | I14: ='Annual Model'!F59-C14*Assumptions!$B$73 -> 569178.22 | J14: ='Annual Model'!G59-C14*Assumptions!$B$73+('Annual Model'!H50/B14)*(1-Assumptions!$B$13)-C14 -> 8836380.5 | K14: =IRR(E14:J14) -> 0.14732479 | L14: =SUM(F14:J14)/-E14 -> 1.8736444
A15: 12000000 | B15: 0.07 | C15: =MIN((A15+('Unit Mix'!$D$21+'Capex Budget'!$B$14)*(1+Assumptions!$B$42))*Assumptions!$B$70,'Annual Model'!C50/Assumptions!$B$71,'Annual Model'!C50/(Assumptions!$B$72*Assumptions!$B$73)) -> 9796488 | D15: =A15+('Unit Mix'!$D$21+'Capex Budget'!$B$14)*(1+Assumptions!$B$42)+A15*Assumptions!$B$9+C15*Assumptions!$B$74+Assumptions!$B$75-C15 -> 5652996.9 | E15: =-D15 -> -5652996.9 | F15: ='Annual Model'!C59-C15*Assumptions!$B$73 -> 267933.12 | G15: ='Annual Model'!D59-C15*Assumptions!$B$73 -> 392819.11 | H15: ='Annual Model'!E59-C15*Assumptions!$B$73 -> 525395.06 | I15: ='Annual Model'!F59-C15*Assumptions!$B$73 -> 569178.22 | J15: ='Annual Model'!G59-C15*Assumptions!$B$73+('Annual Model'!H50/B15)*(1-Assumptions!$B$13)-C15 -> 8192197.9 | K15: =IRR(E15:J15) -> 0.1322825 | L15: =SUM(F15:J15)/-E15 -> 1.7596902
A16: 12000000 | B16: 0.075 | C16: =MIN((A16+('Unit Mix'!$D$21+'Capex Budget'!$B$14)*(1+Assumptions!$B$42))*Assumptions!$B$70,'Annual Model'!C50/Assumptions!$B$71,'Annual Model'!C50/(Assumptions!$B$72*Assumptions!$B$73)) -> 9796488 | D16: =A16+('Unit Mix'!$D$21+'Capex Budget'!$B$14)*(1+Assumptions!$B$42)+A16*Assumptions!$B$9+C16*Assumptions!$B$74+Assumptions!$B$75-C16 -> 5652996.9 | E16: =-D16 -> -5652996.9 | F16: ='Annual Model'!C59-C16*Assumptions!$B$73 -> 267933.12 | G16: ='Annual Model'!D59-C16*Assumptions!$B$73 -> 392819.11 | H16: ='Annual Model'!E59-C16*Assumptions!$B$73 -> 525395.06 | I16: ='Annual Model'!F59-C16*Assumptions!$B$73 -> 569178.22 | J16: ='Annual Model'!G59-C16*Assumptions!$B$73+('Annual Model'!H50/B16)*(1-Assumptions!$B$13)-C16 -> 7032669.4 | K16: =IRR(E16:J16) -> 0.10284816 | L16: =SUM(F16:J16)/-E16 -> 1.5545727
A17: 12250000 | B17: 0.06 | C17: =MIN((A17+('Unit Mix'!$D$21+'Capex Budget'!$B$14)*(1+Assumptions!$B$42))*Assumptions!$B$70,'Annual Model'!C50/Assumptions!$B$71,'Annual Model'!C50/(Assumptions!$B$72*Assumptions!$B$73)) -> 9958988 | D17: =A17+('Unit Mix'!$D$21+'Capex Budget'!$B$14)*(1+Assumptions!$B$42)+A17*Assumptions!$B$9+C17*Assumptions!$B$74+Assumptions!$B$75-C17 -> 5745871.9 | E17: =-D17 -> -5745871.9 | F17: ='Annual Model'!C59-C17*Assumptions!$B$73 -> 258426.87 | G17: ='Annual Model'!D59-C17*Assumptions!$B$73 -> 383312.86 | H17: ='Annual Model'!E59-C17*Assumptions!$B$73 -> 515888.81 | I17: ='Annual Model'!F59-C17*Assumptions!$B$73 -> 559671.97 | J17: ='Annual Model'!G59-C17*Assumptions!$B$73+('Annual Model'!H50/B17)*(1-Assumptions!$B$13)-C17 -> 10919013 | K17: =IRR(E17:J17) -> 0.18554339 | L17: =SUM(F17:J17)/-E17 -> 2.1991986
A18: 12250000 | B18: 0.065 | C18: =MIN((A18+('Unit Mix'!$D$21+'Capex Budget'!$B$14)*(1+Assumptions!$B$42))*Assumptions!$B$70,'Annual Model'!C50/Assumptions!$B$71,'Annual Model'!C50/(Assumptions!$B$72*Assumptions!$B$73)) -> 9958988 | D18: =A18+('Unit Mix'!$D$21+'Capex Budget'!$B$14)*(1+Assumptions!$B$42)+A18*Assumptions!$B$9+C18*Assumptions!$B$74+Assumptions!$B$75-C18 -> 5745871.9 | E18: =-D18 -> -5745871.9 | F18: ='Annual Model'!C59-C18*Assumptions!$B$73 -> 258426.87 | G18: ='Annual Model'!D59-C18*Assumptions!$B$73 -> 383312.86 | H18: ='Annual Model'!E59-C18*Assumptions!$B$73 -> 515888.81 | I18: ='Annual Model'!F59-C18*Assumptions!$B$73 -> 559671.97 | J18: ='Annual Model'!G59-C18*Assumptions!$B$73+('Annual Model'!H50/B18)*(1-Assumptions!$B$13)-C18 -> 9358109.2 | K18: =IRR(E18:J18) -> 0.15354346 | L18: =SUM(F18:J18)/-E18 -> 1.9275421
A19: 12250000 | B19: 0.0675 | C19: =MIN((A19+('Unit Mix'!$D$21+'Capex Budget'!$B$14)*(1+Assumptions!$B$42))*Assumptions!$B$70,'Annual Model'!C50/Assumptions!$B$71,'Annual Model'!C50/(Assumptions!$B$72*Assumptions!$B$73)) -> 9958988 | D19: =A19+('Unit Mix'!$D$21+'Capex Budget'!$B$14)*(1+Assumptions!$B$42)+A19*Assumptions!$B$9+C19*Assumptions!$B$74+Assumptions!$B$75-C19 -> 5745871.9 | E19: =-D19 -> -5745871.9 | F19: ='Annual Model'!C59-C19*Assumptions!$B$73 -> 258426.87 | G19: ='Annual Model'!D59-C19*Assumptions!$B$73 -> 383312.86 | H19: ='Annual Model'!E59-C19*Assumptions!$B$73 -> 515888.81 | I19: ='Annual Model'!F59-C19*Assumptions!$B$73 -> 559671.97 | J19: ='Annual Model'!G59-C19*Assumptions!$B$73+('Annual Model'!H50/B19)*(1-Assumptions!$B$13)-C19 -> 8664374.2 | K19: =IRR(E19:J19) -> 0.13802828 | L19: =SUM(F19:J19)/-E19 -> 1.8068058
A20: 12250000 | B20: 0.07 | C20: =MIN((A20+('Unit Mix'!$D$21+'Capex Budget'!$B$14)*(1+Assumptions!$B$42))*Assumptions!$B$70,'Annual Model'!C50/Assumptions!$B$71,'Annual Model'!C50/(Assumptions!$B$72*Assumptions!$B$73)) -> 9958988 | D20: =A20+('Unit Mix'!$D$21+'Capex Budget'!$B$14)*(1+Assumptions!$B$42)+A20*Assumptions!$B$9+C20*Assumptions!$B$74+Assumptions!$B$75-C20 -> 5745871.9 | E20: =-D20 -> -5745871.9 | F20: ='Annual Model'!C59-C20*Assumptions!$B$73 -> 258426.87 | G20: ='Annual Model'!D59-C20*Assumptions!$B$73 -> 383312.86 | H20: ='Annual Model'!E59-C20*Assumptions!$B$73 -> 515888.81 | I20: ='Annual Model'!F59-C20*Assumptions!$B$73 -> 559671.97 | J20: ='Annual Model'!G59-C20*Assumptions!$B$73+('Annual Model'!H50/B20)*(1-Assumptions!$B$13)-C20 -> 8020191.7 | K20: =IRR(E20:J20) -> 0.12277216 | L20: =SUM(F20:J20)/-E20 -> 1.6946936
A21: 12250000 | B21: 0.075 | C21: =MIN((A21+('Unit Mix'!$D$21+'Capex Budget'!$B$14)*(1+Assumptions!$B$42))*Assumptions!$B$70,'Annual Model'!C50/Assumptions!$B$71,'Annual Model'!C50/(Assumptions!$B$72*Assumptions!$B$73)) -> 9958988 | D21: =A21+('Unit Mix'!$D$21+'Capex Budget'!$B$14)*(1+Assumptions!$B$42)+A21*Assumptions!$B$9+C21*Assumptions!$B$74+Assumptions!$B$75-C21 -> 5745871.9 | E21: =-D21 -> -5745871.9 | F21: ='Annual Model'!C59-C21*Assumptions!$B$73 -> 258426.87 | G21: ='Annual Model'!D59-C21*Assumptions!$B$73 -> 383312.86 | H21: ='Annual Model'!E59-C21*Assumptions!$B$73 -> 515888.81 | I21: ='Annual Model'!F59-C21*Assumptions!$B$73 -> 559671.97 | J21: ='Annual Model'!G59-C21*Assumptions!$B$73+('Annual Model'!H50/B21)*(1-Assumptions!$B$13)-C21 -> 6860663.1 | K21: =IRR(E21:J21) -> 0.092862117 | L21: =SUM(F21:J21)/-E21 -> 1.4928916
A22: 12750000 | B22: 0.06 | C22: =MIN((A22+('Unit Mix'!$D$21+'Capex Budget'!$B$14)*(1+Assumptions!$B$42))*Assumptions!$B$70,'Annual Model'!C50/Assumptions!$B$71,'Annual Model'!C50/(Assumptions!$B$72*Assumptions!$B$73)) -> 10283988 | D22: =A22+('Unit Mix'!$D$21+'Capex Budget'!$B$14)*(1+Assumptions!$B$42)+A22*Assumptions!$B$9+C22*Assumptions!$B$74+Assumptions!$B$75-C22 -> 5931621.9 | E22: =-D22 -> -5931621.9 | F22: ='Annual Model'!C59-C22*Assumptions!$B$73 -> 239414.37 | G22: ='Annual Model'!D59-C22*Assumptions!$B$73 -> 364300.36 | H22: ='Annual Model'!E59-C22*Assumptions!$B$73 -> 496876.31 | I22: ='Annual Model'!F59-C22*Assumptions!$B$73 -> 540659.47 | J22: ='Annual Model'!G59-C22*Assumptions!$B$73+('Annual Model'!H50/B22)*(1-Assumptions!$B$13)-C22 -> 10575001 | K22: =IRR(E22:J22) -> 0.16832466 | L22: =SUM(F22:J22)/-E22 -> 2.0595128
A23: 12750000 | B23: 0.065 | C23: =MIN((A23+('Unit Mix'!$D$21+'Capex Budget'!$B$14)*(1+Assumptions!$B$42))*Assumptions!$B$70,'Annual Model'!C50/Assumptions!$B$71,'Annual Model'!C50/(Assumptions!$B$72*Assumptions!$B$73)) -> 10283988 | D23: =A23+('Unit Mix'!$D$21+'Capex Budget'!$B$14)*(1+Assumptions!$B$42)+A23*Assumptions!$B$9+C23*Assumptions!$B$74+Assumptions!$B$75-C23 -> 5931621.9 | E23: =-D23 -> -5931621.9 | F23: ='Annual Model'!C59-C23*Assumptions!$B$73 -> 239414.37 | G23: ='Annual Model'!D59-C23*Assumptions!$B$73 -> 364300.36 | H23: ='Annual Model'!E59-C23*Assumptions!$B$73 -> 496876.31 | I23: ='Annual Model'!F59-C23*Assumptions!$B$73 -> 540659.47 | J23: ='Annual Model'!G59-C23*Assumptions!$B$73+('Annual Model'!H50/B23)*(1-Assumptions!$B$13)-C23 -> 9014096.7 | K23: =IRR(E23:J23) -> 0.13556359 | L23: =SUM(F23:J23)/-E23 -> 1.7963632
A24: 12750000 | B24: 0.0675 | C24: =MIN((A24+('Unit Mix'!$D$21+'Capex Budget'!$B$14)*(1+Assumptions!$B$42))*Assumptions!$B$70,'Annual Model'!C50/Assumptions!$B$71,'Annual Model'!C50/(Assumptions!$B$72*Assumptions!$B$73)) -> 10283988 | D24: =A24+('Unit Mix'!$D$21+'Capex Budget'!$B$14)*(1+Assumptions!$B$42)+A24*Assumptions!$B$9+C24*Assumptions!$B$74+Assumptions!$B$75-C24 -> 5931621.9 | E24: =-D24 -> -5931621.9 | F24: ='Annual Model'!C59-C24*Assumptions!$B$73 -> 239414.37 | G24: ='Annual Model'!D59-C24*Assumptions!$B$73 -> 364300.36 | H24: ='Annual Model'!E59-C24*Assumptions!$B$73 -> 496876.31 | I24: ='Annual Model'!F59-C24*Assumptions!$B$73 -> 540659.47 | J24: ='Annual Model'!G59-C24*Assumptions!$B$73+('Annual Model'!H50/B24)*(1-Assumptions!$B$13)-C24 -> 8320361.7 | K24: =IRR(E24:J24) -> 0.11962563 | L24: =SUM(F24:J24)/-E24 -> 1.6794078
A25: 12750000 | B25: 0.07 | C25: =MIN((A25+('Unit Mix'!$D$21+'Capex Budget'!$B$14)*(1+Assumptions!$B$42))*Assumptions!$B$70,'Annual Model'!C50/Assumptions!$B$71,'Annual Model'!C50/(Assumptions!$B$72*Assumptions!$B$73)) -> 10283988 | D25: =A25+('Unit Mix'!$D$21+'Capex Budget'!$B$14)*(1+Assumptions!$B$42)+A25*Assumptions!$B$9+C25*Assumptions!$B$74+Assumptions!$B$75-C25 -> 5931621.9 | E25: =-D25 -> -5931621.9 | F25: ='Annual Model'!C59-C25*Assumptions!$B$73 -> 239414.37 | G25: ='Annual Model'!D59-C25*Assumptions!$B$73 -> 364300.36 | H25: ='Annual Model'!E59-C25*Assumptions!$B$73 -> 496876.31 | I25: ='Annual Model'!F59-C25*Assumptions!$B$73 -> 540659.47 | J25: ='Annual Model'!G59-C25*Assumptions!$B$73+('Annual Model'!H50/B25)*(1-Assumptions!$B$13)-C25 -> 7676179.2 | K25: =IRR(E25:J25) -> 0.10391506 | L25: =SUM(F25:J25)/-E25 -> 1.5708064
A26: 12750000 | B26: 0.075 | C26: =MIN((A26+('Unit Mix'!$D$21+'Capex Budget'!$B$14)*(1+Assumptions!$B$42))*Assumptions!$B$70,'Annual Model'!C50/Assumptions!$B$71,'Annual Model'!C50/(Assumptions!$B$72*Assumptions!$B$73)) -> 10283988 | D26: =A26+('Unit Mix'!$D$21+'Capex Budget'!$B$14)*(1+Assumptions!$B$42)+A26*Assumptions!$B$9+C26*Assumptions!$B$74+Assumptions!$B$75-C26 -> 5931621.9 | E26: =-D26 -> -5931621.9 | F26: ='Annual Model'!C59-C26*Assumptions!$B$73 -> 239414.37 | G26: ='Annual Model'!D59-C26*Assumptions!$B$73 -> 364300.36 | H26: ='Annual Model'!E59-C26*Assumptions!$B$73 -> 496876.31 | I26: ='Annual Model'!F59-C26*Assumptions!$B$73 -> 540659.47 | J26: ='Annual Model'!G59-C26*Assumptions!$B$73+('Annual Model'!H50/B26)*(1-Assumptions!$B$13)-C26 -> 6516650.6 | K26: =IRR(E26:J26) -> 0.072987593 | L26: =SUM(F26:J26)/-E26 -> 1.3753239
A27: 13250000 | B27: 0.06 | C27: =MIN((A27+('Unit Mix'!$D$21+'Capex Budget'!$B$14)*(1+Assumptions!$B$42))*Assumptions!$B$70,'Annual Model'!C50/Assumptions!$B$71,'Annual Model'!C50/(Assumptions!$B$72*Assumptions!$B$73)) -> 10608988 | D27: =A27+('Unit Mix'!$D$21+'Capex Budget'!$B$14)*(1+Assumptions!$B$42)+A27*Assumptions!$B$9+C27*Assumptions!$B$74+Assumptions!$B$75-C27 -> 6117371.9 | E27: =-D27 -> -6117371.9 | F27: ='Annual Model'!C59-C27*Assumptions!$B$73 -> 220401.87 | G27: ='Annual Model'!D59-C27*Assumptions!$B$73 -> 345287.86 | H27: ='Annual Model'!E59-C27*Assumptions!$B$73 -> 477863.81 | I27: ='Annual Model'!F59-C27*Assumptions!$B$73 -> 521646.97 | J27: ='Annual Model'!G59-C27*Assumptions!$B$73+('Annual Model'!H50/B27)*(1-Assumptions!$B$13)-C27 -> 10230988 | K27: =IRR(E27:J27) -> 0.15140514 | L27: =SUM(F27:J27)/-E27 -> 1.9283099
A28: 13250000 | B28: 0.065 | C28: =MIN((A28+('Unit Mix'!$D$21+'Capex Budget'!$B$14)*(1+Assumptions!$B$42))*Assumptions!$B$70,'Annual Model'!C50/Assumptions!$B$71,'Annual Model'!C50/(Assumptions!$B$72*Assumptions!$B$73)) -> 10608988 | D28: =A28+('Unit Mix'!$D$21+'Capex Budget'!$B$14)*(1+Assumptions!$B$42)+A28*Assumptions!$B$9+C28*Assumptions!$B$74+Assumptions!$B$75-C28 -> 6117371.9 | E28: =-D28 -> -6117371.9 | F28: ='Annual Model'!C59-C28*Assumptions!$B$73 -> 220401.87 | G28: ='Annual Model'!D59-C28*Assumptions!$B$73 -> 345287.86 | H28: ='Annual Model'!E59-C28*Assumptions!$B$73 -> 477863.81 | I28: ='Annual Model'!F59-C28*Assumptions!$B$73 -> 521646.97 | J28: ='Annual Model'!G59-C28*Assumptions!$B$73+('Annual Model'!H50/B28)*(1-Assumptions!$B$13)-C28 -> 8670084.2 | K28: =IRR(E28:J28) -> 0.11782684 | L28: =SUM(F28:J28)/-E28 -> 1.6731506
A29: 13250000 | B29: 0.0675 | C29: =MIN((A29+('Unit Mix'!$D$21+'Capex Budget'!$B$14)*(1+Assumptions!$B$42))*Assumptions!$B$70,'Annual Model'!C50/Assumptions!$B$71,'Annual Model'!C50/(Assumptions!$B$72*Assumptions!$B$73)) -> 10608988 | D29: =A29+('Unit Mix'!$D$21+'Capex Budget'!$B$14)*(1+Assumptions!$B$42)+A29*Assumptions!$B$9+C29*Assumptions!$B$74+Assumptions!$B$75-C29 -> 6117371.9 | E29: =-D29 -> -6117371.9 | F29: ='Annual Model'!C59-C29*Assumptions!$B$73 -> 220401.87 | G29: ='Annual Model'!D59-C29*Assumptions!$B$73 -> 345287.86 | H29: ='Annual Model'!E59-C29*Assumptions!$B$73 -> 477863.81 | I29: ='Annual Model'!F59-C29*Assumptions!$B$73 -> 521646.97 | J29: ='Annual Model'!G59-C29*Assumptions!$B$73+('Annual Model'!H50/B29)*(1-Assumptions!$B$13)-C29 -> 7976349.2 | K29: =IRR(E29:J29) -> 0.10143188 | L29: =SUM(F29:J29)/-E29 -> 1.5597466
A30: 13250000 | B30: 0.07 | C30: =MIN((A30+('Unit Mix'!$D$21+'Capex Budget'!$B$14)*(1+Assumptions!$B$42))*Assumptions!$B$70,'Annual Model'!C50/Assumptions!$B$71,'Annual Model'!C50/(Assumptions!$B$72*Assumptions!$B$73)) -> 10608988 | D30: =A30+('Unit Mix'!$D$21+'Capex Budget'!$B$14)*(1+Assumptions!$B$42)+A30*Assumptions!$B$9+C30*Assumptions!$B$74+Assumptions!$B$75-C30 -> 6117371.9 | E30: =-D30 -> -6117371.9 | F30: ='Annual Model'!C59-C30*Assumptions!$B$73 -> 220401.87 | G30: ='Annual Model'!D59-C30*Assumptions!$B$73 -> 345287.86 | H30: ='Annual Model'!E59-C30*Assumptions!$B$73 -> 477863.81 | I30: ='Annual Model'!F59-C30*Assumptions!$B$73 -> 521646.97 | J30: ='Annual Model'!G59-C30*Assumptions!$B$73+('Annual Model'!H50/B30)*(1-Assumptions!$B$13)-C30 -> 7332166.7 | K30: =IRR(E30:J30) -> 0.085227468 | L30: =SUM(F30:J30)/-E30 -> 1.4544428
A31: 13250000 | B31: 0.075 | C31: =MIN((A31+('Unit Mix'!$D$21+'Capex Budget'!$B$14)*(1+Assumptions!$B$42))*Assumptions!$B$70,'Annual Model'!C50/Assumptions!$B$71,'Annual Model'!C50/(Assumptions!$B$72*Assumptions!$B$73)) -> 10608988 | D31: =A31+('Unit Mix'!$D$21+'Capex Budget'!$B$14)*(1+Assumptions!$B$42)+A31*Assumptions!$B$9+C31*Assumptions!$B$74+Assumptions!$B$75-C31 -> 6117371.9 | E31: =-D31 -> -6117371.9 | F31: ='Annual Model'!C59-C31*Assumptions!$B$73 -> 220401.87 | G31: ='Annual Model'!D59-C31*Assumptions!$B$73 -> 345287.86 | H31: ='Annual Model'!E59-C31*Assumptions!$B$73 -> 477863.81 | I31: ='Annual Model'!F59-C31*Assumptions!$B$73 -> 521646.97 | J31: ='Annual Model'!G59-C31*Assumptions!$B$73+('Annual Model'!H50/B31)*(1-Assumptions!$B$13)-C31 -> 6172638.1 | K31: =IRR(E31:J31) -> 0.053184387 | L31: =SUM(F31:J31)/-E31 -> 1.2648959
A32: 14200000 | B32: 0.06 | C32: =MIN((A32+('Unit Mix'!$D$21+'Capex Budget'!$B$14)*(1+Assumptions!$B$42))*Assumptions!$B$70,'Annual Model'!C50/Assumptions!$B$71,'Annual Model'!C50/(Assumptions!$B$72*Assumptions!$B$73)) -> 10955346 | D32: =A32+('Unit Mix'!$D$21+'Capex Budget'!$B$14)*(1+Assumptions!$B$42)+A32*Assumptions!$B$9+C32*Assumptions!$B$74+Assumptions!$B$75-C32 -> 6738727.6 | E32: =-D32 -> -6738727.6 | F32: ='Annual Model'!C59-C32*Assumptions!$B$73 -> 200139.93 | G32: ='Annual Model'!D59-C32*Assumptions!$B$73 -> 325025.93 | H32: ='Annual Model'!E59-C32*Assumptions!$B$73 -> 457601.88 | I32: ='Annual Model'!F59-C32*Assumptions!$B$73 -> 501385.04 | J32: ='Annual Model'!G59-C32*Assumptions!$B$73+('Annual Model'!H50/B32)*(1-Assumptions!$B$13)-C32 -> 9864368.3 | K32: =IRR(E32:J32) -> 0.11786625 | L32: =SUM(F32:J32)/-E32 -> 1.6840747
A33: 14200000 | B33: 0.065 | C33: =MIN((A33+('Unit Mix'!$D$21+'Capex Budget'!$B$14)*(1+Assumptions!$B$42))*Assumptions!$B$70,'Annual Model'!C50/Assumptions!$B$71,'Annual Model'!C50/(Assumptions!$B$72*Assumptions!$B$73)) -> 10955346 | D33: =A33+('Unit Mix'!$D$21+'Capex Budget'!$B$14)*(1+Assumptions!$B$42)+A33*Assumptions!$B$9+C33*Assumptions!$B$74+Assumptions!$B$75-C33 -> 6738727.6 | E33: =-D33 -> -6738727.6 | F33: ='Annual Model'!C59-C33*Assumptions!$B$73 -> 200139.93 | G33: ='Annual Model'!D59-C33*Assumptions!$B$73 -> 325025.93 | H33: ='Annual Model'!E59-C33*Assumptions!$B$73 -> 457601.88 | I33: ='Annual Model'!F59-C33*Assumptions!$B$73 -> 501385.04 | J33: ='Annual Model'!G59-C33*Assumptions!$B$73+('Annual Model'!H50/B33)*(1-Assumptions!$B$13)-C33 -> 8303464.5 | K33: =IRR(E33:J33) -> 0.083740892 | L33: =SUM(F33:J33)/-E33 -> 1.4524429
A34: 14200000 | B34: 0.0675 | C34: =MIN((A34+('Unit Mix'!$D$21+'Capex Budget'!$B$14)*(1+Assumptions!$B$42))*Assumptions!$B$70,'Annual Model'!C50/Assumptions!$B$71,'Annual Model'!C50/(Assumptions!$B$72*Assumptions!$B$73)) -> 10955346 | D34: =A34+('Unit Mix'!$D$21+'Capex Budget'!$B$14)*(1+Assumptions!$B$42)+A34*Assumptions!$B$9+C34*Assumptions!$B$74+Assumptions!$B$75-C34 -> 6738727.6 | E34: =-D34 -> -6738727.6 | F34: ='Annual Model'!C59-C34*Assumptions!$B$73 -> 200139.93 | G34: ='Annual Model'!D59-C34*Assumptions!$B$73 -> 325025.93 | H34: ='Annual Model'!E59-C34*Assumptions!$B$73 -> 457601.88 | I34: ='Annual Model'!F59-C34*Assumptions!$B$73 -> 501385.04 | J34: ='Annual Model'!G59-C34*Assumptions!$B$73+('Annual Model'!H50/B34)*(1-Assumptions!$B$13)-C34 -> 7609729.5 | K34: =IRR(E34:J34) -> 0.067006663 | L34: =SUM(F34:J34)/-E34 -> 1.3494954
A35: 14200000 | B35: 0.07 | C35: =MIN((A35+('Unit Mix'!$D$21+'Capex Budget'!$B$14)*(1+Assumptions!$B$42))*Assumptions!$B$70,'Annual Model'!C50/Assumptions!$B$71,'Annual Model'!C50/(Assumptions!$B$72*Assumptions!$B$73)) -> 10955346 | D35: =A35+('Unit Mix'!$D$21+'Capex Budget'!$B$14)*(1+Assumptions!$B$42)+A35*Assumptions!$B$9+C35*Assumptions!$B$74+Assumptions!$B$75-C35 -> 6738727.6 | E35: =-D35 -> -6738727.6 | F35: ='Annual Model'!C59-C35*Assumptions!$B$73 -> 200139.93 | G35: ='Annual Model'!D59-C35*Assumptions!$B$73 -> 325025.93 | H35: ='Annual Model'!E59-C35*Assumptions!$B$73 -> 457601.88 | I35: ='Annual Model'!F59-C35*Assumptions!$B$73 -> 501385.04 | J35: ='Annual Model'!G59-C35*Assumptions!$B$73+('Annual Model'!H50/B35)*(1-Assumptions!$B$13)-C35 -> 6965546.9 | K35: =IRR(E35:J35) -> 0.050413704 | L35: =SUM(F35:J35)/-E35 -> 1.2539014
A36: 14200000 | B36: 0.075 | C36: =MIN((A36+('Unit Mix'!$D$21+'Capex Budget'!$B$14)*(1+Assumptions!$B$42))*Assumptions!$B$70,'Annual Model'!C50/Assumptions!$B$71,'Annual Model'!C50/(Assumptions!$B$72*Assumptions!$B$73)) -> 10955346 | D36: =A36+('Unit Mix'!$D$21+'Capex Budget'!$B$14)*(1+Assumptions!$B$42)+A36*Assumptions!$B$9+C36*Assumptions!$B$74+Assumptions!$B$75-C36 -> 6738727.6 | E36: =-D36 -> -6738727.6 | F36: ='Annual Model'!C59-C36*Assumptions!$B$73 -> 200139.93 | G36: ='Annual Model'!D59-C36*Assumptions!$B$73 -> 325025.93 | H36: ='Annual Model'!E59-C36*Assumptions!$B$73 -> 457601.88 | I36: ='Annual Model'!F59-C36*Assumptions!$B$73 -> 501385.04 | J36: ='Annual Model'!G59-C36*Assumptions!$B$73+('Annual Model'!H50/B36)*(1-Assumptions!$B$13)-C36 -> 5806018.4 | K36: =IRR(E36:J36) -> 0.017423219 | L36: =SUM(F36:J36)/-E36 -> 1.081832
A37: 14750000 | B37: 0.06 | C37: =MIN((A37+('Unit Mix'!$D$21+'Capex Budget'!$B$14)*(1+Assumptions!$B$42))*Assumptions!$B$70,'Annual Model'!C50/Assumptions!$B$71,'Annual Model'!C50/(Assumptions!$B$72*Assumptions!$B$73)) -> 10955346 | D37: =A37+('Unit Mix'!$D$21+'Capex Budget'!$B$14)*(1+Assumptions!$B$42)+A37*Assumptions!$B$9+C37*Assumptions!$B$74+Assumptions!$B$75-C37 -> 7296977.6 | E37: =-D37 -> -7296977.6 | F37: ='Annual Model'!C59-C37*Assumptions!$B$73 -> 200139.93 | G37: ='Annual Model'!D59-C37*Assumptions!$B$73 -> 325025.93 | H37: ='Annual Model'!E59-C37*Assumptions!$B$73 -> 457601.88 | I37: ='Annual Model'!F59-C37*Assumptions!$B$73 -> 501385.04 | J37: ='Annual Model'!G59-C37*Assumptions!$B$73+('Annual Model'!H50/B37)*(1-Assumptions!$B$13)-C37 -> 9864368.3 | K37: =IRR(E37:J37) -> 0.098857245 | L37: =SUM(F37:J37)/-E37 -> 1.5552358
A38: 14750000 | B38: 0.065 | C38: =MIN((A38+('Unit Mix'!$D$21+'Capex Budget'!$B$14)*(1+Assumptions!$B$42))*Assumptions!$B$70,'Annual Model'!C50/Assumptions!$B$71,'Annual Model'!C50/(Assumptions!$B$72*Assumptions!$B$73)) -> 10955346 | D38: =A38+('Unit Mix'!$D$21+'Capex Budget'!$B$14)*(1+Assumptions!$B$42)+A38*Assumptions!$B$9+C38*Assumptions!$B$74+Assumptions!$B$75-C38 -> 7296977.6 | E38: =-D38 -> -7296977.6 | F38: ='Annual Model'!C59-C38*Assumptions!$B$73 -> 200139.93 | G38: ='Annual Model'!D59-C38*Assumptions!$B$73 -> 325025.93 | H38: ='Annual Model'!E59-C38*Assumptions!$B$73 -> 457601.88 | I38: ='Annual Model'!F59-C38*Assumptions!$B$73 -> 501385.04 | J38: ='Annual Model'!G59-C38*Assumptions!$B$73+('Annual Model'!H50/B38)*(1-Assumptions!$B$13)-C38 -> 8303464.5 | K38: =IRR(E38:J38) -> 0.065208719 | L38: =SUM(F38:J38)/-E38 -> 1.3413248
A39: 14750000 | B39: 0.0675 | C39: =MIN((A39+('Unit Mix'!$D$21+'Capex Budget'!$B$14)*(1+Assumptions!$B$42))*Assumptions!$B$70,'Annual Model'!C50/Assumptions!$B$71,'Annual Model'!C50/(Assumptions!$B$72*Assumptions!$B$73)) -> 10955346 | D39: =A39+('Unit Mix'!$D$21+'Capex Budget'!$B$14)*(1+Assumptions!$B$42)+A39*Assumptions!$B$9+C39*Assumptions!$B$74+Assumptions!$B$75-C39 -> 7296977.6 | E39: =-D39 -> -7296977.6 | F39: ='Annual Model'!C59-C39*Assumptions!$B$73 -> 200139.93 | G39: ='Annual Model'!D59-C39*Assumptions!$B$73 -> 325025.93 | H39: ='Annual Model'!E59-C39*Assumptions!$B$73 -> 457601.88 | I39: ='Annual Model'!F59-C39*Assumptions!$B$73 -> 501385.04 | J39: ='Annual Model'!G59-C39*Assumptions!$B$73+('Annual Model'!H50/B39)*(1-Assumptions!$B$13)-C39 -> 7609729.5 | K39: =IRR(E39:J39) -> 0.048705703 | L39: =SUM(F39:J39)/-E39 -> 1.2462533
A40: 14750000 | B40: 0.07 | C40: =MIN((A40+('Unit Mix'!$D$21+'Capex Budget'!$B$14)*(1+Assumptions!$B$42))*Assumptions!$B$70,'Annual Model'!C50/Assumptions!$B$71,'Annual Model'!C50/(Assumptions!$B$72*Assumptions!$B$73)) -> 10955346 | D40: =A40+('Unit Mix'!$D$21+'Capex Budget'!$B$14)*(1+Assumptions!$B$42)+A40*Assumptions!$B$9+C40*Assumptions!$B$74+Assumptions!$B$75-C40 -> 7296977.6 | E40: =-D40 -> -7296977.6 | F40: ='Annual Model'!C59-C40*Assumptions!$B$73 -> 200139.93 | G40: ='Annual Model'!D59-C40*Assumptions!$B$73 -> 325025.93 | H40: ='Annual Model'!E59-C40*Assumptions!$B$73 -> 457601.88 | I40: ='Annual Model'!F59-C40*Assumptions!$B$73 -> 501385.04 | J40: ='Annual Model'!G59-C40*Assumptions!$B$73+('Annual Model'!H50/B40)*(1-Assumptions!$B$13)-C40 -> 6965546.9 | K40: =IRR(E40:J40) -> 0.032340116 | L40: =SUM(F40:J40)/-E40 -> 1.1579725
A41: 14750000 | B41: 0.075 | C41: =MIN((A41+('Unit Mix'!$D$21+'Capex Budget'!$B$14)*(1+Assumptions!$B$42))*Assumptions!$B$70,'Annual Model'!C50/Assumptions!$B$71,'Annual Model'!C50/(Assumptions!$B$72*Assumptions!$B$73)) -> 10955346 | D41: =A41+('Unit Mix'!$D$21+'Capex Budget'!$B$14)*(1+Assumptions!$B$42)+A41*Assumptions!$B$9+C41*Assumptions!$B$74+Assumptions!$B$75-C41 -> 7296977.6 | E41: =-D41 -> -7296977.6 | F41: ='Annual Model'!C59-C41*Assumptions!$B$73 -> 200139.93 | G41: ='Annual Model'!D59-C41*Assumptions!$B$73 -> 325025.93 | H41: ='Annual Model'!E59-C41*Assumptions!$B$73 -> 457601.88 | I41: ='Annual Model'!F59-C41*Assumptions!$B$73 -> 501385.04 | J41: ='Annual Model'!G59-C41*Assumptions!$B$73+('Annual Model'!H50/B41)*(1-Assumptions!$B$13)-C41 -> 5806018.4 | K41: =IRR(E41:J41) -> -0.00020453171 | L41: =SUM(F41:J41)/-E41 -> 0.99906722
A43: GRID 1A — LEVERED IRR: PURCHASE PRICE × EXIT CAP
A44: Purchase Price \ Exit Cap | B44: 0.06 | C44: 0.065 | D44: 0.0675 | E44: 0.07 | F44: 0.075 | G44: Price / Unit
A45: 11500000 | B45: =K7 -> 0.2120336 | C45: =K8 -> 0.18108094 | D45: =K9 -> 0.16614311 | E45: =K10 -> 0.15150401 | F45: =K11 -> 0.12296162 | G45: =A45/Assumptions!$B$17 -> 97457.627
A46: 12000000 | B46: =K12 -> 0.19427914 | C46: =K13 -> 0.16264032 | D46: =K14 -> 0.14732479 | E46: =K15 -> 0.1322825 | F46: =K16 -> 0.10284816 | G46: =A46/Assumptions!$B$17 -> 101694.92
A47: 12250000 | B47: =K17 -> 0.18554339 | C47: =K18 -> 0.15354346 | D47: =K19 -> 0.13802828 | E47: =K20 -> 0.12277216 | F47: =K21 -> 0.092862117 | G47: =A47/Assumptions!$B$17 -> 103813.56
A48: 12750000 | B48: =K22 -> 0.16832466 | C48: =K23 -> 0.13556359 | D48: =K24 -> 0.11962563 | E48: =K25 -> 0.10391506 | F48: =K26 -> 0.072987593 | G48: =A48/Assumptions!$B$17 -> 108050.85
A49: 13250000 | B49: =K27 -> 0.15140514 | C49: =K28 -> 0.11782684 | D49: =K29 -> 0.10143188 | E49: =K30 -> 0.085227468 | F49: =K31 -> 0.053184387 | G49: =A49/Assumptions!$B$17 -> 112288.14
A50: 14200000 | B50: =K32 -> 0.11786625 | C50: =K33 -> 0.083740892 | D50: =K34 -> 0.067006663 | E50: =K35 -> 0.050413704 | F50: =K36 -> 0.017423219 | G50: =A50/Assumptions!$B$17 -> 120338.98
A51: 14750000 | B51: =K37 -> 0.098857245 | C51: =K38 -> 0.065208719 | D51: =K39 -> 0.048705703 | E51: =K40 -> 0.032340116 | F51: =K41 -> -0.00020453171 | G51: =A51/Assumptions!$B$17 -> 125000
A53: $14,200,000 is the price implied by the OM's 6.9% Year-1 cap rate; $12,250,000 ($103,814/unit) is the recommended bid, the highest basis at which this business plan clears a 14% levered IRR and a 1.8x multiple. Both cells are highlighted in the 6.75% column. Note that below roughly $13.5mm the loan is constrained by maximum loan-to-cost, and above it by the 8.0% minimum debt yield.
A55: GRID 1B — EQUITY MULTIPLE: PURCHASE PRICE × EXIT CAP
A56: Purchase Price \ Exit Cap | B56: 0.06 | C56: 0.065 | D56: 0.0675 | E56: 0.07 | F56: 0.075
A57: 11500000 | B57: =L7 -> 2.4265243 | C57: =L8 -> 2.1410234 | D57: =L9 -> 2.0141341 | E57: =L10 -> 1.8963084 | F57: =L11 -> 1.684222
A58: 12000000 | B58: =L12 -> 2.272484 | C58: =L13 -> 1.9963643 | D58: =L14 -> 1.8736444 | E58: =L15 -> 1.7596902 | F58: =L16 -> 1.5545727
A59: 12250000 | B59: =L17 -> 2.1991986 | C59: =L18 -> 1.9275421 | D59: =L19 -> 1.8068058 | E59: =L20 -> 1.6946936 | F59: =L21 -> 1.4928916
A60: 12750000 | B60: =L22 -> 2.0595128 | C60: =L23 -> 1.7963632 | D60: =L24 -> 1.6794078 | E60: =L25 -> 1.5708064 | F60: =L26 -> 1.3753239
A61: 13250000 | B61: =L27 -> 1.9283099 | C61: =L28 -> 1.6731506 | D61: =L29 -> 1.5597466 | E61: =L30 -> 1.4544428 | F61: =L31 -> 1.2648959
A62: 14200000 | B62: =L32 -> 1.6840747 | C62: =L33 -> 1.4524429 | D62: =L34 -> 1.3494954 | E62: =L35 -> 1.2539014 | F62: =L36 -> 1.081832
A63: 14750000 | B63: =L37 -> 1.5552358 | C63: =L38 -> 1.3413248 | D63: =L39 -> 1.2462533 | E63: =L40 -> 1.1579725 | F63: =L41 -> 0.99906722
A66: HELPER BLOCK 2 — RENOVATION PREMIUM × EXIT CAP (live cash flows)
A67: Blended Premium ($/unit/month) | B67: Exit Cap | C67: Δ vs Base | D67: Loan | E67: Year 0 | F67: Year 1 | G67: Year 2 | H67: Year 3 | I67: Year 4 | J67: Year 5 | K67: Levered IRR | L67: Y6 NOI | M67: Y1 NOI
A68: 125 | B68: 0.06 | C68: =A68-Assumptions!$B$39 -> -41.313559 | D68: =MIN(Returns!$C$22*Assumptions!$B$70,M68/Assumptions!$B$71,M68/(Assumptions!$B$72*Assumptions!$B$73)) -> 10852836 | E68: =-((Returns!$C$13-Returns!$C$27*Assumptions!$B$74)+D68*Assumptions!$B$74-D68) -> -6840211.9 | F68: ='Annual Model'!C59+$C68*'Annual Model'!C14*12*'Annual Model'!C10*(1-Assumptions!C$47-Assumptions!C$48-Assumptions!C$49-Assumptions!C$50)*(1-Assumptions!$B$56)-$D68*Assumptions!$B$73 -> 197935.98 | G68: ='Annual Model'!D59+$C68*'Annual Model'!D14*12*'Annual Model'!D10*(1-Assumptions!D$47-Assumptions!D$48-Assumptions!D$49-Assumptions!D$50)*(1-Assumptions!$B$56)-$D68*Assumptions!$B$73 -> 295935.9 | H68: ='Annual Model'!E59+$C68*'Annual Model'!E14*12*'Annual Model'!E10*(1-Assumptions!E$47-Assumptions!E$48-Assumptions!E$49-Assumptions!E$50)*(1-Assumptions!$B$56)-$D68*Assumptions!$B$73 -> 408700.95 | I68: ='Annual Model'!F59+$C68*'Annual Model'!F14*12*'Annual Model'!F10*(1-Assumptions!F$47-Assumptions!F$48-Assumptions!F$49-Assumptions!F$50)*(1-Assumptions!$B$56)-$D68*Assumptions!$B$73 -> 450083.08 | J68: ='Annual Model'!G59+$C68*'Annual Model'!G14*12*'Annual Model'!G10*(1-Assumptions!G$47-Assumptions!G$48-Assumptions!G$49-Assumptions!G$50)*(1-Assumptions!$B$56)-$D68*Assumptions!$B$73+(L68/B68)*(1-Assumptions!$B$13)-$D68 -> 8915916.2 | K68: =IRR(E68:J68) -> 0.090672814 | L68: ='Annual Model'!H50+$C68*Assumptions!$B$17*12*'Annual Model'!H10*(1-Assumptions!G$47-Assumptions!G$48-Assumptions!G$49-Assumptions!G$50)*(1-Assumptions!$B$56) -> 1175257.4 | M68: ='Annual Model'!C50+$C68*'Annual Model'!C14*12*'Annual Model'!C10*(1-Assumptions!C$47-Assumptions!C$48-Assumptions!C$49-Assumptions!C$50)*(1-Assumptions!$B$56) -> 868226.92
A69: 125 | B69: 0.065 | C69: =A69-Assumptions!$B$39 -> -41.313559 | D69: =MIN(Returns!$C$22*Assumptions!$B$70,M69/Assumptions!$B$71,M69/(Assumptions!$B$72*Assumptions!$B$73)) -> 10852836 | E69: =-((Returns!$C$13-Returns!$C$27*Assumptions!$B$74)+D69*Assumptions!$B$74-D69) -> -6840211.9 | F69: ='Annual Model'!C59+$C69*'Annual Model'!C14*12*'Annual Model'!C10*(1-Assumptions!C$47-Assumptions!C$48-Assumptions!C$49-Assumptions!C$50)*(1-Assumptions!$B$56)-$D69*Assumptions!$B$73 -> 197935.98 | G69: ='Annual Model'!D59+$C69*'Annual Model'!D14*12*'Annual Model'!D10*(1-Assumptions!D$47-Assumptions!D$48-Assumptions!D$49-Assumptions!D$50)*(1-Assumptions!$B$56)-$D69*Assumptions!$B$73 -> 295935.9 | H69: ='Annual Model'!E59+$C69*'Annual Model'!E14*12*'Annual Model'!E10*(1-Assumptions!E$47-Assumptions!E$48-Assumptions!E$49-Assumptions!E$50)*(1-Assumptions!$B$56)-$D69*Assumptions!$B$73 -> 408700.95 | I69: ='Annual Model'!F59+$C69*'Annual Model'!F14*12*'Annual Model'!F10*(1-Assumptions!F$47-Assumptions!F$48-Assumptions!F$49-Assumptions!F$50)*(1-Assumptions!$B$56)-$D69*Assumptions!$B$73 -> 450083.08 | J69: ='Annual Model'!G59+$C69*'Annual Model'!G14*12*'Annual Model'!G10*(1-Assumptions!G$47-Assumptions!G$48-Assumptions!G$49-Assumptions!G$50)*(1-Assumptions!$B$56)-$D69*Assumptions!$B$73+(L69/B69)*(1-Assumptions!$B$13)-$D69 -> 7431777.1 | K69: =IRR(E69:J69) -> 0.055365965 | L69: ='Annual Model'!H50+$C69*Assumptions!$B$17*12*'Annual Model'!H10*(1-Assumptions!G$47-Assumptions!G$48-Assumptions!G$49-Assumptions!G$50)*(1-Assumptions!$B$56) -> 1175257.4 | M69: ='Annual Model'!C50+$C69*'Annual Model'!C14*12*'Annual Model'!C10*(1-Assumptions!C$47-Assumptions!C$48-Assumptions!C$49-Assumptions!C$50)*(1-Assumptions!$B$56) -> 868226.92
A70: 125 | B70: 0.0675 | C70: =A70-Assumptions!$B$39 -> -41.313559 | D70: =MIN(Returns!$C$22*Assumptions!$B$70,M70/Assumptions!$B$71,M70/(Assumptions!$B$72*Assumptions!$B$73)) -> 10852836 | E70: =-((Returns!$C$13-Returns!$C$27*Assumptions!$B$74)+D70*Assumptions!$B$74-D70) -> -6840211.9 | F70: ='Annual Model'!C59+$C70*'Annual Model'!C14*12*'Annual Model'!C10*(1-Assumptions!C$47-Assumptions!C$48-Assumptions!C$49-Assumptions!C$50)*(1-Assumptions!$B$56)-$D70*Assumptions!$B$73 -> 197935.98 | G70: ='Annual Model'!D59+$C70*'Annual Model'!D14*12*'Annual Model'!D10*(1-Assumptions!D$47-Assumptions!D$48-Assumptions!D$49-Assumptions!D$50)*(1-Assumptions!$B$56)-$D70*Assumptions!$B$73 -> 295935.9 | H70: ='Annual Model'!E59+$C70*'Annual Model'!E14*12*'Annual Model'!E10*(1-Assumptions!E$47-Assumptions!E$48-Assumptions!E$49-Assumptions!E$50)*(1-Assumptions!$B$56)-$D70*Assumptions!$B$73 -> 408700.95 | I70: ='Annual Model'!F59+$C70*'Annual Model'!F14*12*'Annual Model'!F10*(1-Assumptions!F$47-Assumptions!F$48-Assumptions!F$49-Assumptions!F$50)*(1-Assumptions!$B$56)-$D70*Assumptions!$B$73 -> 450083.08 | J70: ='Annual Model'!G59+$C70*'Annual Model'!G14*12*'Annual Model'!G10*(1-Assumptions!G$47-Assumptions!G$48-Assumptions!G$49-Assumptions!G$50)*(1-Assumptions!$B$56)-$D70*Assumptions!$B$73+(L70/B70)*(1-Assumptions!$B$13)-$D70 -> 6772159.7 | K70: =IRR(E70:J70) -> 0.037945297 | L70: ='Annual Model'!H50+$C70*Assumptions!$B$17*12*'Annual Model'!H10*(1-Assumptions!G$47-Assumptions!G$48-Assumptions!G$49-Assumptions!G$50)*(1-Assumptions!$B$56) -> 1175257.4 | M70: ='Annual Model'!C50+$C70*'Annual Model'!C14*12*'Annual Model'!C10*(1-Assumptions!C$47-Assumptions!C$48-Assumptions!C$49-Assumptions!C$50)*(1-Assumptions!$B$56) -> 868226.92
A71: 125 | B71: 0.07 | C71: =A71-Assumptions!$B$39 -> -41.313559 | D71: =MIN(Returns!$C$22*Assumptions!$B$70,M71/Assumptions!$B$71,M71/(Assumptions!$B$72*Assumptions!$B$73)) -> 10852836 | E71: =-((Returns!$C$13-Returns!$C$27*Assumptions!$B$74)+D71*Assumptions!$B$74-D71) -> -6840211.9 | F71: ='Annual Model'!C59+$C71*'Annual Model'!C14*12*'Annual Model'!C10*(1-Assumptions!C$47-Assumptions!C$48-Assumptions!C$49-Assumptions!C$50)*(1-Assumptions!$B$56)-$D71*Assumptions!$B$73 -> 197935.98 | G71: ='Annual Model'!D59+$C71*'Annual Model'!D14*12*'Annual Model'!D10*(1-Assumptions!D$47-Assumptions!D$48-Assumptions!D$49-Assumptions!D$50)*(1-Assumptions!$B$56)-$D71*Assumptions!$B$73 -> 295935.9 | H71: ='Annual Model'!E59+$C71*'Annual Model'!E14*12*'Annual Model'!E10*(1-Assumptions!E$47-Assumptions!E$48-Assumptions!E$49-Assumptions!E$50)*(1-Assumptions!$B$56)-$D71*Assumptions!$B$73 -> 408700.95 | I71: ='Annual Model'!F59+$C71*'Annual Model'!F14*12*'Annual Model'!F10*(1-Assumptions!F$47-Assumptions!F$48-Assumptions!F$49-Assumptions!F$50)*(1-Assumptions!$B$56)-$D71*Assumptions!$B$73 -> 450083.08 | J71: ='Annual Model'!G59+$C71*'Annual Model'!G14*12*'Annual Model'!G10*(1-Assumptions!G$47-Assumptions!G$48-Assumptions!G$49-Assumptions!G$50)*(1-Assumptions!$B$56)-$D71*Assumptions!$B$73+(L71/B71)*(1-Assumptions!$B$13)-$D71 -> 6159657.8 | K71: =IRR(E71:J71) -> 0.020591232 | L71: ='Annual Model'!H50+$C71*Assumptions!$B$17*12*'Annual Model'!H10*(1-Assumptions!G$47-Assumptions!G$48-Assumptions!G$49-Assumptions!G$50)*(1-Assumptions!$B$56) -> 1175257.4 | M71: ='Annual Model'!C50+$C71*'Annual Model'!C14*12*'Annual Model'!C10*(1-Assumptions!C$47-Assumptions!C$48-Assumptions!C$49-Assumptions!C$50)*(1-Assumptions!$B$56) -> 868226.92
A72: 125 | B72: 0.075 | C72: =A72-Assumptions!$B$39 -> -41.313559 | D72: =MIN(Returns!$C$22*Assumptions!$B$70,M72/Assumptions!$B$71,M72/(Assumptions!$B$72*Assumptions!$B$73)) -> 10852836 | E72: =-((Returns!$C$13-Returns!$C$27*Assumptions!$B$74)+D72*Assumptions!$B$74-D72) -> -6840211.9 | F72: ='Annual Model'!C59+$C72*'Annual Model'!C14*12*'Annual Model'!C10*(1-Assumptions!C$47-Assumptions!C$48-Assumptions!C$49-Assumptions!C$50)*(1-Assumptions!$B$56)-$D72*Assumptions!$B$73 -> 197935.98 | G72: ='Annual Model'!D59+$C72*'Annual Model'!D14*12*'Annual Model'!D10*(1-Assumptions!D$47-Assumptions!D$48-Assumptions!D$49-Assumptions!D$50)*(1-Assumptions!$B$56)-$D72*Assumptions!$B$73 -> 295935.9 | H72: ='Annual Model'!E59+$C72*'Annual Model'!E14*12*'Annual Model'!E10*(1-Assumptions!E$47-Assumptions!E$48-Assumptions!E$49-Assumptions!E$50)*(1-Assumptions!$B$56)-$D72*Assumptions!$B$73 -> 408700.95 | I72: ='Annual Model'!F59+$C72*'Annual Model'!F14*12*'Annual Model'!F10*(1-Assumptions!F$47-Assumptions!F$48-Assumptions!F$49-Assumptions!F$50)*(1-Assumptions!$B$56)-$D72*Assumptions!$B$73 -> 450083.08 | J72: ='Annual Model'!G59+$C72*'Annual Model'!G14*12*'Annual Model'!G10*(1-Assumptions!G$47-Assumptions!G$48-Assumptions!G$49-Assumptions!G$50)*(1-Assumptions!$B$56)-$D72*Assumptions!$B$73+(L72/B72)*(1-Assumptions!$B$13)-$D72 -> 5057154.4 | K72: =IRR(E72:J72) -> -0.014189626 | L72: ='Annual Model'!H50+$C72*Assumptions!$B$17*12*'Annual Model'!H10*(1-Assumptions!G$47-Assumptions!G$48-Assumptions!G$49-Assumptions!G$50)*(1-Assumptions!$B$56) -> 1175257.4 | M72: ='Annual Model'!C50+$C72*'Annual Model'!C14*12*'Annual Model'!C10*(1-Assumptions!C$47-Assumptions!C$48-Assumptions!C$49-Assumptions!C$50)*(1-Assumptions!$B$56) -> 868226.92
A73: 150 | B73: 0.06 | C73: =A73-Assumptions!$B$39 -> -16.313559 | D73: =MIN(Returns!$C$22*Assumptions!$B$70,M73/Assumptions!$B$71,M73/(Assumptions!$B$72*Assumptions!$B$73)) -> 10914868 | E73: =-((Returns!$C$13-Returns!$C$27*Assumptions!$B$74)+D73*Assumptions!$B$74-D73) -> -6778800.9 | F73: ='Annual Model'!C59+$C73*'Annual Model'!C14*12*'Annual Model'!C10*(1-Assumptions!C$47-Assumptions!C$48-Assumptions!C$49-Assumptions!C$50)*(1-Assumptions!$B$56)-$D73*Assumptions!$B$73 -> 199269.66 | G73: ='Annual Model'!D59+$C73*'Annual Model'!D14*12*'Annual Model'!D10*(1-Assumptions!D$47-Assumptions!D$48-Assumptions!D$49-Assumptions!D$50)*(1-Assumptions!$B$56)-$D73*Assumptions!$B$73 -> 313539.1 | H73: ='Annual Model'!E59+$C73*'Annual Model'!E14*12*'Annual Model'!E10*(1-Assumptions!E$47-Assumptions!E$48-Assumptions!E$49-Assumptions!E$50)*(1-Assumptions!$B$56)-$D73*Assumptions!$B$73 -> 438292.28 | I73: ='Annual Model'!F59+$C73*'Annual Model'!F14*12*'Annual Model'!F10*(1-Assumptions!F$47-Assumptions!F$48-Assumptions!F$49-Assumptions!F$50)*(1-Assumptions!$B$56)-$D73*Assumptions!$B$73 -> 481127.34 | J73: ='Annual Model'!G59+$C73*'Annual Model'!G14*12*'Annual Model'!G10*(1-Assumptions!G$47-Assumptions!G$48-Assumptions!G$49-Assumptions!G$50)*(1-Assumptions!$B$56)-$D73*Assumptions!$B$73+(L73/B73)*(1-Assumptions!$B$13)-$D73 -> 9489851.3 | K73: =IRR(E73:J73) -> 0.10731762 | L73: ='Annual Model'!H50+$C73*Assumptions!$B$17*12*'Annual Model'!H10*(1-Assumptions!G$47-Assumptions!G$48-Assumptions!G$49-Assumptions!G$50)*(1-Assumptions!$B$56) -> 1212042.1 | M73: ='Annual Model'!C50+$C73*'Annual Model'!C14*12*'Annual Model'!C10*(1-Assumptions!C$47-Assumptions!C$48-Assumptions!C$49-Assumptions!C$50)*(1-Assumptions!$B$56) -> 873189.42
A74: 150 | B74: 0.065 | C74: =A74-Assumptions!$B$39 -> -16.313559 | D74: =MIN(Returns!$C$22*Assumptions!$B$70,M74/Assumptions!$B$71,M74/(Assumptions!$B$72*Assumptions!$B$73)) -> 10914868 | E74: =-((Returns!$C$13-Returns!$C$27*Assumptions!$B$74)+D74*Assumptions!$B$74-D74) -> -6778800.9 | F74: ='Annual Model'!C59+$C74*'Annual Model'!C14*12*'Annual Model'!C10*(1-Assumptions!C$47-Assumptions!C$48-Assumptions!C$49-Assumptions!C$50)*(1-Assumptions!$B$56)-$D74*Assumptions!$B$73 -> 199269.66 | G74: ='Annual Model'!D59+$C74*'Annual Model'!D14*12*'Annual Model'!D10*(1-Assumptions!D$47-Assumptions!D$48-Assumptions!D$49-Assumptions!D$50)*(1-Assumptions!$B$56)-$D74*Assumptions!$B$73 -> 313539.1 | H74: ='Annual Model'!E59+$C74*'Annual Model'!E14*12*'Annual Model'!E10*(1-Assumptions!E$47-Assumptions!E$48-Assumptions!E$49-Assumptions!E$50)*(1-Assumptions!$B$56)-$D74*Assumptions!$B$73 -> 438292.28 | I74: ='Annual Model'!F59+$C74*'Annual Model'!F14*12*'Annual Model'!F10*(1-Assumptions!F$47-Assumptions!F$48-Assumptions!F$49-Assumptions!F$50)*(1-Assumptions!$B$56)-$D74*Assumptions!$B$73 -> 481127.34 | J74: ='Annual Model'!G59+$C74*'Annual Model'!G14*12*'Annual Model'!G10*(1-Assumptions!G$47-Assumptions!G$48-Assumptions!G$49-Assumptions!G$50)*(1-Assumptions!$B$56)-$D74*Assumptions!$B$73+(L74/B74)*(1-Assumptions!$B$13)-$D74 -> 7959259.7 | K74: =IRR(E74:J74) -> 0.072757539 | L74: ='Annual Model'!H50+$C74*Assumptions!$B$17*12*'Annual Model'!H10*(1-Assumptions!G$47-Assumptions!G$48-Assumptions!G$49-Assumptions!G$50)*(1-Assumptions!$B$56) -> 1212042.1 | M74: ='Annual Model'!C50+$C74*'Annual Model'!C14*12*'Annual Model'!C10*(1-Assumptions!C$47-Assumptions!C$48-Assumptions!C$49-Assumptions!C$50)*(1-Assumptions!$B$56) -> 873189.42
A75: 150 | B75: 0.0675 | C75: =A75-Assumptions!$B$39 -> -16.313559 | D75: =MIN(Returns!$C$22*Assumptions!$B$70,M75/Assumptions!$B$71,M75/(Assumptions!$B$72*Assumptions!$B$73)) -> 10914868 | E75: =-((Returns!$C$13-Returns!$C$27*Assumptions!$B$74)+D75*Assumptions!$B$74-D75) -> -6778800.9 | F75: ='Annual Model'!C59+$C75*'Annual Model'!C14*12*'Annual Model'!C10*(1-Assumptions!C$47-Assumptions!C$48-Assumptions!C$49-Assumptions!C$50)*(1-Assumptions!$B$56)-$D75*Assumptions!$B$73 -> 199269.66 | G75: ='Annual Model'!D59+$C75*'Annual Model'!D14*12*'Annual Model'!D10*(1-Assumptions!D$47-Assumptions!D$48-Assumptions!D$49-Assumptions!D$50)*(1-Assumptions!$B$56)-$D75*Assumptions!$B$73 -> 313539.1 | H75: ='Annual Model'!E59+$C75*'Annual Model'!E14*12*'Annual Model'!E10*(1-Assumptions!E$47-Assumptions!E$48-Assumptions!E$49-Assumptions!E$50)*(1-Assumptions!$B$56)-$D75*Assumptions!$B$73 -> 438292.28 | I75: ='Annual Model'!F59+$C75*'Annual Model'!F14*12*'Annual Model'!F10*(1-Assumptions!F$47-Assumptions!F$48-Assumptions!F$49-Assumptions!F$50)*(1-Assumptions!$B$56)-$D75*Assumptions!$B$73 -> 481127.34 | J75: ='Annual Model'!G59+$C75*'Annual Model'!G14*12*'Annual Model'!G10*(1-Assumptions!G$47-Assumptions!G$48-Assumptions!G$49-Assumptions!G$50)*(1-Assumptions!$B$56)-$D75*Assumptions!$B$73+(L75/B75)*(1-Assumptions!$B$13)-$D75 -> 7278996.8 | K75: =IRR(E75:J75) -> 0.055771496 | L75: ='Annual Model'!H50+$C75*Assumptions!$B$17*12*'Annual Model'!H10*(1-Assumptions!G$47-Assumptions!G$48-Assumptions!G$49-Assumptions!G$50)*(1-Assumptions!$B$56) -> 1212042.1 | M75: ='Annual Model'!C50+$C75*'Annual Model'!C14*12*'Annual Model'!C10*(1-Assumptions!C$47-Assumptions!C$48-Assumptions!C$49-Assumptions!C$50)*(1-Assumptions!$B$56) -> 873189.42
A76: 150 | B76: 0.07 | C76: =A76-Assumptions!$B$39 -> -16.313559 | D76: =MIN(Returns!$C$22*Assumptions!$B$70,M76/Assumptions!$B$71,M76/(Assumptions!$B$72*Assumptions!$B$73)) -> 10914868 | E76: =-((Returns!$C$13-Returns!$C$27*Assumptions!$B$74)+D76*Assumptions!$B$74-D76) -> -6778800.9 | F76: ='Annual Model'!C59+$C76*'Annual Model'!C14*12*'Annual Model'!C10*(1-Assumptions!C$47-Assumptions!C$48-Assumptions!C$49-Assumptions!C$50)*(1-Assumptions!$B$56)-$D76*Assumptions!$B$73 -> 199269.66 | G76: ='Annual Model'!D59+$C76*'Annual Model'!D14*12*'Annual Model'!D10*(1-Assumptions!D$47-Assumptions!D$48-Assumptions!D$49-Assumptions!D$50)*(1-Assumptions!$B$56)-$D76*Assumptions!$B$73 -> 313539.1 | H76: ='Annual Model'!E59+$C76*'Annual Model'!E14*12*'Annual Model'!E10*(1-Assumptions!E$47-Assumptions!E$48-Assumptions!E$49-Assumptions!E$50)*(1-Assumptions!$B$56)-$D76*Assumptions!$B$73 -> 438292.28 | I76: ='Annual Model'!F59+$C76*'Annual Model'!F14*12*'Annual Model'!F10*(1-Assumptions!F$47-Assumptions!F$48-Assumptions!F$49-Assumptions!F$50)*(1-Assumptions!$B$56)-$D76*Assumptions!$B$73 -> 481127.34 | J76: ='Annual Model'!G59+$C76*'Annual Model'!G14*12*'Annual Model'!G10*(1-Assumptions!G$47-Assumptions!G$48-Assumptions!G$49-Assumptions!G$50)*(1-Assumptions!$B$56)-$D76*Assumptions!$B$73+(L76/B76)*(1-Assumptions!$B$13)-$D76 -> 6647324 | K76: =IRR(E76:J76) -> 0.038900049 | L76: ='Annual Model'!H50+$C76*Assumptions!$B$17*12*'Annual Model'!H10*(1-Assumptions!G$47-Assumptions!G$48-Assumptions!G$49-Assumptions!G$50)*(1-Assumptions!$B$56) -> 1212042.1 | M76: ='Annual Model'!C50+$C76*'Annual Model'!C14*12*'Annual Model'!C10*(1-Assumptions!C$47-Assumptions!C$48-Assumptions!C$49-Assumptions!C$50)*(1-Assumptions!$B$56) -> 873189.42
A77: 150 | B77: 0.075 | C77: =A77-Assumptions!$B$39 -> -16.313559 | D77: =MIN(Returns!$C$22*Assumptions!$B$70,M77/Assumptions!$B$71,M77/(Assumptions!$B$72*Assumptions!$B$73)) -> 10914868 | E77: =-((Returns!$C$13-Returns!$C$27*Assumptions!$B$74)+D77*Assumptions!$B$74-D77) -> -6778800.9 | F77: ='Annual Model'!C59+$C77*'Annual Model'!C14*12*'Annual Model'!C10*(1-Assumptions!C$47-Assumptions!C$48-Assumptions!C$49-Assumptions!C$50)*(1-Assumptions!$B$56)-$D77*Assumptions!$B$73 -> 199269.66 | G77: ='Annual Model'!D59+$C77*'Annual Model'!D14*12*'Annual Model'!D10*(1-Assumptions!D$47-Assumptions!D$48-Assumptions!D$49-Assumptions!D$50)*(1-Assumptions!$B$56)-$D77*Assumptions!$B$73 -> 313539.1 | H77: ='Annual Model'!E59+$C77*'Annual Model'!E14*12*'Annual Model'!E10*(1-Assumptions!E$47-Assumptions!E$48-Assumptions!E$49-Assumptions!E$50)*(1-Assumptions!$B$56)-$D77*Assumptions!$B$73 -> 438292.28 | I77: ='Annual Model'!F59+$C77*'Annual Model'!F14*12*'Annual Model'!F10*(1-Assumptions!F$47-Assumptions!F$48-Assumptions!F$49-Assumptions!F$50)*(1-Assumptions!$B$56)-$D77*Assumptions!$B$73 -> 481127.34 | J77: ='Annual Model'!G59+$C77*'Annual Model'!G14*12*'Annual Model'!G10*(1-Assumptions!G$47-Assumptions!G$48-Assumptions!G$49-Assumptions!G$50)*(1-Assumptions!$B$56)-$D77*Assumptions!$B$73+(L77/B77)*(1-Assumptions!$B$13)-$D77 -> 5510313.1 | K77: =IRR(E77:J77) -> 0.0052576487 | L77: ='Annual Model'!H50+$C77*Assumptions!$B$17*12*'Annual Model'!H10*(1-Assumptions!G$47-Assumptions!G$48-Assumptions!G$49-Assumptions!G$50)*(1-Assumptions!$B$56) -> 1212042.1 | M77: ='Annual Model'!C50+$C77*'Annual Model'!C14*12*'Annual Model'!C10*(1-Assumptions!C$47-Assumptions!C$48-Assumptions!C$49-Assumptions!C$50)*(1-Assumptions!$B$56) -> 873189.42
A78: 166 | B78: 0.06 | C78: =A78-Assumptions!$B$39 -> -0.31355932 | D78: =MIN(Returns!$C$22*Assumptions!$B$70,M78/Assumptions!$B$71,M78/(Assumptions!$B$72*Assumptions!$B$73)) -> 10954568 | E78: =-((Returns!$C$13-Returns!$C$27*Assumptions!$B$74)+D78*Assumptions!$B$74-D78) -> -6739497.9 | F78: ='Annual Model'!C59+$C78*'Annual Model'!C14*12*'Annual Model'!C10*(1-Assumptions!C$47-Assumptions!C$48-Assumptions!C$49-Assumptions!C$50)*(1-Assumptions!$B$56)-$D78*Assumptions!$B$73 -> 200123.21 | G78: ='Annual Model'!D59+$C78*'Annual Model'!D14*12*'Annual Model'!D10*(1-Assumptions!D$47-Assumptions!D$48-Assumptions!D$49-Assumptions!D$50)*(1-Assumptions!$B$56)-$D78*Assumptions!$B$73 -> 324805.14 | H78: ='Annual Model'!E59+$C78*'Annual Model'!E14*12*'Annual Model'!E10*(1-Assumptions!E$47-Assumptions!E$48-Assumptions!E$49-Assumptions!E$50)*(1-Assumptions!$B$56)-$D78*Assumptions!$B$73 -> 457230.73 | I78: ='Annual Model'!F59+$C78*'Annual Model'!F14*12*'Annual Model'!F10*(1-Assumptions!F$47-Assumptions!F$48-Assumptions!F$49-Assumptions!F$50)*(1-Assumptions!$B$56)-$D78*Assumptions!$B$73 -> 500995.67 | J78: ='Annual Model'!G59+$C78*'Annual Model'!G14*12*'Annual Model'!G10*(1-Assumptions!G$47-Assumptions!G$48-Assumptions!G$49-Assumptions!G$50)*(1-Assumptions!$B$56)-$D78*Assumptions!$B$73+(L78/B78)*(1-Assumptions!$B$13)-$D78 -> 9857169.8 | K78: =IRR(E78:J78) -> 0.11766568 | L78: ='Annual Model'!H50+$C78*Assumptions!$B$17*12*'Annual Model'!H10*(1-Assumptions!G$47-Assumptions!G$48-Assumptions!G$49-Assumptions!G$50)*(1-Assumptions!$B$56) -> 1235584.3 | M78: ='Annual Model'!C50+$C78*'Annual Model'!C14*12*'Annual Model'!C10*(1-Assumptions!C$47-Assumptions!C$48-Assumptions!C$49-Assumptions!C$50)*(1-Assumptions!$B$56) -> 876365.42
A79: 166 | B79: 0.065 | C79: =A79-Assumptions!$B$39 -> -0.31355932 | D79: =MIN(Returns!$C$22*Assumptions!$B$70,M79/Assumptions!$B$71,M79/(Assumptions!$B$72*Assumptions!$B$73)) -> 10954568 | E79: =-((Returns!$C$13-Returns!$C$27*Assumptions!$B$74)+D79*Assumptions!$B$74-D79) -> -6739497.9 | F79: ='Annual Model'!C59+$C79*'Annual Model'!C14*12*'Annual Model'!C10*(1-Assumptions!C$47-Assumptions!C$48-Assumptions!C$49-Assumptions!C$50)*(1-Assumptions!$B$56)-$D79*Assumptions!$B$73 -> 200123.21 | G79: ='Annual Model'!D59+$C79*'Annual Model'!D14*12*'Annual Model'!D10*(1-Assumptions!D$47-Assumptions!D$48-Assumptions!D$49-Assumptions!D$50)*(1-Assumptions!$B$56)-$D79*Assumptions!$B$73 -> 324805.14 | H79: ='Annual Model'!E59+$C79*'Annual Model'!E14*12*'Annual Model'!E10*(1-Assumptions!E$47-Assumptions!E$48-Assumptions!E$49-Assumptions!E$50)*(1-Assumptions!$B$56)-$D79*Assumptions!$B$73 -> 457230.73 | I79: ='Annual Model'!F59+$C79*'Annual Model'!F14*12*'Annual Model'!F10*(1-Assumptions!F$47-Assumptions!F$48-Assumptions!F$49-Assumptions!F$50)*(1-Assumptions!$B$56)-$D79*Assumptions!$B$73 -> 500995.67 | J79: ='Annual Model'!G59+$C79*'Annual Model'!G14*12*'Annual Model'!G10*(1-Assumptions!G$47-Assumptions!G$48-Assumptions!G$49-Assumptions!G$50)*(1-Assumptions!$B$56)-$D79*Assumptions!$B$73+(L79/B79)*(1-Assumptions!$B$13)-$D79 -> 8296848.6 | K79: =IRR(E79:J79) -> 0.083532315 | L79: ='Annual Model'!H50+$C79*Assumptions!$B$17*12*'Annual Model'!H10*(1-Assumptions!G$47-Assumptions!G$48-Assumptions!G$49-Assumptions!G$50)*(1-Assumptions!$B$56) -> 1235584.3 | M79: ='Annual Model'!C50+$C79*'Annual Model'!C14*12*'Annual Model'!C10*(1-Assumptions!C$47-Assumptions!C$48-Assumptions!C$49-Assumptions!C$50)*(1-Assumptions!$B$56) -> 876365.42
A80: 166 | B80: 0.0675 | C80: =A80-Assumptions!$B$39 -> -0.31355932 | D80: =MIN(Returns!$C$22*Assumptions!$B$70,M80/Assumptions!$B$71,M80/(Assumptions!$B$72*Assumptions!$B$73)) -> 10954568 | E80: =-((Returns!$C$13-Returns!$C$27*Assumptions!$B$74)+D80*Assumptions!$B$74-D80) -> -6739497.9 | F80: ='Annual Model'!C59+$C80*'Annual Model'!C14*12*'Annual Model'!C10*(1-Assumptions!C$47-Assumptions!C$48-Assumptions!C$49-Assumptions!C$50)*(1-Assumptions!$B$56)-$D80*Assumptions!$B$73 -> 200123.21 | G80: ='Annual Model'!D59+$C80*'Annual Model'!D14*12*'Annual Model'!D10*(1-Assumptions!D$47-Assumptions!D$48-Assumptions!D$49-Assumptions!D$50)*(1-Assumptions!$B$56)-$D80*Assumptions!$B$73 -> 324805.14 | H80: ='Annual Model'!E59+$C80*'Annual Model'!E14*12*'Annual Model'!E10*(1-Assumptions!E$47-Assumptions!E$48-Assumptions!E$49-Assumptions!E$50)*(1-Assumptions!$B$56)-$D80*Assumptions!$B$73 -> 457230.73 | I80: ='Annual Model'!F59+$C80*'Annual Model'!F14*12*'Annual Model'!F10*(1-Assumptions!F$47-Assumptions!F$48-Assumptions!F$49-Assumptions!F$50)*(1-Assumptions!$B$56)-$D80*Assumptions!$B$73 -> 500995.67 | J80: ='Annual Model'!G59+$C80*'Annual Model'!G14*12*'Annual Model'!G10*(1-Assumptions!G$47-Assumptions!G$48-Assumptions!G$49-Assumptions!G$50)*(1-Assumptions!$B$56)-$D80*Assumptions!$B$73+(L80/B80)*(1-Assumptions!$B$13)-$D80 -> 7603372.5 | K80: =IRR(E80:J80) -> 0.066793459 | L80: ='Annual Model'!H50+$C80*Assumptions!$B$17*12*'Annual Model'!H10*(1-Assumptions!G$47-Assumptions!G$48-Assumptions!G$49-Assumptions!G$50)*(1-Assumptions!$B$56) -> 1235584.3 | M80: ='Annual Model'!C50+$C80*'Annual Model'!C14*12*'Annual Model'!C10*(1-Assumptions!C$47-Assumptions!C$48-Assumptions!C$49-Assumptions!C$50)*(1-Assumptions!$B$56) -> 876365.42
A81: 166 | B81: 0.07 | C81: =A81-Assumptions!$B$39 -> -0.31355932 | D81: =MIN(Returns!$C$22*Assumptions!$B$70,M81/Assumptions!$B$71,M81/(Assumptions!$B$72*Assumptions!$B$73)) -> 10954568 | E81: =-((Returns!$C$13-Returns!$C$27*Assumptions!$B$74)+D81*Assumptions!$B$74-D81) -> -6739497.9 | F81: ='Annual Model'!C59+$C81*'Annual Model'!C14*12*'Annual Model'!C10*(1-Assumptions!C$47-Assumptions!C$48-Assumptions!C$49-Assumptions!C$50)*(1-Assumptions!$B$56)-$D81*Assumptions!$B$73 -> 200123.21 | G81: ='Annual Model'!D59+$C81*'Annual Model'!D14*12*'Annual Model'!D10*(1-Assumptions!D$47-Assumptions!D$48-Assumptions!D$49-Assumptions!D$50)*(1-Assumptions!$B$56)-$D81*Assumptions!$B$73 -> 324805.14 | H81: ='Annual Model'!E59+$C81*'Annual Model'!E14*12*'Annual Model'!E10*(1-Assumptions!E$47-Assumptions!E$48-Assumptions!E$49-Assumptions!E$50)*(1-Assumptions!$B$56)-$D81*Assumptions!$B$73 -> 457230.73 | I81: ='Annual Model'!F59+$C81*'Annual Model'!F14*12*'Annual Model'!F10*(1-Assumptions!F$47-Assumptions!F$48-Assumptions!F$49-Assumptions!F$50)*(1-Assumptions!$B$56)-$D81*Assumptions!$B$73 -> 500995.67 | J81: ='Annual Model'!G59+$C81*'Annual Model'!G14*12*'Annual Model'!G10*(1-Assumptions!G$47-Assumptions!G$48-Assumptions!G$49-Assumptions!G$50)*(1-Assumptions!$B$56)-$D81*Assumptions!$B$73+(L81/B81)*(1-Assumptions!$B$13)-$D81 -> 6959430.4 | K81: =IRR(E81:J81) -> 0.050195389 | L81: ='Annual Model'!H50+$C81*Assumptions!$B$17*12*'Annual Model'!H10*(1-Assumptions!G$47-Assumptions!G$48-Assumptions!G$49-Assumptions!G$50)*(1-Assumptions!$B$56) -> 1235584.3 | M81: ='Annual Model'!C50+$C81*'Annual Model'!C14*12*'Annual Model'!C10*(1-Assumptions!C$47-Assumptions!C$48-Assumptions!C$49-Assumptions!C$50)*(1-Assumptions!$B$56) -> 876365.42
A82: 166 | B82: 0.075 | C82: =A82-Assumptions!$B$39 -> -0.31355932 | D82: =MIN(Returns!$C$22*Assumptions!$B$70,M82/Assumptions!$B$71,M82/(Assumptions!$B$72*Assumptions!$B$73)) -> 10954568 | E82: =-((Returns!$C$13-Returns!$C$27*Assumptions!$B$74)+D82*Assumptions!$B$74-D82) -> -6739497.9 | F82: ='Annual Model'!C59+$C82*'Annual Model'!C14*12*'Annual Model'!C10*(1-Assumptions!C$47-Assumptions!C$48-Assumptions!C$49-Assumptions!C$50)*(1-Assumptions!$B$56)-$D82*Assumptions!$B$73 -> 200123.21 | G82: ='Annual Model'!D59+$C82*'Annual Model'!D14*12*'Annual Model'!D10*(1-Assumptions!D$47-Assumptions!D$48-Assumptions!D$49-Assumptions!D$50)*(1-Assumptions!$B$56)-$D82*Assumptions!$B$73 -> 324805.14 | H82: ='Annual Model'!E59+$C82*'Annual Model'!E14*12*'Annual Model'!E10*(1-Assumptions!E$47-Assumptions!E$48-Assumptions!E$49-Assumptions!E$50)*(1-Assumptions!$B$56)-$D82*Assumptions!$B$73 -> 457230.73 | I82: ='Annual Model'!F59+$C82*'Annual Model'!F14*12*'Annual Model'!F10*(1-Assumptions!F$47-Assumptions!F$48-Assumptions!F$49-Assumptions!F$50)*(1-Assumptions!$B$56)-$D82*Assumptions!$B$73 -> 500995.67 | J82: ='Annual Model'!G59+$C82*'Annual Model'!G14*12*'Annual Model'!G10*(1-Assumptions!G$47-Assumptions!G$48-Assumptions!G$49-Assumptions!G$50)*(1-Assumptions!$B$56)-$D82*Assumptions!$B$73+(L82/B82)*(1-Assumptions!$B$13)-$D82 -> 5800334.7 | K82: =IRR(E82:J82) -> 0.017192972 | L82: ='Annual Model'!H50+$C82*Assumptions!$B$17*12*'Annual Model'!H10*(1-Assumptions!G$47-Assumptions!G$48-Assumptions!G$49-Assumptions!G$50)*(1-Assumptions!$B$56) -> 1235584.3 | M82: ='Annual Model'!C50+$C82*'Annual Model'!C14*12*'Annual Model'!C10*(1-Assumptions!C$47-Assumptions!C$48-Assumptions!C$49-Assumptions!C$50)*(1-Assumptions!$B$56) -> 876365.42
A83: 190 | B83: 0.06 | C83: =A83-Assumptions!$B$39 -> 23.686441 | D83: =MIN(Returns!$C$22*Assumptions!$B$70,M83/Assumptions!$B$71,M83/(Assumptions!$B$72*Assumptions!$B$73)) -> 11014118 | E83: =-((Returns!$C$13-Returns!$C$27*Assumptions!$B$74)+D83*Assumptions!$B$74-D83) -> -6680543.3 | F83: ='Annual Model'!C59+$C83*'Annual Model'!C14*12*'Annual Model'!C10*(1-Assumptions!C$47-Assumptions!C$48-Assumptions!C$49-Assumptions!C$50)*(1-Assumptions!$B$56)-$D83*Assumptions!$B$73 -> 201403.53 | G83: ='Annual Model'!D59+$C83*'Annual Model'!D14*12*'Annual Model'!D10*(1-Assumptions!D$47-Assumptions!D$48-Assumptions!D$49-Assumptions!D$50)*(1-Assumptions!$B$56)-$D83*Assumptions!$B$73 -> 341704.21 | H83: ='Annual Model'!E59+$C83*'Annual Model'!E14*12*'Annual Model'!E10*(1-Assumptions!E$47-Assumptions!E$48-Assumptions!E$49-Assumptions!E$50)*(1-Assumptions!$B$56)-$D83*Assumptions!$B$73 -> 485638.41 | I83: ='Annual Model'!F59+$C83*'Annual Model'!F14*12*'Annual Model'!F10*(1-Assumptions!F$47-Assumptions!F$48-Assumptions!F$49-Assumptions!F$50)*(1-Assumptions!$B$56)-$D83*Assumptions!$B$73 -> 530798.17 | J83: ='Annual Model'!G59+$C83*'Annual Model'!G14*12*'Annual Model'!G10*(1-Assumptions!G$47-Assumptions!G$48-Assumptions!G$49-Assumptions!G$50)*(1-Assumptions!$B$56)-$D83*Assumptions!$B$73+(L83/B83)*(1-Assumptions!$B$13)-$D83 -> 10408147 | K83: =IRR(E83:J83) -> 0.1327857 | L83: ='Annual Model'!H50+$C83*Assumptions!$B$17*12*'Annual Model'!H10*(1-Assumptions!G$47-Assumptions!G$48-Assumptions!G$49-Assumptions!G$50)*(1-Assumptions!$B$56) -> 1270897.6 | M83: ='Annual Model'!C50+$C83*'Annual Model'!C14*12*'Annual Model'!C10*(1-Assumptions!C$47-Assumptions!C$48-Assumptions!C$49-Assumptions!C$50)*(1-Assumptions!$B$56) -> 881129.43
A84: 190 | B84: 0.065 | C84: =A84-Assumptions!$B$39 -> 23.686441 | D84: =MIN(Returns!$C$22*Assumptions!$B$70,M84/Assumptions!$B$71,M84/(Assumptions!$B$72*Assumptions!$B$73)) -> 11014118 | E84: =-((Returns!$C$13-Returns!$C$27*Assumptions!$B$74)+D84*Assumptions!$B$74-D84) -> -6680543.3 | F84: ='Annual Model'!C59+$C84*'Annual Model'!C14*12*'Annual Model'!C10*(1-Assumptions!C$47-Assumptions!C$48-Assumptions!C$49-Assumptions!C$50)*(1-Assumptions!$B$56)-$D84*Assumptions!$B$73 -> 201403.53 | G84: ='Annual Model'!D59+$C84*'Annual Model'!D14*12*'Annual Model'!D10*(1-Assumptions!D$47-Assumptions!D$48-Assumptions!D$49-Assumptions!D$50)*(1-Assumptions!$B$56)-$D84*Assumptions!$B$73 -> 341704.21 | H84: ='Annual Model'!E59+$C84*'Annual Model'!E14*12*'Annual Model'!E10*(1-Assumptions!E$47-Assumptions!E$48-Assumptions!E$49-Assumptions!E$50)*(1-Assumptions!$B$56)-$D84*Assumptions!$B$73 -> 485638.41 | I84: ='Annual Model'!F59+$C84*'Annual Model'!F14*12*'Annual Model'!F10*(1-Assumptions!F$47-Assumptions!F$48-Assumptions!F$49-Assumptions!F$50)*(1-Assumptions!$B$56)-$D84*Assumptions!$B$73 -> 530798.17 | J84: ='Annual Model'!G59+$C84*'Annual Model'!G14*12*'Annual Model'!G10*(1-Assumptions!G$47-Assumptions!G$48-Assumptions!G$49-Assumptions!G$50)*(1-Assumptions!$B$56)-$D84*Assumptions!$B$73+(L84/B84)*(1-Assumptions!$B$13)-$D84 -> 8803231.9 | K84: =IRR(E84:J84) -> 0.099228385 | L84: ='Annual Model'!H50+$C84*Assumptions!$B$17*12*'Annual Model'!H10*(1-Assumptions!G$47-Assumptions!G$48-Assumptions!G$49-Assumptions!G$50)*(1-Assumptions!$B$56) -> 1270897.6 | M84: ='Annual Model'!C50+$C84*'Annual Model'!C14*12*'Annual Model'!C10*(1-Assumptions!C$47-Assumptions!C$48-Assumptions!C$49-Assumptions!C$50)*(1-Assumptions!$B$56) -> 881129.43
A85: 190 | B85: 0.0675 | C85: =A85-Assumptions!$B$39 -> 23.686441 | D85: =MIN(Returns!$C$22*Assumptions!$B$70,M85/Assumptions!$B$71,M85/(Assumptions!$B$72*Assumptions!$B$73)) -> 11014118 | E85: =-((Returns!$C$13-Returns!$C$27*Assumptions!$B$74)+D85*Assumptions!$B$74-D85) -> -6680543.3 | F85: ='Annual Model'!C59+$C85*'Annual Model'!C14*12*'Annual Model'!C10*(1-Assumptions!C$47-Assumptions!C$48-Assumptions!C$49-Assumptions!C$50)*(1-Assumptions!$B$56)-$D85*Assumptions!$B$73 -> 201403.53 | G85: ='Annual Model'!D59+$C85*'Annual Model'!D14*12*'Annual Model'!D10*(1-Assumptions!D$47-Assumptions!D$48-Assumptions!D$49-Assumptions!D$50)*(1-Assumptions!$B$56)-$D85*Assumptions!$B$73 -> 341704.21 | H85: ='Annual Model'!E59+$C85*'Annual Model'!E14*12*'Annual Model'!E10*(1-Assumptions!E$47-Assumptions!E$48-Assumptions!E$49-Assumptions!E$50)*(1-Assumptions!$B$56)-$D85*Assumptions!$B$73 -> 485638.41 | I85: ='Annual Model'!F59+$C85*'Annual Model'!F14*12*'Annual Model'!F10*(1-Assumptions!F$47-Assumptions!F$48-Assumptions!F$49-Assumptions!F$50)*(1-Assumptions!$B$56)-$D85*Assumptions!$B$73 -> 530798.17 | J85: ='Annual Model'!G59+$C85*'Annual Model'!G14*12*'Annual Model'!G10*(1-Assumptions!G$47-Assumptions!G$48-Assumptions!G$49-Assumptions!G$50)*(1-Assumptions!$B$56)-$D85*Assumptions!$B$73+(L85/B85)*(1-Assumptions!$B$13)-$D85 -> 8089936.1 | K85: =IRR(E85:J85) -> 0.082821959 | L85: ='Annual Model'!H50+$C85*Assumptions!$B$17*12*'Annual Model'!H10*(1-Assumptions!G$47-Assumptions!G$48-Assumptions!G$49-Assumptions!G$50)*(1-Assumptions!$B$56) -> 1270897.6 | M85: ='Annual Model'!C50+$C85*'Annual Model'!C14*12*'Annual Model'!C10*(1-Assumptions!C$47-Assumptions!C$48-Assumptions!C$49-Assumptions!C$50)*(1-Assumptions!$B$56) -> 881129.43
A86: 190 | B86: 0.07 | C86: =A86-Assumptions!$B$39 -> 23.686441 | D86: =MIN(Returns!$C$22*Assumptions!$B$70,M86/Assumptions!$B$71,M86/(Assumptions!$B$72*Assumptions!$B$73)) -> 11014118 | E86: =-((Returns!$C$13-Returns!$C$27*Assumptions!$B$74)+D86*Assumptions!$B$74-D86) -> -6680543.3 | F86: ='Annual Model'!C59+$C86*'Annual Model'!C14*12*'Annual Model'!C10*(1-Assumptions!C$47-Assumptions!C$48-Assumptions!C$49-Assumptions!C$50)*(1-Assumptions!$B$56)-$D86*Assumptions!$B$73 -> 201403.53 | G86: ='Annual Model'!D59+$C86*'Annual Model'!D14*12*'Annual Model'!D10*(1-Assumptions!D$47-Assumptions!D$48-Assumptions!D$49-Assumptions!D$50)*(1-Assumptions!$B$56)-$D86*Assumptions!$B$73 -> 341704.21 | H86: ='Annual Model'!E59+$C86*'Annual Model'!E14*12*'Annual Model'!E10*(1-Assumptions!E$47-Assumptions!E$48-Assumptions!E$49-Assumptions!E$50)*(1-Assumptions!$B$56)-$D86*Assumptions!$B$73 -> 485638.41 | I86: ='Annual Model'!F59+$C86*'Annual Model'!F14*12*'Annual Model'!F10*(1-Assumptions!F$47-Assumptions!F$48-Assumptions!F$49-Assumptions!F$50)*(1-Assumptions!$B$56)-$D86*Assumptions!$B$73 -> 530798.17 | J86: ='Annual Model'!G59+$C86*'Annual Model'!G14*12*'Annual Model'!G10*(1-Assumptions!G$47-Assumptions!G$48-Assumptions!G$49-Assumptions!G$50)*(1-Assumptions!$B$56)-$D86*Assumptions!$B$73+(L86/B86)*(1-Assumptions!$B$13)-$D86 -> 7427590 | K86: =IRR(E86:J86) -> 0.066590342 | L86: ='Annual Model'!H50+$C86*Assumptions!$B$17*12*'Annual Model'!H10*(1-Assumptions!G$47-Assumptions!G$48-Assumptions!G$49-Assumptions!G$50)*(1-Assumptions!$B$56) -> 1270897.6 | M86: ='Annual Model'!C50+$C86*'Annual Model'!C14*12*'Annual Model'!C10*(1-Assumptions!C$47-Assumptions!C$48-Assumptions!C$49-Assumptions!C$50)*(1-Assumptions!$B$56) -> 881129.43
A87: 190 | B87: 0.075 | C87: =A87-Assumptions!$B$39 -> 23.686441 | D87: =MIN(Returns!$C$22*Assumptions!$B$70,M87/Assumptions!$B$71,M87/(Assumptions!$B$72*Assumptions!$B$73)) -> 11014118 | E87: =-((Returns!$C$13-Returns!$C$27*Assumptions!$B$74)+D87*Assumptions!$B$74-D87) -> -6680543.3 | F87: ='Annual Model'!C59+$C87*'Annual Model'!C14*12*'Annual Model'!C10*(1-Assumptions!C$47-Assumptions!C$48-Assumptions!C$49-Assumptions!C$50)*(1-Assumptions!$B$56)-$D87*Assumptions!$B$73 -> 201403.53 | G87: ='Annual Model'!D59+$C87*'Annual Model'!D14*12*'Annual Model'!D10*(1-Assumptions!D$47-Assumptions!D$48-Assumptions!D$49-Assumptions!D$50)*(1-Assumptions!$B$56)-$D87*Assumptions!$B$73 -> 341704.21 | H87: ='Annual Model'!E59+$C87*'Annual Model'!E14*12*'Annual Model'!E10*(1-Assumptions!E$47-Assumptions!E$48-Assumptions!E$49-Assumptions!E$50)*(1-Assumptions!$B$56)-$D87*Assumptions!$B$73 -> 485638.41 | I87: ='Annual Model'!F59+$C87*'Annual Model'!F14*12*'Annual Model'!F10*(1-Assumptions!F$47-Assumptions!F$48-Assumptions!F$49-Assumptions!F$50)*(1-Assumptions!$B$56)-$D87*Assumptions!$B$73 -> 530798.17 | J87: ='Annual Model'!G59+$C87*'Annual Model'!G14*12*'Annual Model'!G10*(1-Assumptions!G$47-Assumptions!G$48-Assumptions!G$49-Assumptions!G$50)*(1-Assumptions!$B$56)-$D87*Assumptions!$B$73+(L87/B87)*(1-Assumptions!$B$13)-$D87 -> 6235367.1 | K87: =IRR(E87:J87) -> 0.034440502 | L87: ='Annual Model'!H50+$C87*Assumptions!$B$17*12*'Annual Model'!H10*(1-Assumptions!G$47-Assumptions!G$48-Assumptions!G$49-Assumptions!G$50)*(1-Assumptions!$B$56) -> 1270897.6 | M87: ='Annual Model'!C50+$C87*'Annual Model'!C14*12*'Annual Model'!C10*(1-Assumptions!C$47-Assumptions!C$48-Assumptions!C$49-Assumptions!C$50)*(1-Assumptions!$B$56) -> 881129.43
A89: GRID 2 — LEVERED IRR: RENOVATION PREMIUM × EXIT CAP (at the base purchase price)
A90: Blended Premium \ Exit Cap | B90: 0.06 | C90: 0.065 | D90: 0.0675 | E90: 0.07 | F90: 0.075 | G90: Return on Cost
A91: 125 | B91: =K68 -> 0.090672814 | C91: =K69 -> 0.055365965 | D91: =K70 -> 0.037945297 | E91: =K71 -> 0.020591232 | F91: =K72 -> -0.014189626 | G91: =A91*12/Assumptions!$B$35 -> 0.09521248
A92: 150 | B92: =K73 -> 0.10731762 | C92: =K74 -> 0.072757539 | D92: =K75 -> 0.055771496 | E92: =K76 -> 0.038900049 | F92: =K77 -> 0.0052576487 | G92: =A92*12/Assumptions!$B$35 -> 0.11425498
A93: 166 | B93: =K78 -> 0.11766568 | C93: =K79 -> 0.083532315 | D93: =K80 -> 0.066793459 | E93: =K81 -> 0.050195389 | F93: =K82 -> 0.017192972 | G93: =A93*12/Assumptions!$B$35 -> 0.12644217
A94: 190 | B94: =K83 -> 0.1327857 | C94: =K84 -> 0.099228385 | D94: =K85 -> 0.082821959 | E94: =K86 -> 0.066590342 | F94: =K87 -> 0.034440502 | G94: =A94*12/Assumptions!$B$35 -> 0.14472297
A96: Grid 2 holds the purchase price at the base case and flexes the blended renovation premium. $125 is CBRE's light-touch scope plus a partial W/D benefit; $166 is our base case; $190 approximates achieving the top of the submarket comp range. Even at $190 the deal does not clear a value-add hurdle at the base price — the constraint is basis, not the renovation.

Sheet DD Questions
A1: CHATEAU IN THE WOODS | 4020 Monaco Drive, Indianapolis, IN 46220 | 118 Units
A2: Due Diligence & Seller / Broker Question List — with the answer assumed in this model
A3: Blue = hardcoded input / lever · Black = formula · Green = link to another sheet · Yellow fill = key assumption
A5: # | B5: Category | C5: Question for the seller / broker | D5: Reasonable answer assumed in this model | E5: Priority
B6: 1. RENT ROLL, LEASES & LEASING PERFORMANCE
A7: 1 | B7: Rent Roll, Leases & Leasing Performance | C7: Please provide the complete lease file for all 118 units: executed leases, every addendum, renewal notices, and the current concession log by unit. | D7: No unusual concessions or side agreements. Concessions underwritten at 0.75% of gross potential rent in Years 1-2, falling to 0.50%. | E7: High
A8: 2 | B8: Rent Roll, Leases & Leasing Performance | C8: The 07/01/2026 rent roll shows 4 units in Evict and 8 in Notice-Unrented. For each, what is the status of the action, what is owed, and when is possession expected? | D8: All four evictions resolve within 90 days of closing and the units are re-leased at renovated rents. The cost sits inside the 1.50% Year-1 bad debt allowance. | E8: High
A9: 3 | B9: Rent Roll, Leases & Leasing Performance | C9: Unit 4017-C carries a lease rent of $821.03 against a $1,250 market rent and is on notice. Is that a concession, an employee unit, a subsidy, or a partial-month proration? | D9: A proration or one-off concession rather than a genuine below-market lease. Modelled at market rent on turn. | E9: Medium
A10: 4 | B10: Rent Roll, Leases & Leasing Performance | C10: Please provide 24 months of leasing traffic, tour-to-lease conversion, renewal rate, average renewal increase achieved, and the ILS source report. | D10: Renewal rate of 55-60%, producing roughly 55-60 natural turns a year. This is what makes a 5-unit-per-month renovation pace achievable without forcing residents out. | E10: High
A11: 5 | B11: Rent Roll, Leases & Leasing Performance | C11: Which units are on month-to-month tenancies and what is being charged? The OM cites a $100/month month-to-month fee that the T-12 does not separately disclose. | D11: A small number of month-to-month units; the premium income sits inside miscellaneous other income. | E11: Low
A12: 6 | B12: Rent Roll, Leases & Leasing Performance | C12: Units 4005-D, 4029-F, 4013-A, 4017-E and 4034-E show a lease-from date but no lease-to date. Are these expired leases holding over? | D12: Holdover on month-to-month, re-leased at market rent when renovated. | E12: Medium
A13: 7 | B13: Rent Roll, Leases & Leasing Performance | C13: Please confirm there are no affordable, Section 8, HAP, LIHTC or other regulatory restrictions on any unit. | D13: The property is entirely market rate with no restrictions. | E13: High
B14: 2. WASHER / DRYER INVENTORY — THE LARGEST DATA CONFLICT IN THE PACKAGE
A15: 8 | B15: Washer / Dryer Inventory — the largest data conflict in the package | C15: Please confirm, unit by unit, which units contain a washer and dryer, which have hookups only, and which have neither. The OM states that 78 of 118 units have a full-size or stackable washer/dryer, then lists only 53 side-by-side plus 1 stackable, and its own floor-plan and building-mix schedules foot to 54. | D15: The rent roll governs per the case data hierarchy: 53 units have machines (Rhone 15, Roman 4, Cabernet 4, Brunswick 30) and 65 require both hookups and machines at $5,000 each. Every 10 units of error moves the capital budget by $50,000. | E15: High
A16: 9 | B16: Washer / Dryer Inventory — the largest data conflict in the package | C16: For the 65 units without laundry, please provide plumbing and electrical capacity confirmation: panel amperage, riser and stack capacity, and whether a dedicated 240V circuit and a drain can be run inside the $5,000 allowance. | D16: The $5,000 per unit prescribed by the case covers hookups plus machines with no panel or riser upgrade required. A riser or panel constraint would be a material change. | E16: High
A17: 10 | B17: Washer / Dryer Inventory — the largest data conflict in the package | C17: The OM states the Verdun 2-bed / 2-bath layout supports adding machines in the bedroom closet. Has an architect or general contractor confirmed this for all 25 Verdun units, and does it reduce the closet below any code or marketing minimum? | D17: All 25 Verdun units accommodate stacked machines without losing a required closet. CBRE's own forecast assumes the same. | E17: High
A18: 11 | B18: Washer / Dryer Inventory — the largest data conflict in the package | C18: The OM identifies unit 4017-D as a Bordeaux with stackable machines at a $1,307 market rent, but the rent roll shows all 25 Bordeaux units at $1,260 in a single unit type. Which is correct? | D18: The rent roll governs, so 4017-D is underwritten as needing the $5,000 addition. Conservative by $5,000. | E18: Low
A19: 12 | B19: Washer / Dryer Inventory — the largest data conflict in the package | C19: What was the previous washer/dryer rental programme, why was it discontinued, and are there surviving vendor contracts or leased equipment on site? | D19: No surviving equipment lease. The 15 laundry centres are owned and can be repurposed or removed once in-unit laundry is universal. | E19: Medium
A20: 13 | B20: Washer / Dryer Inventory — the largest data conflict in the package | C20: Once every unit has in-unit laundry, is there a use or conversion opportunity for the 15 laundry centres (3 per building)? | D20: No value underwritten. Any storage or unit conversion would be incremental upside. | E20: Low
B21: 3. RENOVATION SCOPE, COST & RENT PREMIUM
A22: 14 | B22: Renovation Scope, Cost & Rent Premium | C22: Please provide the scope, unit-level cost detail and before/after rents for the 2006 rehabilitation of 116 units, and identify the two units never rehabbed. | D22: The 2006 scope was cabinets, counters and flooring. Those components are now 20 years old, which is why every unit reads as classic against today's market. The two un-rehabbed units require full scope. | E22: High
A23: 15 | B23: Renovation Scope, Cost & Rent Premium | C23: Have any units been renovated to a current standard in the last three years? If so, what premium was achieved, over what lease-up period, and at what cost? | D23: No recent renovations, so there is no in-place proof of premium. This is the single largest unproven assumption in the model and the reason premium is sensitised from $125 to $190 per month. | E23: High
A24: 16 | B24: Renovation Scope, Cost & Rent Premium | C24: Please provide two or three general contractor bids on our scope for a representative Abbey, Verdun and Brunswick unit, inclusive of the washer/dryer addition. | D24: $13,000 per unit interior plus $5,000 for the laundry addition, a $15,754 blended cost. A $2,000 per unit miss is $236,000 of capital. | E24: High
A25: 17 | B25: Renovation Scope, Cost & Rent Premium | C25: What is realistic turn time from vacate to rent-ready under our scope, and can the site sustain five units a month with the current team? | D25: 14 days of incremental downtime beyond a normal turn. We fund a second maintenance technician in payroll. | E25: Medium
A26: 18 | B26: Renovation Scope, Cost & Rent Premium | C26: Are there asbestos, lead paint or mould surveys? A 1974 building rehabbed in 2006 may have regulated materials behind cabinets and in flooring mastic. | D26: No abatement beyond what the 8% contingency absorbs. A material finding would change the programme cost and pace. | E26: High
A27: 19 | B27: Renovation Scope, Cost & Rent Premium | C27: Do the units have individual electrical panels sized for modern appliance loads, and is there capacity for in-unit laundry plus upgraded lighting? | D27: Cutler-Hammer breaker boxes with adequate capacity, per the OM systems schedule. | E27: Medium
B28: 4. PHYSICAL CONDITION & CAPITAL REQUIREMENTS
A29: 20 | B29: Physical Condition & Capital Requirements | C29: Please provide the most recent property condition assessment, all roof inspection reports, and the roof warranty documentation for the 2020 and 2024 replacements. | D29: 3.5 of the 5 rubber roofs are original and require replacement at roughly $103,000 each. Underwritten at $360,000 phased over Years 2-4. Building 4 cost $90,000 in 2020 and half of Building 5 cost $54,507 in 2024. | E29: High
A30: 21 | B30: Physical Condition & Capital Requirements | C30: The OM identifies 37 below-grade units with patio drains and 4 sump pumps needed. Is there any history of water intrusion, insurance claims, mould remediation or resident complaints in those units? | D30: No systemic intrusion; $40,000 resolves the drains and pumps. A systemic finding would be a material adverse item and would change the recommendation. | E30: High
A31: 22 | B31: Physical Condition & Capital Requirements | C31: What is the remaining useful life of the central gas water heaters and the 8 individual electric units? The T-12 shows $29,053 of water heater replacement in just two months. | D31: Ongoing replacement runs through the $300 per unit replacement reserve. A full central plant replacement is not underwritten. | E31: High
A32: 23 | B32: Physical Condition & Capital Requirements | C32: Please provide a unit-level inventory with the age and condition of the individual gas furnaces and condensing units. | D32: Staggered ages with replacement funded through the reserve; $3,946 of HVAC replacement appears in the T-12. | E32: Medium
A33: 24 | B33: Physical Condition & Capital Requirements | C33: Windows and sliding patio doors are original aluminium sliders. Please provide any quote for full replacement against the current practice of replacing fogged glass on turns. | D33: Glass replacement on turns at $150,000 across three years, not full window replacement. | E33: Medium
A34: 25 | B34: Physical Condition & Capital Requirements | C34: Please provide the paving assessment and any quote for the parking and carport areas, plus the warranties on the 2022 pool deck and the 2020 Hardie siding and gutter work. | D34: $150,000 for patch, sealcoat and stripe. The envelope and pool deck require no capital during the hold. | E34: Medium
A35: 26 | B35: Physical Condition & Capital Requirements | C35: Is the property fully separately metered for electricity, and are there master-metered obligations beyond gas and water/sewer? | D35: Electricity is individually metered and resident-paid, per the OM utility schedule. | E35: Low
A36: 27 | B36: Physical Condition & Capital Requirements | C36: Please provide the elevator, boiler, fire suppression and life-safety inspection certificates, and the status of the building entry systems the OM flags for upgrade. | D36: All current. $60,000 underwritten for entry system upgrades across the 20 building entries. | E36: Medium
B37: 5. FINANCIAL STATEMENTS & OPERATIONS
A38: 28 | B38: Financial Statements & Operations | C38: Please provide 24 months of monthly general ledger detail, monthly bank statements, and an accounts receivable ageing by unit. | D38: The T-12 provided is complete and accrual-accurate. The AR ageing supports the 1.50% Year-1 bad debt allowance. | E38: High
A39: 29 | B39: Financial Statements & Operations | C39: Bad debt: $28,229 was written off against $19,050 collected over the T-12, and January 2026 alone was $5,670. Please explain the trend and describe the current collections process. | D39: Deterioration is driven by the four evictions in process and normalises as the resident profile improves post-renovation. Underwritten at 1.50% falling to 1.00% of gross potential rent. | E39: High
A40: 30 | B40: Financial Statements & Operations | C40: General and administrative expense carries $17,528 of legal and $14,730 of tax and audit fees concentrated in December 2025 and January 2026. Are these transaction costs that should be excluded from a run-rate? | D40: Sale-related and non-recurring. Underwritten at $50,000 against $62,887 in the T-12 and CBRE's $42,209 forecast. | E40: Medium
A41: 31 | B41: Financial Statements & Operations | C41: Please provide the Comcast bulk internet contract: the 7-year term, the escalator, the stabilised per-unit cost, and confirmation of the $49 resident charge and its billing mechanics. | D41: $27.95 per unit per month stabilised, escalating 3%, billed to residents at $49. The T-12 captures only $11,068 of a ramping contract against $39,577 stabilised — understating this line is the easiest way to overstate NOI on this deal. | E41: High
A42: 32 | B42: Financial Statements & Operations | C42: Please provide the valet trash contract, its start date, per-unit cost and term, and confirm what share of residents are currently being charged the $25. | D42: The property begins paying the contractor in January 2026 and the charge is recoverable from all residents on renewal. Ramped at 75% in Year 1 to 100% by Year 3. | E42: High
A43: 33 | B43: Financial Statements & Operations | C43: What portion of the T-12 'Utility Fees' line of $97,812 is water and sewer recovery versus valet trash, and what is the actual recovery ratio on water and sewer usage? | D43: 85% water and sewer recovery with valet trash charged separately, consistent with CBRE's own restatement. Historical recovery has ranged from 78% to 128%. | E43: High
A44: 34 | B44: Financial Statements & Operations | C44: Please provide the payroll register and benefits detail by position, and confirm which costs are reimbursed by the manager versus paid directly. | D44: $235,000 in Year 1 for a manager, part-time leasing consultant, maintenance supervisor and one technician, growing 3.5%. | E44: Medium
A45: 35 | B45: Financial Statements & Operations | C45: Is the current property management agreement assumable, and what is the fee and any termination cost? | D45: Terminable at closing. 4.0% of effective gross revenue going forward against an effective 3.5% in the T-12. | E45: Low
A46: 36 | B46: Financial Statements & Operations | C46: Please provide the ResMan chart of accounts and confirm the accrual policy for real estate taxes; the October 2025 entry of $17,958 appears to be a catch-up. | D46: An accrual true-up rather than a rate change. Year-1 taxes underwritten at $140,000. | E46: Medium
A47: 37 | B47: Financial Statements & Operations | C47: Storage: only 5 of 23 units are rented at $15-20. Is there a reason demand is so low, and is $25 achievable? | D47: No structural constraint. Underwritten at 12 units rented at $25, or $3,600 a year against $141 actual. | E47: Low
A48: 38 | B48: Financial Statements & Operations | C48: The carport income of $16,197 implies roughly 54 of 74 carports rented at $25. What drives the vacancy, and is $35-40 achievable post-renovation? | D48: Held at the T-12 actual with no rate increase underwritten. Any increase is upside. | E48: Low
B49: 6. REAL ESTATE TAXES — THE LARGEST EXPENSE JUDGEMENT
A50: 39 | B50: Real Estate Taxes — the largest expense judgement | C50: Please provide the last three Form 11A reassessment notices, the current tax bills, and any pending appeal or settlement. | D50: The 2025 assessed value of $5,547,800 and the 2.539% rate are correct and no appeal is pending. | E50: High
A51: 40 | B51: Real Estate Taxes — the largest expense judgement | C51: Has the seller obtained guidance from the Marion County Assessor on how a sale at this price will be treated, given that Indiana values apartments at the lowest of the income, market and cost approaches? | D51: The income approach governs, so assessed value tracks NOI rather than the sale price. Taxes are stepped from $140,000 in Year 1 to $210,000 in Year 5, roughly 10% a year. If assessed value instead moved to the 69% of sale price the OM's own comp study shows, the tax bill would rise about $110,000 a year and cost roughly $1.6mm of value. | E51: High
A52: 41 | B52: Real Estate Taxes — the largest expense judgement | C52: Please confirm the SB-1 deduction schedule as it applies to this parcel, and the referendum rate applicable in taxing district 800. | D52: CBRE's SB-1 forecast is correct: a 6% assessed value deduction for taxes payable 2026 rising to 33.4% by 2031, taxed at the lower of the actual rate or the 2% cap plus referendum. | E52: High
A53: 42 | B53: Real Estate Taxes — the largest expense judgement | C53: What is the storm water fee and is it assessed separately from the real estate tax bill? | D53: $2,966 in 2026 growing 5% a year, included inside the tax line. | E53: Low
A54: 43 | B54: Real Estate Taxes — the largest expense judgement | C54: Are there personal property taxes, and does the SB-1 personal property deduction eliminate the $4,110 assessed in 2025? | D54: Eliminated under the $1mm deduction for taxes payable 2026. Nothing underwritten. | E54: Low
B55: 7. INSURANCE & RISK
A56: 44 | B56: Insurance & Risk | C56: Please provide five years of loss runs, the current policy with limits and deductibles, and the most recent insurance appraisal or replacement-cost estimate. | D56: No material loss history. $95,000 in Year 1 ($805 per unit) growing 5%, against $94,611 in the T-12 and CBRE's $88,326 forecast. | E56: High
A57: 45 | B57: Insurance & Risk | C57: Are there open or threatened claims, habitability complaints, fair housing matters, code violations or litigation involving the property or its management? | D57: None. No litigation reserve is underwritten. | E57: High
A58: 46 | B58: Insurance & Risk | C58: Please confirm the flood determination. The OM cites Zone X on panel 18097C0151G, but 37 units are below grade. | D58: Zone X confirmed and no flood insurance required. The below-grade units are a drainage matter, not a flood zone matter. | E58: Medium
A59: 47 | B59: Insurance & Risk | C59: Please provide any environmental site assessment (Phase I, and Phase II if one exists), including any underground storage tank history. | D59: Clean Phase I with no recognised environmental conditions. | E59: High
B60: 8. MARKET, COMPARABLES & THE RENT THESIS
